Workbook

Sheet README
A1: SIMM-style initial margin workbook (RatesFX: IR and FX delta, vega, curvature) with schedule IM, backtests and attribution.
A3: ALL DATA IS SYNTHETIC. This is a SIMM-style implementation for learning and validation practice. It is not ISDA licensed, not ISDA certified and makes no compliance claim. ISDA SIMM is a trademark of ISDA.
A5: How to use: change a value on Inputs (parameter set, exception probability, Basel probabilities) or a typed CRIF amount on Sensitivities, a notional or PV on Portfolio, or a loss or forecast on Backtest, and all live sheets recalculate. Checks!B3 equals 1 when every live cell matches the Python reference within tolerance (the references on Python_Ref belong to the shipped inputs, so Checks will show 0 once you change an input; that is expected).
A7: Sheets: Inputs and Parameters (typed, with provenance), Portfolio, Sensitivities (typed CRIF plus helper columns and closed-form Bachelier and Garman-Kohlhagen checks), SIMM_Delta, SIMM_Vega, SIMM_Curvature, SIMM_Total, Schedule_IM, Backtest, Attribution (live formulas), Checks, Conclusions (static text), Python_Ref (typed Python results), Parameters_Reg (typed schedule rates, weights and BCBS 22 Table 2).
A9: What is replicated in cell formulas: net sensitivities, risk weights by lookup, concentration risk CR, weighted sensitivities, 12x12 tenor correlation grids, K and S per currency, inter-currency aggregation with gamma and g_bc, FX sigma_SIMM, FX delta and vega with concentration scaling, curvature scale factors, theta, lambda, HVR scale, risk class and RatesFX aggregation, schedule IM, Kupiec, Christoffersen, Basel zone, Shapley and bridge.
A11: LIMITS, stated plainly. (1) The CRIF is typed from Python: trade pricing and the bump and reprice sensitivities are not replicated in Excel; only one swaption (Bachelier) and one FX option (Garman-Kohlhagen) are repriced in closed form as spot checks. (2) The sample CRIF has no inflation or cross-currency basis rows and a single OIS sub-curve, so those SIMM branches (inflation risk weight, basis correlation of minus 1 percent, sub-curve phi) are not built into the formulas. (3) The 16 subset IMs of the attribution are typed from Python because each needs a full SIMM run on a different market or portfolio. The rates, FX and vol split of the market step is typed for the same reason. (4) The Backtest series are typed because the VaR models need the full simulated history. (5) The workbook was recalculated and verified in LibreOffice only. It uses functions that Excel 2016 also has, but it was not opened in Excel.
A13: Shipped inputs: parameter set 2.8+2512, calculation currency USD, p = 0.010000000000000009.

Sheet Inputs
A1: Inputs (typed). Change a value here and the live sheets recalculate.
A4: SIMM parameter set | B4: 2.8+2512
A5: Calculation currency | B5: USD
A6: Exception probability p (1 minus confidence) | B6: 0.01
A7: Basel yellow zone cumulative probability | B7: 0.95
A8: Basel red zone cumulative probability | B8: 0.9999
A9: USD per million (thresholds are in USD mm) | B9: 1000000
A10: Basel window (observations) | B10: 250
A12: Lists used as labels by the live sheets
A13: IR currencies | B13: USD | C13: EUR | D13: GBP | E13: JPY | F13: MXN
A14: Tenor labels | B14: 2w | C14: 1m | D14: 3m | E14: 6m | F14: 1y | G14: 2y | H14: 3y | I14: 5y | J14: 10y | K14: 15y | L14: 20y | M14: 30y
A15: Tenor years | B15: 0.038356164 | C15: 0.083333333 | D15: 0.25 | E15: 0.5 | F15: 1 | G15: 2 | H15: 3 | I15: 5 | J15: 10 | K15: 15 | L15: 20 | M15: 30
A16: FX currencies | B16: EUR | C16: GBP | D16: JPY | E16: MXN
A17: FX pairs | B17: EURUSD | C17: GBPUSD | D17: USDJPY | E17: USDMXN
A19: Currency | B19: USD per unit (schedule IM notionals)
A20: USD | B20: 1
A21: EUR | B21: 1.08
A22: GBP | B22: 1.27
A23: JPY | B23: 0.0067567568
A24: MXN | B24: 0.055555556
A27: Case | B27: base

Sheet Parameters
A1: SIMM-style parameters (typed from data/parameters/simm_parameters.csv with provenance). Column A is the lookup key.
A4: key | B4: param_set | C4: risk_class | D4: param_name | E4: key1 | F4: key2 | G4: value | H4: unit | I4: source_doc | J4: version | K4: effective_date | L4: section | M4: paragraph | N4: table | O4: pdf_page | P4: source_url | Q4: retrieved_on | R4: source_sha256 | S4: verification_status | T4: verification_method
A5: =B5&"|"&C5&"|"&D5&"|"&E5&"|"&F5 -> 2.8+2512|IR|delta_rw|regular|2w | B5: 2.8+2512 | C5: IR | D5: delta_rw | E5: regular | F5: 2w | G5: 107 | H5: multiplier of per-1bp sensitivity | I5: ISDA SIMM Methodology v2.8+2512 (based on v2.8+2512.2, 13 May 2026) | J5: 2.8+2512 | K5: 2026-07-11 | L5: D.1 | M5: 33 | N5: Table 1 risk weights per vertex | O5: 14 | P5: https://www.isda.org/a/hhkiE/ISDA-SIMM_v2.82512_PUBLIC.pdf | Q5: 2026-10-02 | R5: 8484d3de7dcb5280b6ad6458d051c50f8ccc3370bc279ae1c47a7bccb8064636 | S5: VERIFIED_PRIMARY | T5: two extractors agree (PyMuPDF, markitdown; sequence) + page image check
A6: =B6&"|"&C6&"|"&D6&"|"&E6&"|"&F6 -> 2.8+2512|IR|delta_rw|regular|1m | B6: 2.8+2512 | C6: IR | D6: delta_rw | E6: regular | F6: 1m | G6: 101 | H6: multiplier of per-1bp sensitivity | I6: ISDA SIMM Methodology v2.8+2512 (based on v2.8+2512.2, 13 May 2026) | J6: 2.8+2512 | K6: 2026-07-11 | L6: D.1 | M6: 33 | N6: Table 1 risk weights per vertex | O6: 14 | P6: https://www.isda.org/a/hhkiE/ISDA-SIMM_v2.82512_PUBLIC.pdf | Q6: 2026-10-02 | R6: 8484d3de7dcb5280b6ad6458d051c50f8ccc3370bc279ae1c47a7bccb8064636 | S6: VERIFIED_PRIMARY | T6: two extractors agree (PyMuPDF, markitdown; sequence) + page image check
A7: =B7&"|"&C7&"|"&D7&"|"&E7&"|"&F7 -> 2.8+2512|IR|delta_rw|regular|3m | B7: 2.8+2512 | C7: IR | D7: delta_rw | E7: regular | F7: 3m | G7: 90 | H7: multiplier of per-1bp sensitivity | I7: ISDA SIMM Methodology v2.8+2512 (based on v2.8+2512.2, 13 May 2026) | J7: 2.8+2512 | K7: 2026-07-11 | L7: D.1 | M7: 33 | N7: Table 1 risk weights per vertex | O7: 14 | P7: https://www.isda.org/a/hhkiE/ISDA-SIMM_v2.82512_PUBLIC.pdf | Q7: 2026-10-02 | R7: 8484d3de7dcb5280b6ad6458d051c50f8ccc3370bc279ae1c47a7bccb8064636 | S7: VERIFIED_PRIMARY | T7: two extractors agree (PyMuPDF, markitdown; sequence) + page image check
A8: =B8&"|"&C8&"|"&D8&"|"&E8&"|"&F8 -> 2.8+2512|IR|delta_rw|regular|6m | B8: 2.8+2512 | C8: IR | D8: delta_rw | E8: regular | F8: 6m | G8: 69 | H8: multiplier of per-1bp sensitivity | I8: ISDA SIMM Methodology v2.8+2512 (based on v2.8+2512.2, 13 May 2026) | J8: 2.8+2512 | K8: 2026-07-11 | L8: D.1 | M8: 33 | N8: Table 1 risk weights per vertex | O8: 14 | P8: https://www.isda.org/a/hhkiE/ISDA-SIMM_v2.82512_PUBLIC.pdf | Q8: 2026-10-02 | R8: 8484d3de7dcb5280b6ad6458d051c50f8ccc3370bc279ae1c47a7bccb8064636 | S8: VERIFIED_PRIMARY | T8: two extractors agree (PyMuPDF, markitdown; sequence) + page image check
A9: =B9&"|"&C9&"|"&D9&"|"&E9&"|"&F9 -> 2.8+2512|IR|delta_rw|regular|1y | B9: 2.8+2512 | C9: IR | D9: delta_rw | E9: regular | F9: 1y | G9: 68 | H9: multiplier of per-1bp sensitivity | I9: ISDA SIMM Methodology v2.8+2512 (based on v2.8+2512.2, 13 May 2026) | J9: 2.8+2512 | K9: 2026-07-11 | L9: D.1 | M9: 33 | N9: Table 1 risk weights per vertex | O9: 14 | P9: https://www.isda.org/a/hhkiE/ISDA-SIMM_v2.82512_PUBLIC.pdf | Q9: 2026-10-02 | R9: 8484d3de7dcb5280b6ad6458d051c50f8ccc3370bc279ae1c47a7bccb8064636 | S9: VERIFIED_PRIMARY | T9: two extractors agree (PyMuPDF, markitdown; sequence) + page image check
A10: =B10&"|"&C10&"|"&D10&"|"&E10&"|"&F10 -> 2.8+2512|IR|delta_rw|regular|2y | B10: 2.8+2512 | C10: IR | D10: delta_rw | E10: regular | F10: 2y | G10: 69 | H10: multiplier of per-1bp sensitivity | I10: ISDA SIMM Methodology v2.8+2512 (based on v2.8+2512.2, 13 May 2026) | J10: 2.8+2512 | K10: 2026-07-11 | L10: D.1 | M10: 33 | N10: Table 1 risk weights per vertex | O10: 14 | P10: https://www.isda.org/a/hhkiE/ISDA-SIMM_v2.82512_PUBLIC.pdf | Q10: 2026-10-02 | R10: 8484d3de7dcb5280b6ad6458d051c50f8ccc3370bc279ae1c47a7bccb8064636 | S10: VERIFIED_PRIMARY | T10: two extractors agree (PyMuPDF, markitdown; sequence) + page image check
A11: =B11&"|"&C11&"|"&D11&"|"&E11&"|"&F11 -> 2.8+2512|IR|delta_rw|regular|3y | B11: 2.8+2512 | C11: IR | D11: delta_rw | E11: regular | F11: 3y | G11: 66 | H11: multiplier of per-1bp sensitivity | I11: ISDA SIMM Methodology v2.8+2512 (based on v2.8+2512.2, 13 May 2026) | J11: 2.8+2512 | K11: 2026-07-11 | L11: D.1 | M11: 33 | N11: Table 1 risk weights per vertex | O11: 14 | P11: https://www.isda.org/a/hhkiE/ISDA-SIMM_v2.82512_PUBLIC.pdf | Q11: 2026-10-02 | R11: 8484d3de7dcb5280b6ad6458d051c50f8ccc3370bc279ae1c47a7bccb8064636 | S11: VERIFIED_PRIMARY | T11: two extractors agree (PyMuPDF, markitdown; sequence) + page image check
A12: =B12&"|"&C12&"|"&D12&"|"&E12&"|"&F12 -> 2.8+2512|IR|delta_rw|regular|5y | B12: 2.8+2512 | C12: IR | D12: delta_rw | E12: regular | F12: 5y | G12: 61 | H12: multiplier of per-1bp sensitivity | I12: ISDA SIMM Methodology v2.8+2512 (based on v2.8+2512.2, 13 May 2026) | J12: 2.8+2512 | K12: 2026-07-11 | L12: D.1 | M12: 33 | N12: Table 1 risk weights per vertex | O12: 14 | P12: https://www.isda.org/a/hhkiE/ISDA-SIMM_v2.82512_PUBLIC.pdf | Q12: 2026-10-02 | R12: 8484d3de7dcb5280b6ad6458d051c50f8ccc3370bc279ae1c47a7bccb8064636 | S12: VERIFIED_PRIMARY | T12: two extractors agree (PyMuPDF, markitdown; sequence) + page image check
A13: =B13&"|"&C13&"|"&D13&"|"&E13&"|"&F13 -> 2.8+2512|IR|delta_rw|regular|10y | B13: 2.8+2512 | C13: IR | D13: delta_rw | E13: regular | F13: 10y | G13: 60 | H13: multiplier of per-1bp sensitivity | I13: ISDA SIMM Methodology v2.8+2512 (based on v2.8+2512.2, 13 May 2026) | J13: 2.8+2512 | K13: 2026-07-11 | L13: D.1 | M13: 33 | N13: Table 1 risk weights per vertex | O13: 14 | P13: https://www.isda.org/a/hhkiE/ISDA-SIMM_v2.82512_PUBLIC.pdf | Q13: 2026-10-02 | R13: 8484d3de7dcb5280b6ad6458d051c50f8ccc3370bc279ae1c47a7bccb8064636 | S13: VERIFIED_PRIMARY | T13: two extractors agree (PyMuPDF, markitdown; sequence) + page image check
A14: =B14&"|"&C14&"|"&D14&"|"&E14&"|"&F14 -> 2.8+2512|IR|delta_rw|regular|15y | B14: 2.8+2512 | C14: IR | D14: delta_rw | E14: regular | F14: 15y | G14: 58 | H14: multiplier of per-1bp sensitivity | I14: ISDA SIMM Methodology v2.8+2512 (based on v2.8+2512.2, 13 May 2026) | J14: 2.8+2512 | K14: 2026-07-11 | L14: D.1 | M14: 33 | N14: Table 1 risk weights per vertex | O14: 14 | P14: https://www.isda.org/a/hhkiE/ISDA-SIMM_v2.82512_PUBLIC.pdf | Q14: 2026-10-02 | R14: 8484d3de7dcb5280b6ad6458d051c50f8ccc3370bc279ae1c47a7bccb8064636 | S14: VERIFIED_PRIMARY | T14: two extractors agree (PyMuPDF, markitdown; sequence) + page image check
A15: =B15&"|"&C15&"|"&D15&"|"&E15&"|"&F15 -> 2.8+2512|IR|delta_rw|regular|20y | B15: 2.8+2512 | C15: IR | D15: delta_rw | E15: regular | F15: 20y | G15: 58 | H15: multiplier of per-1bp sensitivity | I15: ISDA SIMM Methodology v2.8+2512 (based on v2.8+2512.2, 13 May 2026) | J15: 2.8+2512 | K15: 2026-07-11 | L15: D.1 | M15: 33 | N15: Table 1 risk weights per vertex | O15: 14 | P15: https://www.isda.org/a/hhkiE/ISDA-SIMM_v2.82512_PUBLIC.pdf | Q15: 2026-10-02 | R15: 8484d3de7dcb5280b6ad6458d051c50f8ccc3370bc279ae1c47a7bccb8064636 | S15: VERIFIED_PRIMARY | T15: two extractors agree (PyMuPDF, markitdown; sequence) + page image check
A16: =B16&"|"&C16&"|"&D16&"|"&E16&"|"&F16 -> 2.8+2512|IR|delta_rw|regular|30y | B16: 2.8+2512 | C16: IR | D16: delta_rw | E16: regular | F16: 30y | G16: 66 | H16: multiplier of per-1bp sensitivity | I16: ISDA SIMM Methodology v2.8+2512 (based on v2.8+2512.2, 13 May 2026) | J16: 2.8+2512 | K16: 2026-07-11 | L16: D.1 | M16: 33 | N16: Table 1 risk weights per vertex | O16: 14 | P16: https://www.isda.org/a/hhkiE/ISDA-SIMM_v2.82512_PUBLIC.pdf | Q16: 2026-10-02 | R16: 8484d3de7dcb5280b6ad6458d051c50f8ccc3370bc279ae1c47a7bccb8064636 | S16: VERIFIED_PRIMARY | T16: two extractors agree (PyMuPDF, markitdown; sequence) + page image check
... A40: =B40&"|"&C40&"|"&D40&"|"&E40&"|"&F40 -> 2.8+2512|IR|delta_rw|high|30y | B40: 2.8+2512 | C40: IR | D40: delta_rw | E40: high | F40: 30y | G40: 96 | H40: multiplier of per-1bp sensitivity | I40: ISDA SIMM Methodology v2.8+2512 (based on v2.8+2512.2, 13 May 2026) | J40: 2.8+2512 | K40: 2026-07-11 | L40: D.1 | M40: 33 | N40: Table 3 risk weights per vertex | O40: 14 | P40: https://www.isda.org/a/hhkiE/ISDA-SIMM_v2.82512_PUBLIC.pdf | Q40: 2026-10-02 | R40: 8484d3de7dcb5280b6ad6458d051c50f8ccc3370bc279ae1c47a7bccb8064636 | S40: VERIFIED_PRIMARY | T40: two extractors agree (PyMuPDF, markitdown; sequence) + page image check
A41: =B41&"|"&C41&"|"&D41&"|"&E41&"|"&F41 -> 2.8+2512|IR|delta_rw_inflation|any| | B41: 2.8+2512 | C41: IR | D41: delta_rw_inflation | E41: any | G41: 51 | H41: multiplier of per-1bp sensitivity | I41: ISDA SIMM Methodology v2.8+2512 (based on v2.8+2512.2, 13 May 2026) | J41: 2.8+2512 | K41: 2026-07-11 | L41: D.1 | M41: 33 | N41: text below Table 3 | O41: 14 | P41: https://www.isda.org/a/hhkiE/ISDA-SIMM_v2.82512_PUBLIC.pdf | Q41: 2026-10-02 | R41: 8484d3de7dcb5280b6ad6458d051c50f8ccc3370bc279ae1c47a7bccb8064636 | S41: VERIFIED_PRIMARY | T41: two extractors agree (PyMuPDF, markitdown; sequence) + page image check
A42: =B42&"|"&C42&"|"&D42&"|"&E42&"|"&F42 -> 2.8+2512|IR|delta_rw_xccy_basis|any| | B42: 2.8+2512 | C42: IR | D42: delta_rw_xccy_basis | E42: any | G42: 21 | H42: multiplier of per-1bp sensitivity | I42: ISDA SIMM Methodology v2.8+2512 (based on v2.8+2512.2, 13 May 2026) | J42: 2.8+2512 | K42: 2026-07-11 | L42: D.1 | M42: 33 | N42: text below Table 3 | O42: 14 | P42: https://www.isda.org/a/hhkiE/ISDA-SIMM_v2.82512_PUBLIC.pdf | Q42: 2026-10-02 | R42: 8484d3de7dcb5280b6ad6458d051c50f8ccc3370bc279ae1c47a7bccb8064636 | S42: VERIFIED_PRIMARY | T42: two extractors agree (PyMuPDF, markitdown; sequence) + page image check
A43: =B43&"|"&C43&"|"&D43&"|"&E43&"|"&F43 -> 2.8+2512|IR|hvr|| | B43: 2.8+2512 | C43: IR | D43: hvr | G43: 0.74 | H43: ratio | I43: ISDA SIMM Methodology v2.8+2512 (based on v2.8+2512.2, 13 May 2026) | J43: 2.8+2512 | K43: 2026-07-11 | L43: D.1 | M43: 34 | N43: text of paragraph 34 (no table) | O43: 14 | P43: https://www.isda.org/a/hhkiE/ISDA-SIMM_v2.82512_PUBLIC.pdf | Q43: 2026-10-02 | R43: 8484d3de7dcb5280b6ad6458d051c50f8ccc3370bc279ae1c47a7bccb8064636 | S43: VERIFIED_PRIMARY | T43: two extractors agree (PyMuPDF, markitdown; sequence) + page image check
A44: =B44&"|"&C44&"|"&D44&"|"&E44&"|"&F44 -> 2.8+2512|IR|vega_rw|| | B44: 2.8+2512 | C44: IR | D44: vega_rw | G44: 0.2 | H44: ratio | I44: ISDA SIMM Methodology v2.8+2512 (based on v2.8+2512.2, 13 May 2026) | J44: 2.8+2512 | K44: 2026-07-11 | L44: D.1 | M44: 35 | N44: text of paragraph 35 (no table) | O44: 14 | P44: https://www.isda.org/a/hhkiE/ISDA-SIMM_v2.82512_PUBLIC.pdf | Q44: 2026-10-02 | R44: 8484d3de7dcb5280b6ad6458d051c50f8ccc3370bc279ae1c47a7bccb8064636 | S44: VERIFIED_PRIMARY | T44: two extractors agree (PyMuPDF, markitdown; sequence) + page image check
A45: =B45&"|"&C45&"|"&D45&"|"&E45&"|"&F45 -> 2.8+2512|IR|rw_group_member|regular|USD | B45: 2.8+2512 | C45: IR | D45: rw_group_member | E45: regular | F45: USD | G45: 1 | H45: membership | I45: ISDA SIMM Methodology v2.8+2512 (based on v2.8+2512.2, 13 May 2026) | J45: 2.8+2512 | K45: 2026-07-11 | L45: D.1 | M45: 33(1) | N45: text of paragraph 33(1) (no table) | O45: 14 | P45: https://www.isda.org/a/hhkiE/ISDA-SIMM_v2.82512_PUBLIC.pdf | Q45: 2026-10-02 | R45: 8484d3de7dcb5280b6ad6458d051c50f8ccc3370bc279ae1c47a7bccb8064636 | S45: VERIFIED_PRIMARY | T45: two extractors agree (PyMuPDF, markitdown; sequence) + page image check
A46: =B46&"|"&C46&"|"&D46&"|"&E46&"|"&F46 -> 2.8+2512|IR|rw_group_member|regular|EUR | B46: 2.8+2512 | C46: IR | D46: rw_group_member | E46: regular | F46: EUR | G46: 1 | H46: membership | I46: ISDA SIMM Methodology v2.8+2512 (based on v2.8+2512.2, 13 May 2026) | J46: 2.8+2512 | K46: 2026-07-11 | L46: D.1 | M46: 33(1) | N46: text of paragraph 33(1) (no table) | O46: 14 | P46: https://www.isda.org/a/hhkiE/ISDA-SIMM_v2.82512_PUBLIC.pdf | Q46: 2026-10-02 | R46: 8484d3de7dcb5280b6ad6458d051c50f8ccc3370bc279ae1c47a7bccb8064636 | S46: VERIFIED_PRIMARY | T46: two extractors agree (PyMuPDF, markitdown; sequence) + page image check
A47: =B47&"|"&C47&"|"&D47&"|"&E47&"|"&F47 -> 2.8+2512|IR|rw_group_member|regular|GBP | B47: 2.8+2512 | C47: IR | D47: rw_group_member | E47: regular | F47: GBP | G47: 1 | H47: membership | I47: ISDA SIMM Methodology v2.8+2512 (based on v2.8+2512.2, 13 May 2026) | J47: 2.8+2512 | K47: 2026-07-11 | L47: D.1 | M47: 33(1) | N47: text of paragraph 33(1) (no table) | O47: 14 | P47: https://www.isda.org/a/hhkiE/ISDA-SIMM_v2.82512_PUBLIC.pdf | Q47: 2026-10-02 | R47: 8484d3de7dcb5280b6ad6458d051c50f8ccc3370bc279ae1c47a7bccb8064636 | S47: VERIFIED_PRIMARY | T47: two extractors agree (PyMuPDF, markitdown; sequence) + page image check
A48: =B48&"|"&C48&"|"&D48&"|"&E48&"|"&F48 -> 2.8+2512|IR|rw_group_member|regular|CHF | B48: 2.8+2512 | C48: IR | D48: rw_group_member | E48: regular | F48: CHF | G48: 1 | H48: membership | I48: ISDA SIMM Methodology v2.8+2512 (based on v2.8+2512.2, 13 May 2026) | J48: 2.8+2512 | K48: 2026-07-11 | L48: D.1 | M48: 33(1) | N48: text of paragraph 33(1) (no table) | O48: 14 | P48: https://www.isda.org/a/hhkiE/ISDA-SIMM_v2.82512_PUBLIC.pdf | Q48: 2026-10-02 | R48: 8484d3de7dcb5280b6ad6458d051c50f8ccc3370bc279ae1c47a7bccb8064636 | S48: VERIFIED_PRIMARY | T48: two extractors agree (PyMuPDF, markitdown; sequence) + page image check
A49: =B49&"|"&C49&"|"&D49&"|"&E49&"|"&F49 -> 2.8+2512|IR|rw_group_member|regular|AUD | B49: 2.8+2512 | C49: IR | D49: rw_group_member | E49: regular | F49: AUD | G49: 1 | H49: membership | I49: ISDA SIMM Methodology v2.8+2512 (based on v2.8+2512.2, 13 May 2026) | J49: 2.8+2512 | K49: 2026-07-11 | L49: D.1 | M49: 33(1) | N49: text of paragraph 33(1) (no table) | O49: 14 | P49: https://www.isda.org/a/hhkiE/ISDA-SIMM_v2.82512_PUBLIC.pdf | Q49: 2026-10-02 | R49: 8484d3de7dcb5280b6ad6458d051c50f8ccc3370bc279ae1c47a7bccb8064636 | S49: VERIFIED_PRIMARY | T49: two extractors agree (PyMuPDF, markitdown; sequence) + page image check
A50: =B50&"|"&C50&"|"&D50&"|"&E50&"|"&F50 -> 2.8+2512|IR|rw_group_member|regular|NZD | B50: 2.8+2512 | C50: IR | D50: rw_group_member | E50: regular | F50: NZD | G50: 1 | H50: membership | I50: ISDA SIMM Methodology v2.8+2512 (based on v2.8+2512.2, 13 May 2026) | J50: 2.8+2512 | K50: 2026-07-11 | L50: D.1 | M50: 33(1) | N50: text of paragraph 33(1) (no table) | O50: 14 | P50: https://www.isda.org/a/hhkiE/ISDA-SIMM_v2.82512_PUBLIC.pdf | Q50: 2026-10-02 | R50: 8484d3de7dcb5280b6ad6458d051c50f8ccc3370bc279ae1c47a7bccb8064636 | S50: VERIFIED_PRIMARY | T50: two extractors agree (PyMuPDF, markitdown; sequence) + page image check
A51: =B51&"|"&C51&"|"&D51&"|"&E51&"|"&F51 -> 2.8+2512|IR|rw_group_member|regular|CAD | B51: 2.8+2512 | C51: IR | D51: rw_group_member | E51: regular | F51: CAD | G51: 1 | H51: membership | I51: ISDA SIMM Methodology v2.8+2512 (based on v2.8+2512.2, 13 May 2026) | J51: 2.8+2512 | K51: 2026-07-11 | L51: D.1 | M51: 33(1) | N51: text of paragraph 33(1) (no table) | O51: 14 | P51: https://www.isda.org/a/hhkiE/ISDA-SIMM_v2.82512_PUBLIC.pdf | Q51: 2026-10-02 | R51: 8484d3de7dcb5280b6ad6458d051c50f8ccc3370bc279ae1c47a7bccb8064636 | S51: VERIFIED_PRIMARY | T51: two extractors agree (PyMuPDF, markitdown; sequence) + page image check
A52: =B52&"|"&C52&"|"&D52&"|"&E52&"|"&F52 -> 2.8+2512|IR|rw_group_member|regular|SEK | B52: 2.8+2512 | C52: IR | D52: rw_group_member | E52: regular | F52: SEK | G52: 1 | H52: membership | I52: ISDA SIMM Methodology v2.8+2512 (based on v2.8+2512.2, 13 May 2026) | J52: 2.8+2512 | K52: 2026-07-11 | L52: D.1 | M52: 33(1) | N52: text of paragraph 33(1) (no table) | O52: 14 | P52: https://www.isda.org/a/hhkiE/ISDA-SIMM_v2.82512_PUBLIC.pdf | Q52: 2026-10-02 | R52: 8484d3de7dcb5280b6ad6458d051c50f8ccc3370bc279ae1c47a7bccb8064636 | S52: VERIFIED_PRIMARY | T52: two extractors agree (PyMuPDF, markitdown; sequence) + page image check
A53: =B53&"|"&C53&"|"&D53&"|"&E53&"|"&F53 -> 2.8+2512|IR|rw_group_member|regular|NOK | B53: 2.8+2512 | C53: IR | D53: rw_group_member | E53: regular | F53: NOK | G53: 1 | H53: membership | I53: ISDA SIMM Methodology v2.8+2512 (based on v2.8+2512.2, 13 May 2026) | J53: 2.8+2512 | K53: 2026-07-11 | L53: D.1 | M53: 33(1) | N53: text of paragraph 33(1) (no table) | O53: 14 | P53: https://www.isda.org/a/hhkiE/ISDA-SIMM_v2.82512_PUBLIC.pdf | Q53: 2026-10-02 | R53: 8484d3de7dcb5280b6ad6458d051c50f8ccc3370bc279ae1c47a7bccb8064636 | S53: VERIFIED_PRIMARY | T53: two extractors agree (PyMuPDF, markitdown; sequence) + page image check
A54: =B54&"|"&C54&"|"&D54&"|"&E54&"|"&F54 -> 2.8+2512|IR|rw_group_member|regular|DKK | B54: 2.8+2512 | C54: IR | D54: rw_group_member | E54: regular | F54: DKK | G54: 1 | H54: membership | I54: ISDA SIMM Methodology v2.8+2512 (based on v2.8+2512.2, 13 May 2026) | J54: 2.8+2512 | K54: 2026-07-11 | L54: D.1 | M54: 33(1) | N54: text of paragraph 33(1) (no table) | O54: 14 | P54: https://www.isda.org/a/hhkiE/ISDA-SIMM_v2.82512_PUBLIC.pdf | Q54: 2026-10-02 | R54: 8484d3de7dcb5280b6ad6458d051c50f8ccc3370bc279ae1c47a7bccb8064636 | S54: VERIFIED_PRIMARY | T54: two extractors agree (PyMuPDF, markitdown; sequence) + page image check
A55: =B55&"|"&C55&"|"&D55&"|"&E55&"|"&F55 -> 2.8+2512|IR|rw_group_member|regular|HKD | B55: 2.8+2512 | C55: IR | D55: rw_group_member | E55: regular | F55: HKD | G55: 1 | H55: membership | I55: ISDA SIMM Methodology v2.8+2512 (based on v2.8+2512.2, 13 May 2026) | J55: 2.8+2512 | K55: 2026-07-11 | L55: D.1 | M55: 33(1) | N55: text of paragraph 33(1) (no table) | O55: 14 | P55: https://www.isda.org/a/hhkiE/ISDA-SIMM_v2.82512_PUBLIC.pdf | Q55: 2026-10-02 | R55: 8484d3de7dcb5280b6ad6458d051c50f8ccc3370bc279ae1c47a7bccb8064636 | S55: VERIFIED_PRIMARY | T55: two extractors agree (PyMuPDF, markitdown; sequence) + page image check
A56: =B56&"|"&C56&"|"&D56&"|"&E56&"|"&F56 -> 2.8+2512|IR|rw_group_member|regular|KRW | B56: 2.8+2512 | C56: IR | D56: rw_group_member | E56: regular | F56: KRW | G56: 1 | H56: membership | I56: ISDA SIMM Methodology v2.8+2512 (based on v2.8+2512.2, 13 May 2026) | J56: 2.8+2512 | K56: 2026-07-11 | L56: D.1 | M56: 33(1) | N56: text of paragraph 33(1) (no table) | O56: 14 | P56: https://www.isda.org/a/hhkiE/ISDA-SIMM_v2.82512_PUBLIC.pdf | Q56: 2026-10-02 | R56: 8484d3de7dcb5280b6ad6458d051c50f8ccc3370bc279ae1c47a7bccb8064636 | S56: VERIFIED_PRIMARY | T56: two extractors agree (PyMuPDF, markitdown; sequence) + page image check
... A204: =B204&"|"&C204&"|"&D204&"|"&E204&"|"&F204 -> 2.8+2512|IR|delta_tenor_corr|30y|30y | B204: 2.8+2512 | C204: IR | D204: delta_tenor_corr | E204: 30y | F204: 30y | G204: 1 | H204: fraction | I204: ISDA SIMM Methodology v2.8+2512 (based on v2.8+2512.2, 13 May 2026) | J204: 2.8+2512 | K204: 2026-07-11 | L204: D.2 | M204: 36 | N204: correlation matrix for aggregated weighted sensitivities or risk exposures (row 30y) | O204: 15 | P204: https://www.isda.org/a/hhkiE/ISDA-SIMM_v2.82512_PUBLIC.pdf | Q204: 2026-10-02 | R204: 8484d3de7dcb5280b6ad6458d051c50f8ccc3370bc279ae1c47a7bccb8064636 | S204: VERIFIED_PRIMARY | T204: two extractors agree (PyMuPDF, markitdown; sequence) + page image check; diagonal blank in source, 1 by definition
A205: =B205&"|"&C205&"|"&D205&"|"&E205&"|"&F205 -> 2.8+2512|IR|subcurve_phi|| | B205: 2.8+2512 | C205: IR | D205: subcurve_phi | G205: 0.981 | H205: fraction | I205: ISDA SIMM Methodology v2.8+2512 (based on v2.8+2512.2, 13 May 2026) | J205: 2.8+2512 | K205: 2026-07-11 | L205: D.2 | M205: 36 | N205: text under matrix (to one decimal place) | O205: 15 | P205: https://www.isda.org/a/hhkiE/ISDA-SIMM_v2.82512_PUBLIC.pdf | Q205: 2026-10-02 | R205: 8484d3de7dcb5280b6ad6458d051c50f8ccc3370bc279ae1c47a7bccb8064636 | S205: VERIFIED_PRIMARY | T205: two extractors agree (PyMuPDF, markitdown; sequence) + page image check
A206: =B206&"|"&C206&"|"&D206&"|"&E206&"|"&F206 -> 2.8+2512|IR|inflation_yield_corr|| | B206: 2.8+2512 | C206: IR | D206: inflation_yield_corr | G206: 0.42 | H206: fraction | I206: ISDA SIMM Methodology v2.8+2512 (based on v2.8+2512.2, 13 May 2026) | J206: 2.8+2512 | K206: 2026-07-11 | L206: D.2 | M206: 36 | N206: text under matrix | O206: 15 | P206: https://www.isda.org/a/hhkiE/ISDA-SIMM_v2.82512_PUBLIC.pdf | Q206: 2026-10-02 | R206: 8484d3de7dcb5280b6ad6458d051c50f8ccc3370bc279ae1c47a7bccb8064636 | S206: VERIFIED_PRIMARY | T206: two extractors agree (PyMuPDF, markitdown; sequence) + page image check
A207: =B207&"|"&C207&"|"&D207&"|"&E207&"|"&F207 -> 2.8+2512|IR|inflation_vol_ir_vol_corr|| | B207: 2.8+2512 | C207: IR | D207: inflation_vol_ir_vol_corr | G207: 0.42 | H207: fraction | I207: ISDA SIMM Methodology v2.8+2512 (based on v2.8+2512.2, 13 May 2026) | J207: 2.8+2512 | K207: 2026-07-11 | L207: D.2 | M207: 36 | N207: same sentence: inflation vol vs IR vol | O207: 15 | P207: https://www.isda.org/a/hhkiE/ISDA-SIMM_v2.82512_PUBLIC.pdf | Q207: 2026-10-02 | R207: 8484d3de7dcb5280b6ad6458d051c50f8ccc3370bc279ae1c47a7bccb8064636 | S207: VERIFIED_PRIMARY | T207: two extractors agree (PyMuPDF, markitdown; sequence) + page image check
A208: =B208&"|"&C208&"|"&D208&"|"&E208&"|"&F208 -> 2.8+2512|IR|xccy_basis_yield_corr|| | B208: 2.8+2512 | C208: IR | D208: xccy_basis_yield_corr | G208: -0.01 | H208: fraction | I208: ISDA SIMM Methodology v2.8+2512 (based on v2.8+2512.2, 13 May 2026) | J208: 2.8+2512 | K208: 2026-07-11 | L208: D.2 | M208: 36 | N208: text under matrix (vs yield or inflation, same currency) | O208: 15 | P208: https://www.isda.org/a/hhkiE/ISDA-SIMM_v2.82512_PUBLIC.pdf | Q208: 2026-10-02 | R208: 8484d3de7dcb5280b6ad6458d051c50f8ccc3370bc279ae1c47a7bccb8064636 | S208: VERIFIED_PRIMARY | T208: two extractors agree (PyMuPDF, markitdown; sequence) + page image check
A209: =B209&"|"&C209&"|"&D209&"|"&E209&"|"&F209 -> 2.8+2512|IR|gamma|| | B209: 2.8+2512 | C209: IR | D209: gamma | G209: 0.35 | H209: fraction | I209: ISDA SIMM Methodology v2.8+2512 (based on v2.8+2512.2, 13 May 2026) | J209: 2.8+2512 | K209: 2026-07-11 | L209: D.2 | M209: 37 | N209: text of paragraph 37 (no table) | O209: 15 | P209: https://www.isda.org/a/hhkiE/ISDA-SIMM_v2.82512_PUBLIC.pdf | Q209: 2026-10-02 | R209: 8484d3de7dcb5280b6ad6458d051c50f8ccc3370bc279ae1c47a7bccb8064636 | S209: VERIFIED_PRIMARY | T209: two extractors agree (PyMuPDF, markitdown; sequence) + page image check
A210: =B210&"|"&C210&"|"&D210&"|"&E210&"|"&F210 -> 2.8+2512|IR|delta_ct|high| | B210: 2.8+2512 | C210: IR | D210: delta_ct | E210: high | G210: 71 | H210: USD mm per bp | I210: ISDA SIMM Methodology v2.8+2512 (based on v2.8+2512.2, 13 May 2026) | J210: 2.8+2512 | K210: 2026-07-11 | L210: J.1 | M210: 74 | N210: text of paragraph 74 (no table) | O210: 26 | P210: https://www.isda.org/a/hhkiE/ISDA-SIMM_v2.82512_PUBLIC.pdf | Q210: 2026-10-02 | R210: 8484d3de7dcb5280b6ad6458d051c50f8ccc3370bc279ae1c47a7bccb8064636 | S210: VERIFIED_PRIMARY | T210: two extractors agree (PyMuPDF, markitdown; sequence) + page image check
A211: =B211&"|"&C211&"|"&D211&"|"&E211&"|"&F211 -> 2.8+2512|IR|delta_ct|regular_well_traded| | B211: 2.8+2512 | C211: IR | D211: delta_ct | E211: regular_well_traded | G211: 220 | H211: USD mm per bp | I211: ISDA SIMM Methodology v2.8+2512 (based on v2.8+2512.2, 13 May 2026) | J211: 2.8+2512 | K211: 2026-07-11 | L211: J.1 | M211: 74 | N211: text of paragraph 74 (no table) | O211: 26 | P211: https://www.isda.org/a/hhkiE/ISDA-SIMM_v2.82512_PUBLIC.pdf | Q211: 2026-10-02 | R211: 8484d3de7dcb5280b6ad6458d051c50f8ccc3370bc279ae1c47a7bccb8064636 | S211: VERIFIED_PRIMARY | T211: two extractors agree (PyMuPDF, markitdown; sequence) + page image check
A212: =B212&"|"&C212&"|"&D212&"|"&E212&"|"&F212 -> 2.8+2512|IR|delta_ct|regular_less_well_traded| | B212: 2.8+2512 | C212: IR | D212: delta_ct | E212: regular_less_well_traded | G212: 110 | H212: USD mm per bp | I212: ISDA SIMM Methodology v2.8+2512 (based on v2.8+2512.2, 13 May 2026) | J212: 2.8+2512 | K212: 2026-07-11 | L212: J.1 | M212: 74 | N212: text of paragraph 74 (no table) | O212: 26 | P212: https://www.isda.org/a/hhkiE/ISDA-SIMM_v2.82512_PUBLIC.pdf | Q212: 2026-10-02 | R212: 8484d3de7dcb5280b6ad6458d051c50f8ccc3370bc279ae1c47a7bccb8064636 | S212: VERIFIED_PRIMARY | T212: two extractors agree (PyMuPDF, markitdown; sequence) + page image check
A213: =B213&"|"&C213&"|"&D213&"|"&E213&"|"&F213 -> 2.8+2512|IR|delta_ct|low| | B213: 2.8+2512 | C213: IR | D213: delta_ct | E213: low | G213: 370 | H213: USD mm per bp | I213: ISDA SIMM Methodology v2.8+2512 (based on v2.8+2512.2, 13 May 2026) | J213: 2.8+2512 | K213: 2026-07-11 | L213: J.1 | M213: 74 | N213: text of paragraph 74 (no table) | O213: 26 | P213: https://www.isda.org/a/hhkiE/ISDA-SIMM_v2.82512_PUBLIC.pdf | Q213: 2026-10-02 | R213: 8484d3de7dcb5280b6ad6458d051c50f8ccc3370bc279ae1c47a7bccb8064636 | S213: VERIFIED_PRIMARY | T213: two extractors agree (PyMuPDF, markitdown; sequence) + page image check
A214: =B214&"|"&C214&"|"&D214&"|"&E214&"|"&F214 -> 2.8+2512|IR|vega_ct|high| | B214: 2.8+2512 | C214: IR | D214: vega_ct | E214: high | G214: 160 | H214: USD mm | I214: ISDA SIMM Methodology v2.8+2512 (based on v2.8+2512.2, 13 May 2026) | J214: 2.8+2512 | K214: 2026-07-11 | L214: J.6 | M214: 81 | N214: text of paragraph 81 (no table) | O214: 27 | P214: https://www.isda.org/a/hhkiE/ISDA-SIMM_v2.82512_PUBLIC.pdf | Q214: 2026-10-02 | R214: 8484d3de7dcb5280b6ad6458d051c50f8ccc3370bc279ae1c47a7bccb8064636 | S214: VERIFIED_PRIMARY | T214: two extractors agree (PyMuPDF, markitdown; sequence) + page image check
A215: =B215&"|"&C215&"|"&D215&"|"&E215&"|"&F215 -> 2.8+2512|IR|vega_ct|regular_well_traded| | B215: 2.8+2512 | C215: IR | D215: vega_ct | E215: regular_well_traded | G215: 3800 | H215: USD mm | I215: ISDA SIMM Methodology v2.8+2512 (based on v2.8+2512.2, 13 May 2026) | J215: 2.8+2512 | K215: 2026-07-11 | L215: J.6 | M215: 81 | N215: text of paragraph 81 (no table) | O215: 27 | P215: https://www.isda.org/a/hhkiE/ISDA-SIMM_v2.82512_PUBLIC.pdf | Q215: 2026-10-02 | R215: 8484d3de7dcb5280b6ad6458d051c50f8ccc3370bc279ae1c47a7bccb8064636 | S215: VERIFIED_PRIMARY | T215: two extractors agree (PyMuPDF, markitdown; sequence) + page image check
A216: =B216&"|"&C216&"|"&D216&"|"&E216&"|"&F216 -> 2.8+2512|IR|vega_ct|regular_less_well_traded| | B216: 2.8+2512 | C216: IR | D216: vega_ct | E216: regular_less_well_traded | G216: 520 | H216: USD mm | I216: ISDA SIMM Methodology v2.8+2512 (based on v2.8+2512.2, 13 May 2026) | J216: 2.8+2512 | K216: 2026-07-11 | L216: J.6 | M216: 81 | N216: text of paragraph 81 (no table) | O216: 27 | P216: https://www.isda.org/a/hhkiE/ISDA-SIMM_v2.82512_PUBLIC.pdf | Q216: 2026-10-02 | R216: 8484d3de7dcb5280b6ad6458d051c50f8ccc3370bc279ae1c47a7bccb8064636 | S216: VERIFIED_PRIMARY | T216: two extractors agree (PyMuPDF, markitdown; sequence) + page image check
A217: =B217&"|"&C217&"|"&D217&"|"&E217&"|"&F217 -> 2.8+2512|IR|vega_ct|low| | B217: 2.8+2512 | C217: IR | D217: vega_ct | E217: low | G217: 1100 | H217: USD mm | I217: ISDA SIMM Methodology v2.8+2512 (based on v2.8+2512.2, 13 May 2026) | J217: 2.8+2512 | K217: 2026-07-11 | L217: J.6 | M217: 81 | N217: text of paragraph 81 (no table) | O217: 27 | P217: https://www.isda.org/a/hhkiE/ISDA-SIMM_v2.82512_PUBLIC.pdf | Q217: 2026-10-02 | R217: 8484d3de7dcb5280b6ad6458d051c50f8ccc3370bc279ae1c47a7bccb8064636 | S217: VERIFIED_PRIMARY | T217: two extractors agree (PyMuPDF, markitdown; sequence) + page image check
A218: =B218&"|"&C218&"|"&D218&"|"&E218&"|"&F218 -> 2.8+2512|IR|ct_group_member|regular_well_traded|USD | B218: 2.8+2512 | C218: IR | D218: ct_group_member | E218: regular_well_traded | F218: USD | G218: 1 | H218: membership | I218: ISDA SIMM Methodology v2.8+2512 (based on v2.8+2512.2, 13 May 2026) | J218: 2.8+2512 | K218: 2026-07-11 | L218: J.1 | M218: 75(2) | N218: text of paragraph 75(2) (no table) | O218: 26 | P218: https://www.isda.org/a/hhkiE/ISDA-SIMM_v2.82512_PUBLIC.pdf | Q218: 2026-10-02 | R218: 8484d3de7dcb5280b6ad6458d051c50f8ccc3370bc279ae1c47a7bccb8064636 | S218: VERIFIED_PRIMARY | T218: two extractors agree (PyMuPDF, markitdown; sequence) + page image check
A219: =B219&"|"&C219&"|"&D219&"|"&E219&"|"&F219 -> 2.8+2512|IR|ct_group_member|regular_well_traded|EUR | B219: 2.8+2512 | C219: IR | D219: ct_group_member | E219: regular_well_traded | F219: EUR | G219: 1 | H219: membership | I219: ISDA SIMM Methodology v2.8+2512 (based on v2.8+2512.2, 13 May 2026) | J219: 2.8+2512 | K219: 2026-07-11 | L219: J.1 | M219: 75(2) | N219: text of paragraph 75(2) (no table) | O219: 26 | P219: https://www.isda.org/a/hhkiE/ISDA-SIMM_v2.82512_PUBLIC.pdf | Q219: 2026-10-02 | R219: 8484d3de7dcb5280b6ad6458d051c50f8ccc3370bc279ae1c47a7bccb8064636 | S219: VERIFIED_PRIMARY | T219: two extractors agree (PyMuPDF, markitdown; sequence) + page image check
A220: =B220&"|"&C220&"|"&D220&"|"&E220&"|"&F220 -> 2.8+2512|IR|ct_group_member|regular_well_traded|GBP | B220: 2.8+2512 | C220: IR | D220: ct_group_member | E220: regular_well_traded | F220: GBP | G220: 1 | H220: membership | I220: ISDA SIMM Methodology v2.8+2512 (based on v2.8+2512.2, 13 May 2026) | J220: 2.8+2512 | K220: 2026-07-11 | L220: J.1 | M220: 75(2) | N220: text of paragraph 75(2) (no table) | O220: 26 | P220: https://www.isda.org/a/hhkiE/ISDA-SIMM_v2.82512_PUBLIC.pdf | Q220: 2026-10-02 | R220: 8484d3de7dcb5280b6ad6458d051c50f8ccc3370bc279ae1c47a7bccb8064636 | S220: VERIFIED_PRIMARY | T220: two extractors agree (PyMuPDF, markitdown; sequence) + page image check
A221: =B221&"|"&C221&"|"&D221&"|"&E221&"|"&F221 -> 2.8+2512|IR|ct_group_member|regular_less_well_traded|AUD | B221: 2.8+2512 | C221: IR | D221: ct_group_member | E221: regular_less_well_traded | F221: AUD | G221: 1 | H221: membership | I221: ISDA SIMM Methodology v2.8+2512 (based on v2.8+2512.2, 13 May 2026) | J221: 2.8+2512 | K221: 2026-07-11 | L221: J.1 | M221: 75(3) | N221: text of paragraph 75(3) (no table) | O221: 26 | P221: https://www.isda.org/a/hhkiE/ISDA-SIMM_v2.82512_PUBLIC.pdf | Q221: 2026-10-02 | R221: 8484d3de7dcb5280b6ad6458d051c50f8ccc3370bc279ae1c47a7bccb8064636 | S221: VERIFIED_PRIMARY | T221: two extractors agree (PyMuPDF, markitdown; sequence) + page image check
A222: =B222&"|"&C222&"|"&D222&"|"&E222&"|"&F222 -> 2.8+2512|IR|ct_group_member|regular_less_well_traded|CAD | B222: 2.8+2512 | C222: IR | D222: ct_group_member | E222: regular_less_well_traded | F222: CAD | G222: 1 | H222: membership | I222: ISDA SIMM Methodology v2.8+2512 (based on v2.8+2512.2, 13 May 2026) | J222: 2.8+2512 | K222: 2026-07-11 | L222: J.1 | M222: 75(3) | N222: text of paragraph 75(3) (no table) | O222: 26 | P222: https://www.isda.org/a/hhkiE/ISDA-SIMM_v2.82512_PUBLIC.pdf | Q222: 2026-10-02 | R222: 8484d3de7dcb5280b6ad6458d051c50f8ccc3370bc279ae1c47a7bccb8064636 | S222: VERIFIED_PRIMARY | T222: two extractors agree (PyMuPDF, markitdown; sequence) + page image check
A223: =B223&"|"&C223&"|"&D223&"|"&E223&"|"&F223 -> 2.8+2512|IR|ct_group_member|regular_less_well_traded|CHF | B223: 2.8+2512 | C223: IR | D223: ct_group_member | E223: regular_less_well_traded | F223: CHF | G223: 1 | H223: membership | I223: ISDA SIMM Methodology v2.8+2512 (based on v2.8+2512.2, 13 May 2026) | J223: 2.8+2512 | K223: 2026-07-11 | L223: J.1 | M223: 75(3) | N223: text of paragraph 75(3) (no table) | O223: 26 | P223: https://www.isda.org/a/hhkiE/ISDA-SIMM_v2.82512_PUBLIC.pdf | Q223: 2026-10-02 | R223: 8484d3de7dcb5280b6ad6458d051c50f8ccc3370bc279ae1c47a7bccb8064636 | S223: VERIFIED_PRIMARY | T223: two extractors agree (PyMuPDF, markitdown; sequence) + page image check
A224: =B224&"|"&C224&"|"&D224&"|"&E224&"|"&F224 -> 2.8+2512|IR|ct_group_member|regular_less_well_traded|DKK | B224: 2.8+2512 | C224: IR | D224: ct_group_member | E224: regular_less_well_traded | F224: DKK | G224: 1 | H224: membership | I224: ISDA SIMM Methodology v2.8+2512 (based on v2.8+2512.2, 13 May 2026) | J224: 2.8+2512 | K224: 2026-07-11 | L224: J.1 | M224: 75(3) | N224: text of paragraph 75(3) (no table) | O224: 26 | P224: https://www.isda.org/a/hhkiE/ISDA-SIMM_v2.82512_PUBLIC.pdf | Q224: 2026-10-02 | R224: 8484d3de7dcb5280b6ad6458d051c50f8ccc3370bc279ae1c47a7bccb8064636 | S224: VERIFIED_PRIMARY | T224: two extractors agree (PyMuPDF, markitdown; sequence) + page image check
A225: =B225&"|"&C225&"|"&D225&"|"&E225&"|"&F225 -> 2.8+2512|IR|ct_group_member|regular_less_well_traded|HKD | B225: 2.8+2512 | C225: IR | D225: ct_group_member | E225: regular_less_well_traded | F225: HKD | G225: 1 | H225: membership | I225: ISDA SIMM Methodology v2.8+2512 (based on v2.8+2512.2, 13 May 2026) | J225: 2.8+2512 | K225: 2026-07-11 | L225: J.1 | M225: 75(3) | N225: text of paragraph 75(3) (no table) | O225: 26 | P225: https://www.isda.org/a/hhkiE/ISDA-SIMM_v2.82512_PUBLIC.pdf | Q225: 2026-10-02 | R225: 8484d3de7dcb5280b6ad6458d051c50f8ccc3370bc279ae1c47a7bccb8064636 | S225: VERIFIED_PRIMARY | T225: two extractors agree (PyMuPDF, markitdown; sequence) + page image check
A226: =B226&"|"&C226&"|"&D226&"|"&E226&"|"&F226 -> 2.8+2512|IR|ct_group_member|regular_less_well_traded|KRW | B226: 2.8+2512 | C226: IR | D226: ct_group_member | E226: regular_less_well_traded | F226: KRW | G226: 1 | H226: membership | I226: ISDA SIMM Methodology v2.8+2512 (based on v2.8+2512.2, 13 May 2026) | J226: 2.8+2512 | K226: 2026-07-11 | L226: J.1 | M226: 75(3) | N226: text of paragraph 75(3) (no table) | O226: 26 | P226: https://www.isda.org/a/hhkiE/ISDA-SIMM_v2.82512_PUBLIC.pdf | Q226: 2026-10-02 | R226: 8484d3de7dcb5280b6ad6458d051c50f8ccc3370bc279ae1c47a7bccb8064636 | S226: VERIFIED_PRIMARY | T226: two extractors agree (PyMuPDF, markitdown; sequence) + page image check
A227: =B227&"|"&C227&"|"&D227&"|"&E227&"|"&F227 -> 2.8+2512|IR|ct_group_member|regular_less_well_traded|NOK | B227: 2.8+2512 | C227: IR | D227: ct_group_member | E227: regular_less_well_traded | F227: NOK | G227: 1 | H227: membership | I227: ISDA SIMM Methodology v2.8+2512 (based on v2.8+2512.2, 13 May 2026) | J227: 2.8+2512 | K227: 2026-07-11 | L227: J.1 | M227: 75(3) | N227: text of paragraph 75(3) (no table) | O227: 26 | P227: https://www.isda.org/a/hhkiE/ISDA-SIMM_v2.82512_PUBLIC.pdf | Q227: 2026-10-02 | R227: 8484d3de7dcb5280b6ad6458d051c50f8ccc3370bc279ae1c47a7bccb8064636 | S227: VERIFIED_PRIMARY | T227: two extractors agree (PyMuPDF, markitdown; sequence) + page image check
A228: =B228&"|"&C228&"|"&D228&"|"&E228&"|"&F228 -> 2.8+2512|IR|ct_group_member|regular_less_well_traded|NZD | B228: 2.8+2512 | C228: IR | D228: ct_group_member | E228: regular_less_well_traded | F228: NZD | G228: 1 | H228: membership | I228: ISDA SIMM Methodology v2.8+2512 (based on v2.8+2512.2, 13 May 2026) | J228: 2.8+2512 | K228: 2026-07-11 | L228: J.1 | M228: 75(3) | N228: text of paragraph 75(3) (no table) | O228: 26 | P228: https://www.isda.org/a/hhkiE/ISDA-SIMM_v2.82512_PUBLIC.pdf | Q228: 2026-10-02 | R228: 8484d3de7dcb5280b6ad6458d051c50f8ccc3370bc279ae1c47a7bccb8064636 | S228: VERIFIED_PRIMARY | T228: two extractors agree (PyMuPDF, markitdown; sequence) + page image check
A229: =B229&"|"&C229&"|"&D229&"|"&E229&"|"&F229 -> 2.8+2512|IR|ct_group_member|regular_less_well_traded|SEK | B229: 2.8+2512 | C229: IR | D229: ct_group_member | E229: regular_less_well_traded | F229: SEK | G229: 1 | H229: membership | I229: ISDA SIMM Methodology v2.8+2512 (based on v2.8+2512.2, 13 May 2026) | J229: 2.8+2512 | K229: 2026-07-11 | L229: J.1 | M229: 75(3) | N229: text of paragraph 75(3) (no table) | O229: 26 | P229: https://www.isda.org/a/hhkiE/ISDA-SIMM_v2.82512_PUBLIC.pdf | Q229: 2026-10-02 | R229: 8484d3de7dcb5280b6ad6458d051c50f8ccc3370bc279ae1c47a7bccb8064636 | S229: VERIFIED_PRIMARY | T229: two extractors agree (PyMuPDF, markitdown; sequence) + page image check
... A247: =B247&"|"&C247&"|"&D247&"|"&E247&"|"&F247 -> 2.8+2512|FX|delta_rw|high|high | B247: 2.8+2512 | C247: FX | D247: delta_rw | E247: high | F247: high | G247: 31.7 | H247: multiplier of per-1% sensitivity | I247: ISDA SIMM Methodology v2.8+2512 (based on v2.8+2512.2, 13 May 2026) | J247: 2.8+2512 | K247: 2026-07-11 | L247: I.1 | M247: 69 | N247: FX risk weight table (key1=FX vol group of the given currency, key2=FX vol group of the calculation currency) | O247: 24 | P247: https://www.isda.org/a/hhkiE/ISDA-SIMM_v2.82512_PUBLIC.pdf | Q247: 2026-10-02 | R247: 8484d3de7dcb5280b6ad6458d051c50f8ccc3370bc279ae1c47a7bccb8064636 | S247: VERIFIED_PRIMARY | T247: two extractors agree (PyMuPDF, markitdown; sequence) + page image check
A248: =B248&"|"&C248&"|"&D248&"|"&E248&"|"&F248 -> 2.8+2512|FX|hvr|| | B248: 2.8+2512 | C248: FX | D248: hvr | G248: 0.67 | H248: ratio | I248: ISDA SIMM Methodology v2.8+2512 (based on v2.8+2512.2, 13 May 2026) | J248: 2.8+2512 | K248: 2026-07-11 | L248: I.1 | M248: 70 | N248: text of paragraph 70 (no table) | O248: 24 | P248: https://www.isda.org/a/hhkiE/ISDA-SIMM_v2.82512_PUBLIC.pdf | Q248: 2026-10-02 | R248: 8484d3de7dcb5280b6ad6458d051c50f8ccc3370bc279ae1c47a7bccb8064636 | S248: VERIFIED_PRIMARY | T248: two extractors agree (PyMuPDF, markitdown; sequence) + page image check
A249: =B249&"|"&C249&"|"&D249&"|"&E249&"|"&F249 -> 2.8+2512|FX|vega_rw|| | B249: 2.8+2512 | C249: FX | D249: vega_rw | G249: 0.33 | H249: ratio | I249: ISDA SIMM Methodology v2.8+2512 (based on v2.8+2512.2, 13 May 2026) | J249: 2.8+2512 | K249: 2026-07-11 | L249: I.1 | M249: 71 | N249: text of paragraph 71 (no table) | O249: 24 | P249: https://www.isda.org/a/hhkiE/ISDA-SIMM_v2.82512_PUBLIC.pdf | Q249: 2026-10-02 | R249: 8484d3de7dcb5280b6ad6458d051c50f8ccc3370bc279ae1c47a7bccb8064636 | S249: VERIFIED_PRIMARY | T249: two extractors agree (PyMuPDF, markitdown; sequence) + page image check
A250: =B250&"|"&C250&"|"&D250&"|"&E250&"|"&F250 -> 2.8+2512|FX|delta_corr_calc_regular|regular|regular | B250: 2.8+2512 | C250: FX | D250: delta_corr_calc_regular | E250: regular | F250: regular | G250: 0.5 | H250: fraction | I250: ISDA SIMM Methodology v2.8+2512 (based on v2.8+2512.2, 13 May 2026) | J250: 2.8+2512 | K250: 2026-07-11 | L250: I.2 | M250: 72 | N250: FX correlation table, calculation currency in the regular FX vol group (key1, key2 = FX vol groups of the two risk factors) | O250: 24 | P250: https://www.isda.org/a/hhkiE/ISDA-SIMM_v2.82512_PUBLIC.pdf | Q250: 2026-10-02 | R250: 8484d3de7dcb5280b6ad6458d051c50f8ccc3370bc279ae1c47a7bccb8064636 | S250: VERIFIED_PRIMARY | T250: two extractors agree (PyMuPDF, markitdown; sequence) + page image check
A251: =B251&"|"&C251&"|"&D251&"|"&E251&"|"&F251 -> 2.8+2512|FX|delta_corr_calc_regular|regular|high | B251: 2.8+2512 | C251: FX | D251: delta_corr_calc_regular | E251: regular | F251: high | G251: 0.12 | H251: fraction | I251: ISDA SIMM Methodology v2.8+2512 (based on v2.8+2512.2, 13 May 2026) | J251: 2.8+2512 | K251: 2026-07-11 | L251: I.2 | M251: 72 | N251: FX correlation table, calculation currency in the regular FX vol group (key1, key2 = FX vol groups of the two risk factors) | O251: 24 | P251: https://www.isda.org/a/hhkiE/ISDA-SIMM_v2.82512_PUBLIC.pdf | Q251: 2026-10-02 | R251: 8484d3de7dcb5280b6ad6458d051c50f8ccc3370bc279ae1c47a7bccb8064636 | S251: VERIFIED_PRIMARY | T251: two extractors agree (PyMuPDF, markitdown; sequence) + page image check
A252: =B252&"|"&C252&"|"&D252&"|"&E252&"|"&F252 -> 2.8+2512|FX|delta_corr_calc_regular|high|regular | B252: 2.8+2512 | C252: FX | D252: delta_corr_calc_regular | E252: high | F252: regular | G252: 0.12 | H252: fraction | I252: ISDA SIMM Methodology v2.8+2512 (based on v2.8+2512.2, 13 May 2026) | J252: 2.8+2512 | K252: 2026-07-11 | L252: I.2 | M252: 72 | N252: FX correlation table, calculation currency in the regular FX vol group (key1, key2 = FX vol groups of the two risk factors) | O252: 24 | P252: https://www.isda.org/a/hhkiE/ISDA-SIMM_v2.82512_PUBLIC.pdf | Q252: 2026-10-02 | R252: 8484d3de7dcb5280b6ad6458d051c50f8ccc3370bc279ae1c47a7bccb8064636 | S252: VERIFIED_PRIMARY | T252: two extractors agree (PyMuPDF, markitdown; sequence) + page image check
A253: =B253&"|"&C253&"|"&D253&"|"&E253&"|"&F253 -> 2.8+2512|FX|delta_corr_calc_regular|high|high | B253: 2.8+2512 | C253: FX | D253: delta_corr_calc_regular | E253: high | F253: high | G253: 0.03 | H253: fraction | I253: ISDA SIMM Methodology v2.8+2512 (based on v2.8+2512.2, 13 May 2026) | J253: 2.8+2512 | K253: 2026-07-11 | L253: I.2 | M253: 72 | N253: FX correlation table, calculation currency in the regular FX vol group (key1, key2 = FX vol groups of the two risk factors) | O253: 24 | P253: https://www.isda.org/a/hhkiE/ISDA-SIMM_v2.82512_PUBLIC.pdf | Q253: 2026-10-02 | R253: 8484d3de7dcb5280b6ad6458d051c50f8ccc3370bc279ae1c47a7bccb8064636 | S253: VERIFIED_PRIMARY | T253: two extractors agree (PyMuPDF, markitdown; sequence) + page image check
A254: =B254&"|"&C254&"|"&D254&"|"&E254&"|"&F254 -> 2.8+2512|FX|delta_corr_calc_high|regular|regular | B254: 2.8+2512 | C254: FX | D254: delta_corr_calc_high | E254: regular | F254: regular | G254: 0.97 | H254: fraction | I254: ISDA SIMM Methodology v2.8+2512 (based on v2.8+2512.2, 13 May 2026) | J254: 2.8+2512 | K254: 2026-07-11 | L254: I.2 | M254: 72 | N254: FX correlation table, calculation currency in the high FX vol group (key1, key2 = FX vol groups of the two risk factors) | O254: 25 | P254: https://www.isda.org/a/hhkiE/ISDA-SIMM_v2.82512_PUBLIC.pdf | Q254: 2026-10-02 | R254: 8484d3de7dcb5280b6ad6458d051c50f8ccc3370bc279ae1c47a7bccb8064636 | S254: VERIFIED_PRIMARY | T254: two extractors agree (PyMuPDF, markitdown; sequence) + page image check
A255: =B255&"|"&C255&"|"&D255&"|"&E255&"|"&F255 -> 2.8+2512|FX|delta_corr_calc_high|regular|high | B255: 2.8+2512 | C255: FX | D255: delta_corr_calc_high | E255: regular | F255: high | G255: 0.7 | H255: fraction | I255: ISDA SIMM Methodology v2.8+2512 (based on v2.8+2512.2, 13 May 2026) | J255: 2.8+2512 | K255: 2026-07-11 | L255: I.2 | M255: 72 | N255: FX correlation table, calculation currency in the high FX vol group (key1, key2 = FX vol groups of the two risk factors) | O255: 25 | P255: https://www.isda.org/a/hhkiE/ISDA-SIMM_v2.82512_PUBLIC.pdf | Q255: 2026-10-02 | R255: 8484d3de7dcb5280b6ad6458d051c50f8ccc3370bc279ae1c47a7bccb8064636 | S255: VERIFIED_PRIMARY | T255: two extractors agree (PyMuPDF, markitdown; sequence) + page image check
A256: =B256&"|"&C256&"|"&D256&"|"&E256&"|"&F256 -> 2.8+2512|FX|delta_corr_calc_high|high|regular | B256: 2.8+2512 | C256: FX | D256: delta_corr_calc_high | E256: high | F256: regular | G256: 0.7 | H256: fraction | I256: ISDA SIMM Methodology v2.8+2512 (based on v2.8+2512.2, 13 May 2026) | J256: 2.8+2512 | K256: 2026-07-11 | L256: I.2 | M256: 72 | N256: FX correlation table, calculation currency in the high FX vol group (key1, key2 = FX vol groups of the two risk factors) | O256: 25 | P256: https://www.isda.org/a/hhkiE/ISDA-SIMM_v2.82512_PUBLIC.pdf | Q256: 2026-10-02 | R256: 8484d3de7dcb5280b6ad6458d051c50f8ccc3370bc279ae1c47a7bccb8064636 | S256: VERIFIED_PRIMARY | T256: two extractors agree (PyMuPDF, markitdown; sequence) + page image check
A257: =B257&"|"&C257&"|"&D257&"|"&E257&"|"&F257 -> 2.8+2512|FX|delta_corr_calc_high|high|high | B257: 2.8+2512 | C257: FX | D257: delta_corr_calc_high | E257: high | F257: high | G257: 0.5 | H257: fraction | I257: ISDA SIMM Methodology v2.8+2512 (based on v2.8+2512.2, 13 May 2026) | J257: 2.8+2512 | K257: 2026-07-11 | L257: I.2 | M257: 72 | N257: FX correlation table, calculation currency in the high FX vol group (key1, key2 = FX vol groups of the two risk factors) | O257: 25 | P257: https://www.isda.org/a/hhkiE/ISDA-SIMM_v2.82512_PUBLIC.pdf | Q257: 2026-10-02 | R257: 8484d3de7dcb5280b6ad6458d051c50f8ccc3370bc279ae1c47a7bccb8064636 | S257: VERIFIED_PRIMARY | T257: two extractors agree (PyMuPDF, markitdown; sequence) + page image check
A258: =B258&"|"&C258&"|"&D258&"|"&E258&"|"&F258 -> 2.8+2512|FX|vol_curvature_corr|| | B258: 2.8+2512 | C258: FX | D258: vol_curvature_corr | G258: 0.5 | H258: fraction | I258: ISDA SIMM Methodology v2.8+2512 (based on v2.8+2512.2, 13 May 2026) | J258: 2.8+2512 | K258: 2026-07-11 | L258: I.2 | M258: 73 | N258: text of paragraph 73 (no table) | O258: 25 | P258: https://www.isda.org/a/hhkiE/ISDA-SIMM_v2.82512_PUBLIC.pdf | Q258: 2026-10-02 | R258: 8484d3de7dcb5280b6ad6458d051c50f8ccc3370bc279ae1c47a7bccb8064636 | S258: VERIFIED_PRIMARY | T258: two extractors agree (PyMuPDF, markitdown; sequence) + page image check
A259: =B259&"|"&C259&"|"&D259&"|"&E259&"|"&F259 -> 2.8+2512|FX|delta_ct|Category 1| | B259: 2.8+2512 | C259: FX | D259: delta_ct | E259: Category 1 | G259: 2100 | H259: USD mm per percent | I259: ISDA SIMM Methodology v2.8+2512 (based on v2.8+2512.2, 13 May 2026) | J259: 2.8+2512 | K259: 2026-07-11 | L259: J.5 | M259: 79 | N259: text of paragraph 79 (no table) | O259: 27 | P259: https://www.isda.org/a/hhkiE/ISDA-SIMM_v2.82512_PUBLIC.pdf | Q259: 2026-10-02 | R259: 8484d3de7dcb5280b6ad6458d051c50f8ccc3370bc279ae1c47a7bccb8064636 | S259: VERIFIED_PRIMARY | T259: two extractors agree (PyMuPDF, markitdown; sequence) + page image check
A260: =B260&"|"&C260&"|"&D260&"|"&E260&"|"&F260 -> 2.8+2512|FX|delta_ct|Category 2| | B260: 2.8+2512 | C260: FX | D260: delta_ct | E260: Category 2 | G260: 710 | H260: USD mm per percent | I260: ISDA SIMM Methodology v2.8+2512 (based on v2.8+2512.2, 13 May 2026) | J260: 2.8+2512 | K260: 2026-07-11 | L260: J.5 | M260: 79 | N260: text of paragraph 79 (no table) | O260: 27 | P260: https://www.isda.org/a/hhkiE/ISDA-SIMM_v2.82512_PUBLIC.pdf | Q260: 2026-10-02 | R260: 8484d3de7dcb5280b6ad6458d051c50f8ccc3370bc279ae1c47a7bccb8064636 | S260: VERIFIED_PRIMARY | T260: two extractors agree (PyMuPDF, markitdown; sequence) + page image check
A261: =B261&"|"&C261&"|"&D261&"|"&E261&"|"&F261 -> 2.8+2512|FX|delta_ct|Category 3| | B261: 2.8+2512 | C261: FX | D261: delta_ct | E261: Category 3 | G261: 120 | H261: USD mm per percent | I261: ISDA SIMM Methodology v2.8+2512 (based on v2.8+2512.2, 13 May 2026) | J261: 2.8+2512 | K261: 2026-07-11 | L261: J.5 | M261: 79 | N261: text of paragraph 79 (no table) | O261: 27 | P261: https://www.isda.org/a/hhkiE/ISDA-SIMM_v2.82512_PUBLIC.pdf | Q261: 2026-10-02 | R261: 8484d3de7dcb5280b6ad6458d051c50f8ccc3370bc279ae1c47a7bccb8064636 | S261: VERIFIED_PRIMARY | T261: two extractors agree (PyMuPDF, markitdown; sequence) + page image check
A262: =B262&"|"&C262&"|"&D262&"|"&E262&"|"&F262 -> 2.8+2512|FX|vega_ct|Category 1|Category 1 | B262: 2.8+2512 | C262: FX | D262: vega_ct | E262: Category 1 | F262: Category 1 | G262: 2900 | H262: USD mm | I262: ISDA SIMM Methodology v2.8+2512 (based on v2.8+2512.2, 13 May 2026) | J262: 2.8+2512 | K262: 2026-07-11 | L262: J.10 | M262: 86 | N262: text of paragraph 86 (no table) | O262: 28 | P262: https://www.isda.org/a/hhkiE/ISDA-SIMM_v2.82512_PUBLIC.pdf | Q262: 2026-10-02 | R262: 8484d3de7dcb5280b6ad6458d051c50f8ccc3370bc279ae1c47a7bccb8064636 | S262: VERIFIED_PRIMARY | T262: two extractors agree (PyMuPDF, markitdown; multiset) + page image check; markitdown row order differs in this table (multiset equal); pair labels from PyMuPDF
A263: =B263&"|"&C263&"|"&D263&"|"&E263&"|"&F263 -> 2.8+2512|FX|vega_ct|Category 1|Category 2 | B263: 2.8+2512 | C263: FX | D263: vega_ct | E263: Category 1 | F263: Category 2 | G263: 1500 | H263: USD mm | I263: ISDA SIMM Methodology v2.8+2512 (based on v2.8+2512.2, 13 May 2026) | J263: 2.8+2512 | K263: 2026-07-11 | L263: J.10 | M263: 86 | N263: text of paragraph 86 (no table) | O263: 28 | P263: https://www.isda.org/a/hhkiE/ISDA-SIMM_v2.82512_PUBLIC.pdf | Q263: 2026-10-02 | R263: 8484d3de7dcb5280b6ad6458d051c50f8ccc3370bc279ae1c47a7bccb8064636 | S263: VERIFIED_PRIMARY | T263: two extractors agree (PyMuPDF, markitdown; multiset) + page image check; markitdown row order differs in this table (multiset equal); pair labels from PyMuPDF
A264: =B264&"|"&C264&"|"&D264&"|"&E264&"|"&F264 -> 2.8+2512|FX|vega_ct|Category 1|Category 3 | B264: 2.8+2512 | C264: FX | D264: vega_ct | E264: Category 1 | F264: Category 3 | G264: 840 | H264: USD mm | I264: ISDA SIMM Methodology v2.8+2512 (based on v2.8+2512.2, 13 May 2026) | J264: 2.8+2512 | K264: 2026-07-11 | L264: J.10 | M264: 86 | N264: text of paragraph 86 (no table) | O264: 28 | P264: https://www.isda.org/a/hhkiE/ISDA-SIMM_v2.82512_PUBLIC.pdf | Q264: 2026-10-02 | R264: 8484d3de7dcb5280b6ad6458d051c50f8ccc3370bc279ae1c47a7bccb8064636 | S264: VERIFIED_PRIMARY | T264: two extractors agree (PyMuPDF, markitdown; multiset) + page image check; markitdown row order differs in this table (multiset equal); pair labels from PyMuPDF
A265: =B265&"|"&C265&"|"&D265&"|"&E265&"|"&F265 -> 2.8+2512|FX|vega_ct|Category 2|Category 2 | B265: 2.8+2512 | C265: FX | D265: vega_ct | E265: Category 2 | F265: Category 2 | G265: 760 | H265: USD mm | I265: ISDA SIMM Methodology v2.8+2512 (based on v2.8+2512.2, 13 May 2026) | J265: 2.8+2512 | K265: 2026-07-11 | L265: J.10 | M265: 86 | N265: text of paragraph 86 (no table) | O265: 28 | P265: https://www.isda.org/a/hhkiE/ISDA-SIMM_v2.82512_PUBLIC.pdf | Q265: 2026-10-02 | R265: 8484d3de7dcb5280b6ad6458d051c50f8ccc3370bc279ae1c47a7bccb8064636 | S265: VERIFIED_PRIMARY | T265: two extractors agree (PyMuPDF, markitdown; multiset) + page image check; markitdown row order differs in this table (multiset equal); pair labels from PyMuPDF
A266: =B266&"|"&C266&"|"&D266&"|"&E266&"|"&F266 -> 2.8+2512|FX|vega_ct|Category 2|Category 3 | B266: 2.8+2512 | C266: FX | D266: vega_ct | E266: Category 2 | F266: Category 3 | G266: 490 | H266: USD mm | I266: ISDA SIMM Methodology v2.8+2512 (based on v2.8+2512.2, 13 May 2026) | J266: 2.8+2512 | K266: 2026-07-11 | L266: J.10 | M266: 86 | N266: text of paragraph 86 (no table) | O266: 28 | P266: https://www.isda.org/a/hhkiE/ISDA-SIMM_v2.82512_PUBLIC.pdf | Q266: 2026-10-02 | R266: 8484d3de7dcb5280b6ad6458d051c50f8ccc3370bc279ae1c47a7bccb8064636 | S266: VERIFIED_PRIMARY | T266: two extractors agree (PyMuPDF, markitdown; multiset) + page image check; markitdown row order differs in this table (multiset equal); pair labels from PyMuPDF
A267: =B267&"|"&C267&"|"&D267&"|"&E267&"|"&F267 -> 2.8+2512|FX|vega_ct|Category 3|Category 3 | B267: 2.8+2512 | C267: FX | D267: vega_ct | E267: Category 3 | F267: Category 3 | G267: 310 | H267: USD mm | I267: ISDA SIMM Methodology v2.8+2512 (based on v2.8+2512.2, 13 May 2026) | J267: 2.8+2512 | K267: 2026-07-11 | L267: J.10 | M267: 86 | N267: text of paragraph 86 (no table) | O267: 28 | P267: https://www.isda.org/a/hhkiE/ISDA-SIMM_v2.82512_PUBLIC.pdf | Q267: 2026-10-02 | R267: 8484d3de7dcb5280b6ad6458d051c50f8ccc3370bc279ae1c47a7bccb8064636 | S267: VERIFIED_PRIMARY | T267: two extractors agree (PyMuPDF, markitdown; multiset) + page image check; markitdown row order differs in this table (multiset equal); pair labels from PyMuPDF
A268: =B268&"|"&C268&"|"&D268&"|"&E268&"|"&F268 -> 2.8+2512|FX|ct_category_member|Category 1|USD | B268: 2.8+2512 | C268: FX | D268: ct_category_member | E268: Category 1 | F268: USD | G268: 1 | H268: membership | I268: ISDA SIMM Methodology v2.8+2512 (based on v2.8+2512.2, 13 May 2026) | J268: 2.8+2512 | K268: 2026-07-11 | L268: J.5 | M268: 80 | N268: text of paragraph 80 (no table) | O268: 27 | P268: https://www.isda.org/a/hhkiE/ISDA-SIMM_v2.82512_PUBLIC.pdf | Q268: 2026-10-02 | R268: 8484d3de7dcb5280b6ad6458d051c50f8ccc3370bc279ae1c47a7bccb8064636 | S268: VERIFIED_PRIMARY | T268: two extractors agree (PyMuPDF, markitdown; sequence) + page image check
A269: =B269&"|"&C269&"|"&D269&"|"&E269&"|"&F269 -> 2.8+2512|FX|ct_category_member|Category 1|EUR | B269: 2.8+2512 | C269: FX | D269: ct_category_member | E269: Category 1 | F269: EUR | G269: 1 | H269: membership | I269: ISDA SIMM Methodology v2.8+2512 (based on v2.8+2512.2, 13 May 2026) | J269: 2.8+2512 | K269: 2026-07-11 | L269: J.5 | M269: 80 | N269: text of paragraph 80 (no table) | O269: 27 | P269: https://www.isda.org/a/hhkiE/ISDA-SIMM_v2.82512_PUBLIC.pdf | Q269: 2026-10-02 | R269: 8484d3de7dcb5280b6ad6458d051c50f8ccc3370bc279ae1c47a7bccb8064636 | S269: VERIFIED_PRIMARY | T269: two extractors agree (PyMuPDF, markitdown; sequence) + page image check
A270: =B270&"|"&C270&"|"&D270&"|"&E270&"|"&F270 -> 2.8+2512|FX|ct_category_member|Category 1|JPY | B270: 2.8+2512 | C270: FX | D270: ct_category_member | E270: Category 1 | F270: JPY | G270: 1 | H270: membership | I270: ISDA SIMM Methodology v2.8+2512 (based on v2.8+2512.2, 13 May 2026) | J270: 2.8+2512 | K270: 2026-07-11 | L270: J.5 | M270: 80 | N270: text of paragraph 80 (no table) | O270: 27 | P270: https://www.isda.org/a/hhkiE/ISDA-SIMM_v2.82512_PUBLIC.pdf | Q270: 2026-10-02 | R270: 8484d3de7dcb5280b6ad6458d051c50f8ccc3370bc279ae1c47a7bccb8064636 | S270: VERIFIED_PRIMARY | T270: two extractors agree (PyMuPDF, markitdown; sequence) + page image check
A271: =B271&"|"&C271&"|"&D271&"|"&E271&"|"&F271 -> 2.8+2512|FX|ct_category_member|Category 1|GBP | B271: 2.8+2512 | C271: FX | D271: ct_category_member | E271: Category 1 | F271: GBP | G271: 1 | H271: membership | I271: ISDA SIMM Methodology v2.8+2512 (based on v2.8+2512.2, 13 May 2026) | J271: 2.8+2512 | K271: 2026-07-11 | L271: J.5 | M271: 80 | N271: text of paragraph 80 (no table) | O271: 27 | P271: https://www.isda.org/a/hhkiE/ISDA-SIMM_v2.82512_PUBLIC.pdf | Q271: 2026-10-02 | R271: 8484d3de7dcb5280b6ad6458d051c50f8ccc3370bc279ae1c47a7bccb8064636 | S271: VERIFIED_PRIMARY | T271: two extractors agree (PyMuPDF, markitdown; sequence) + page image check
A272: =B272&"|"&C272&"|"&D272&"|"&E272&"|"&F272 -> 2.8+2512|FX|ct_category_member|Category 1|AUD | B272: 2.8+2512 | C272: FX | D272: ct_category_member | E272: Category 1 | F272: AUD | G272: 1 | H272: membership | I272: ISDA SIMM Methodology v2.8+2512 (based on v2.8+2512.2, 13 May 2026) | J272: 2.8+2512 | K272: 2026-07-11 | L272: J.5 | M272: 80 | N272: text of paragraph 80 (no table) | O272: 27 | P272: https://www.isda.org/a/hhkiE/ISDA-SIMM_v2.82512_PUBLIC.pdf | Q272: 2026-10-02 | R272: 8484d3de7dcb5280b6ad6458d051c50f8ccc3370bc279ae1c47a7bccb8064636 | S272: VERIFIED_PRIMARY | T272: two extractors agree (PyMuPDF, markitdown; sequence) + page image check
A273: =B273&"|"&C273&"|"&D273&"|"&E273&"|"&F273 -> 2.8+2512|FX|ct_category_member|Category 1|CHF | B273: 2.8+2512 | C273: FX | D273: ct_category_member | E273: Category 1 | F273: CHF | G273: 1 | H273: membership | I273: ISDA SIMM Methodology v2.8+2512 (based on v2.8+2512.2, 13 May 2026) | J273: 2.8+2512 | K273: 2026-07-11 | L273: J.5 | M273: 80 | N273: text of paragraph 80 (no table) | O273: 27 | P273: https://www.isda.org/a/hhkiE/ISDA-SIMM_v2.82512_PUBLIC.pdf | Q273: 2026-10-02 | R273: 8484d3de7dcb5280b6ad6458d051c50f8ccc3370bc279ae1c47a7bccb8064636 | S273: VERIFIED_PRIMARY | T273: two extractors agree (PyMuPDF, markitdown; sequence) + page image check
... A288: =B288&"|"&C288&"|"&D288&"|"&E288&"|"&F288 -> 2.8+2512|FX|ct_category_member|Category 3|ALL_OTHER | B288: 2.8+2512 | C288: FX | D288: ct_category_member | E288: Category 3 | F288: ALL_OTHER | G288: 1 | H288: membership | I288: ISDA SIMM Methodology v2.8+2512 (based on v2.8+2512.2, 13 May 2026) | J288: 2.8+2512 | K288: 2026-07-11 | L288: J.5 | M288: 80 | N288: all other currencies | O288: 27 | P288: https://www.isda.org/a/hhkiE/ISDA-SIMM_v2.82512_PUBLIC.pdf | Q288: 2026-10-02 | R288: 8484d3de7dcb5280b6ad6458d051c50f8ccc3370bc279ae1c47a7bccb8064636 | S288: VERIFIED_PRIMARY | T288: two extractors agree (PyMuPDF, markitdown; sequence) + page image check
A289: =B289&"|"&C289&"|"&D289&"|"&E289&"|"&F289 -> 2.8+2512|ALL|curvature_sf_example|2w| | B289: 2.8+2512 | C289: ALL | D289: curvature_sf_example | E289: 2w | G289: 0.5 | H289: fraction | I289: ISDA SIMM Methodology v2.8+2512 (based on v2.8+2512.2, 13 May 2026) | J289: 2.8+2512 | K289: 2026-07-11 | L289: B | M289: 11(a) | N289: SF example table (document rounds to 0.1 percent) | O289: 7 | P289: https://www.isda.org/a/hhkiE/ISDA-SIMM_v2.82512_PUBLIC.pdf | Q289: 2026-10-02 | R289: 8484d3de7dcb5280b6ad6458d051c50f8ccc3370bc279ae1c47a7bccb8064636 | S289: VERIFIED_PRIMARY | T289: two extractors agree (PyMuPDF, markitdown; sequence) + page image check
A290: =B290&"|"&C290&"|"&D290&"|"&E290&"|"&F290 -> 2.8+2512|ALL|curvature_sf_example|1m| | B290: 2.8+2512 | C290: ALL | D290: curvature_sf_example | E290: 1m | G290: 0.23 | H290: fraction | I290: ISDA SIMM Methodology v2.8+2512 (based on v2.8+2512.2, 13 May 2026) | J290: 2.8+2512 | K290: 2026-07-11 | L290: B | M290: 11(a) | N290: SF example table (document rounds to 0.1 percent) | O290: 7 | P290: https://www.isda.org/a/hhkiE/ISDA-SIMM_v2.82512_PUBLIC.pdf | Q290: 2026-10-02 | R290: 8484d3de7dcb5280b6ad6458d051c50f8ccc3370bc279ae1c47a7bccb8064636 | S290: VERIFIED_PRIMARY | T290: two extractors agree (PyMuPDF, markitdown; sequence) + page image check
A291: =B291&"|"&C291&"|"&D291&"|"&E291&"|"&F291 -> 2.8+2512|ALL|curvature_sf_example|3m| | B291: 2.8+2512 | C291: ALL | D291: curvature_sf_example | E291: 3m | G291: 0.077 | H291: fraction | I291: ISDA SIMM Methodology v2.8+2512 (based on v2.8+2512.2, 13 May 2026) | J291: 2.8+2512 | K291: 2026-07-11 | L291: B | M291: 11(a) | N291: SF example table (document rounds to 0.1 percent) | O291: 7 | P291: https://www.isda.org/a/hhkiE/ISDA-SIMM_v2.82512_PUBLIC.pdf | Q291: 2026-10-02 | R291: 8484d3de7dcb5280b6ad6458d051c50f8ccc3370bc279ae1c47a7bccb8064636 | S291: VERIFIED_PRIMARY | T291: two extractors agree (PyMuPDF, markitdown; sequence) + page image check
A292: =B292&"|"&C292&"|"&D292&"|"&E292&"|"&F292 -> 2.8+2512|ALL|curvature_sf_example|6m| | B292: 2.8+2512 | C292: ALL | D292: curvature_sf_example | E292: 6m | G292: 0.038 | H292: fraction | I292: ISDA SIMM Methodology v2.8+2512 (based on v2.8+2512.2, 13 May 2026) | J292: 2.8+2512 | K292: 2026-07-11 | L292: B | M292: 11(a) | N292: SF example table (document rounds to 0.1 percent) | O292: 7 | P292: https://www.isda.org/a/hhkiE/ISDA-SIMM_v2.82512_PUBLIC.pdf | Q292: 2026-10-02 | R292: 8484d3de7dcb5280b6ad6458d051c50f8ccc3370bc279ae1c47a7bccb8064636 | S292: VERIFIED_PRIMARY | T292: two extractors agree (PyMuPDF, markitdown; sequence) + page image check
A293: =B293&"|"&C293&"|"&D293&"|"&E293&"|"&F293 -> 2.8+2512|ALL|curvature_sf_example|12m| | B293: 2.8+2512 | C293: ALL | D293: curvature_sf_example | E293: 12m | G293: 0.019 | H293: fraction | I293: ISDA SIMM Methodology v2.8+2512 (based on v2.8+2512.2, 13 May 2026) | J293: 2.8+2512 | K293: 2026-07-11 | L293: B | M293: 11(a) | N293: SF example table (document rounds to 0.1 percent) | O293: 7 | P293: https://www.isda.org/a/hhkiE/ISDA-SIMM_v2.82512_PUBLIC.pdf | Q293: 2026-10-02 | R293: 8484d3de7dcb5280b6ad6458d051c50f8ccc3370bc279ae1c47a7bccb8064636 | S293: VERIFIED_PRIMARY | T293: two extractors agree (PyMuPDF, markitdown; sequence) + page image check
A294: =B294&"|"&C294&"|"&D294&"|"&E294&"|"&F294 -> 2.8+2512|ALL|curvature_sf_example|2y| | B294: 2.8+2512 | C294: ALL | D294: curvature_sf_example | E294: 2y | G294: 0.01 | H294: fraction | I294: ISDA SIMM Methodology v2.8+2512 (based on v2.8+2512.2, 13 May 2026) | J294: 2.8+2512 | K294: 2026-07-11 | L294: B | M294: 11(a) | N294: SF example table (document rounds to 0.1 percent) | O294: 7 | P294: https://www.isda.org/a/hhkiE/ISDA-SIMM_v2.82512_PUBLIC.pdf | Q294: 2026-10-02 | R294: 8484d3de7dcb5280b6ad6458d051c50f8ccc3370bc279ae1c47a7bccb8064636 | S294: VERIFIED_PRIMARY | T294: two extractors agree (PyMuPDF, markitdown; sequence) + page image check
A295: =B295&"|"&C295&"|"&D295&"|"&E295&"|"&F295 -> 2.8+2512|ALL|curvature_sf_example|3y| | B295: 2.8+2512 | C295: ALL | D295: curvature_sf_example | E295: 3y | G295: 0.006 | H295: fraction | I295: ISDA SIMM Methodology v2.8+2512 (based on v2.8+2512.2, 13 May 2026) | J295: 2.8+2512 | K295: 2026-07-11 | L295: B | M295: 11(a) | N295: SF example table (document rounds to 0.1 percent) | O295: 7 | P295: https://www.isda.org/a/hhkiE/ISDA-SIMM_v2.82512_PUBLIC.pdf | Q295: 2026-10-02 | R295: 8484d3de7dcb5280b6ad6458d051c50f8ccc3370bc279ae1c47a7bccb8064636 | S295: VERIFIED_PRIMARY | T295: two extractors agree (PyMuPDF, markitdown; sequence) + page image check
A296: =B296&"|"&C296&"|"&D296&"|"&E296&"|"&F296 -> 2.8+2512|ALL|curvature_sf_example|5y| | B296: 2.8+2512 | C296: ALL | D296: curvature_sf_example | E296: 5y | G296: 0.004 | H296: fraction | I296: ISDA SIMM Methodology v2.8+2512 (based on v2.8+2512.2, 13 May 2026) | J296: 2.8+2512 | K296: 2026-07-11 | L296: B | M296: 11(a) | N296: SF example table (document rounds to 0.1 percent) | O296: 7 | P296: https://www.isda.org/a/hhkiE/ISDA-SIMM_v2.82512_PUBLIC.pdf | Q296: 2026-10-02 | R296: 8484d3de7dcb5280b6ad6458d051c50f8ccc3370bc279ae1c47a7bccb8064636 | S296: VERIFIED_PRIMARY | T296: two extractors agree (PyMuPDF, markitdown; sequence) + page image check
A297: =B297&"|"&C297&"|"&D297&"|"&E297&"|"&F297 -> 2.8+2512|ALL|curvature_sf_example|10y| | B297: 2.8+2512 | C297: ALL | D297: curvature_sf_example | E297: 10y | G297: 0.002 | H297: fraction | I297: ISDA SIMM Methodology v2.8+2512 (based on v2.8+2512.2, 13 May 2026) | J297: 2.8+2512 | K297: 2026-07-11 | L297: B | M297: 11(a) | N297: SF example table (document rounds to 0.1 percent) | O297: 7 | P297: https://www.isda.org/a/hhkiE/ISDA-SIMM_v2.82512_PUBLIC.pdf | Q297: 2026-10-02 | R297: 8484d3de7dcb5280b6ad6458d051c50f8ccc3370bc279ae1c47a7bccb8064636 | S297: VERIFIED_PRIMARY | T297: two extractors agree (PyMuPDF, markitdown; sequence) + page image check
A298: =B298&"|"&C298&"|"&D298&"|"&E298&"|"&F298 -> 2.8+2512|ALL|curvature_sf_scale|| | B298: 2.8+2512 | C298: ALL | D298: curvature_sf_scale | G298: 0.5 | H298: fraction | I298: ISDA SIMM Methodology v2.8+2512 (based on v2.8+2512.2, 13 May 2026) | J298: 2.8+2512 | K298: 2026-07-11 | L298: B | M298: 11(a) | N298: SF(t) = 0.5 min(1, 14 days / t days) | O298: 7 | P298: https://www.isda.org/a/hhkiE/ISDA-SIMM_v2.82512_PUBLIC.pdf | Q298: 2026-10-02 | R298: 8484d3de7dcb5280b6ad6458d051c50f8ccc3370bc279ae1c47a7bccb8064636 | S298: VERIFIED_PRIMARY | T298: two extractors agree (PyMuPDF, markitdown; sequence) + page image check
A299: =B299&"|"&C299&"|"&D299&"|"&E299&"|"&F299 -> 2.8+2512|ALL|curvature_sf_ref_days|| | B299: 2.8+2512 | C299: ALL | D299: curvature_sf_ref_days | G299: 14 | H299: days | I299: ISDA SIMM Methodology v2.8+2512 (based on v2.8+2512.2, 13 May 2026) | J299: 2.8+2512 | K299: 2026-07-11 | L299: B | M299: 11(a) | N299: SF(t) = 0.5 min(1, 14 days / t days) | O299: 7 | P299: https://www.isda.org/a/hhkiE/ISDA-SIMM_v2.82512_PUBLIC.pdf | Q299: 2026-10-02 | R299: 8484d3de7dcb5280b6ad6458d051c50f8ccc3370bc279ae1c47a7bccb8064636 | S299: VERIFIED_PRIMARY | T299: two extractors agree (PyMuPDF, markitdown; sequence) + page image check
A300: =B300&"|"&C300&"|"&D300&"|"&E300&"|"&F300 -> 2.8+2512|ALL|tenor_days_per_year|| | B300: 2.8+2512 | C300: ALL | D300: tenor_days_per_year | G300: 365 | H300: days | I300: ISDA SIMM Methodology v2.8+2512 (based on v2.8+2512.2, 13 May 2026) | J300: 2.8+2512 | K300: 2026-07-11 | L300: B | M300: 11(a) | N300: 12m = 365 calendar days, pro-rata for other tenors | O300: 7 | P300: https://www.isda.org/a/hhkiE/ISDA-SIMM_v2.82512_PUBLIC.pdf | Q300: 2026-10-02 | R300: 8484d3de7dcb5280b6ad6458d051c50f8ccc3370bc279ae1c47a7bccb8064636 | S300: VERIFIED_PRIMARY | T300: two extractors agree (PyMuPDF, markitdown; sequence) + page image check
A301: =B301&"|"&C301&"|"&D301&"|"&E301&"|"&F301 -> 2.8+2512|ALL|curvature_lambda_quantile|| | B301: 2.8+2512 | C301: ALL | D301: curvature_lambda_quantile | G301: 0.995 | H301: fraction | I301: ISDA SIMM Methodology v2.8+2512 (based on v2.8+2512.2, 13 May 2026) | J301: 2.8+2512 | K301: 2026-07-11 | L301: B | M301: 11(d) | N301: lambda = (Phi^-1(99.5%)^2 - 1)(1+theta) - theta; theta = min(sum CVR / sum |CVR|, 0) | O301: 7 | P301: https://www.isda.org/a/hhkiE/ISDA-SIMM_v2.82512_PUBLIC.pdf | Q301: 2026-10-02 | R301: 8484d3de7dcb5280b6ad6458d051c50f8ccc3370bc279ae1c47a7bccb8064636 | S301: VERIFIED_PRIMARY | T301: two extractors agree (PyMuPDF, markitdown; sequence) + page image check
A302: =B302&"|"&C302&"|"&D302&"|"&E302&"|"&F302 -> 2.8+2512|IR|curvature_hvr_exponent|| | B302: 2.8+2512 | C302: IR | D302: curvature_hvr_exponent | G302: -2 | H302: exponent | I302: ISDA SIMM Methodology v2.8+2512 (based on v2.8+2512.2, 13 May 2026) | J302: 2.8+2512 | K302: 2026-07-11 | L302: B | M302: 11(d) | N302: IR curvature margin multiplied by HVR_IR^-2 | O302: 8 | P302: https://www.isda.org/a/hhkiE/ISDA-SIMM_v2.82512_PUBLIC.pdf | Q302: 2026-10-02 | R302: 8484d3de7dcb5280b6ad6458d051c50f8ccc3370bc279ae1c47a7bccb8064636 | S302: VERIFIED_PRIMARY | T302: two extractors agree (PyMuPDF, markitdown; sequence) + page image check
A303: =B303&"|"&C303&"|"&D303&"|"&E303&"|"&F303 -> 2.8+2512|ALL|vega_sigma_days_numerator|| | B303: 2.8+2512 | C303: ALL | D303: vega_sigma_days_numerator | G303: 365 | H303: days | I303: ISDA SIMM Methodology v2.8+2512 (based on v2.8+2512.2, 13 May 2026) | J303: 2.8+2512 | K303: 2026-07-11 | L303: B | M303: 10(b) | N303: sigma_kj = RW_k sqrt(365/14)/alpha, alpha = Phi^-1(99%), Equity/FX/Commodity | O303: 5 | P303: https://www.isda.org/a/hhkiE/ISDA-SIMM_v2.82512_PUBLIC.pdf | Q303: 2026-10-02 | R303: 8484d3de7dcb5280b6ad6458d051c50f8ccc3370bc279ae1c47a7bccb8064636 | S303: VERIFIED_PRIMARY | T303: two extractors agree (PyMuPDF, markitdown; sequence) + page image check
...

Sheet Parameters_Reg
A1: Regulatory parameters (typed with provenance): schedule IM rates, weights, BCBS 22 Table 2.
A4: asset_class | B4: maturity_low_years | C4: maturity_high_years (1E9 means open ended) | D4: rate_pct | E4: source_doc | F4: section | G4: verification_status | H4: retrieved_on | J4: constant | K4: value | L4: source_doc | M4: citation | N4: verification_status | P4: exceptions | Q4: zone | R4: plus_factor | S4: source
A5: Credit | B5: 0 | C5: 2 | D5: 2 | E5: 12 CFR Part 45 (OCC), eCFR as of 2026-09-30 | F5: Appendix A to Part 45, Table A (Standardized Minimum Gross Initial Margin Requirements) | G5: VERIFIED_PRIMARY | H5: 2026-10-02 | J5: schedule_gross_weight | K5: 0.4 | L5: 12 CFR Part 45 (OCC), eCFR as of 2026-09-30 | M5: 12 CFR Part 45 Appendix A, footnote 1 | N5: VERIFIED_PRIMARY | P5: 0 | Q5: Green | R5: 0 | S5: BCBS 22 Table 2
A6: Credit | B6: 2 | C6: 5 | D6: 5 | E6: 12 CFR Part 45 (OCC), eCFR as of 2026-09-30 | F6: Appendix A to Part 45, Table A (Standardized Minimum Gross Initial Margin Requirements) | G6: VERIFIED_PRIMARY | H6: 2026-10-02 | J6: schedule_ngr_weight | K6: 0.6 | L6: 12 CFR Part 45 (OCC), eCFR as of 2026-09-30 | M6: 12 CFR Part 45 Appendix A, footnote 1 | N6: VERIFIED_PRIMARY | P6: 1 | Q6: Green | R6: 0 | S6: BCBS 22 Table 2
A7: Credit | B7: 5 | C7: 1000000000 | D7: 10 | E7: 12 CFR Part 45 (OCC), eCFR as of 2026-09-30 | F7: Appendix A to Part 45, Table A (Standardized Minimum Gross Initial Margin Requirements) | G7: VERIFIED_PRIMARY | H7: 2026-10-02 | P7: 2 | Q7: Green | R7: 0 | S7: BCBS 22 Table 2
A8: Commodity | B8: 0 | C8: 1000000000 | D8: 15 | E8: 12 CFR Part 45 (OCC), eCFR as of 2026-09-30 | F8: Appendix A to Part 45, Table A (Standardized Minimum Gross Initial Margin Requirements) | G8: VERIFIED_PRIMARY | H8: 2026-10-02 | P8: 3 | Q8: Green | R8: 0 | S8: BCBS 22 Table 2
A9: Equity | B9: 0 | C9: 1000000000 | D9: 15 | E9: 12 CFR Part 45 (OCC), eCFR as of 2026-09-30 | F9: Appendix A to Part 45, Table A (Standardized Minimum Gross Initial Margin Requirements) | G9: VERIFIED_PRIMARY | H9: 2026-10-02 | P9: 4 | Q9: Green | R9: 0 | S9: BCBS 22 Table 2
A10: Foreign exchange | B10: 0 | C10: 1000000000 | D10: 6 | E10: 12 CFR Part 45 (OCC), eCFR as of 2026-09-30 | F10: Appendix A to Part 45, Table A (Standardized Minimum Gross Initial Margin Requirements) | G10: VERIFIED_PRIMARY | H10: 2026-10-02 | P10: 5 | Q10: Yellow | R10: 0.4 | S10: BCBS 22 Table 2
A11: Cross-currency swap | B11: 0 | C11: 2 | D11: 1 | E11: 12 CFR Part 45 (OCC), eCFR as of 2026-09-30 | F11: Appendix A to Part 45, Table A (Standardized Minimum Gross Initial Margin Requirements) | G11: VERIFIED_PRIMARY | H11: 2026-10-02 | P11: 6 | Q11: Yellow | R11: 0.5 | S11: BCBS 22 Table 2
A12: Cross-currency swap | B12: 2 | C12: 5 | D12: 2 | E12: 12 CFR Part 45 (OCC), eCFR as of 2026-09-30 | F12: Appendix A to Part 45, Table A (Standardized Minimum Gross Initial Margin Requirements) | G12: VERIFIED_PRIMARY | H12: 2026-10-02 | P12: 7 | Q12: Yellow | R12: 0.65 | S12: BCBS 22 Table 2
A13: Cross-currency swap | B13: 5 | C13: 1000000000 | D13: 4 | E13: 12 CFR Part 45 (OCC), eCFR as of 2026-09-30 | F13: Appendix A to Part 45, Table A (Standardized Minimum Gross Initial Margin Requirements) | G13: VERIFIED_PRIMARY | H13: 2026-10-02 | P13: 8 | Q13: Yellow | R13: 0.75 | S13: BCBS 22 Table 2
A14: Interest rate | B14: 0 | C14: 2 | D14: 1 | E14: 12 CFR Part 45 (OCC), eCFR as of 2026-09-30 | F14: Appendix A to Part 45, Table A (Standardized Minimum Gross Initial Margin Requirements) | G14: VERIFIED_PRIMARY | H14: 2026-10-02 | P14: 9 | Q14: Yellow | R14: 0.85 | S14: BCBS 22 Table 2
A15: Interest rate | B15: 2 | C15: 5 | D15: 2 | E15: 12 CFR Part 45 (OCC), eCFR as of 2026-09-30 | F15: Appendix A to Part 45, Table A (Standardized Minimum Gross Initial Margin Requirements) | G15: VERIFIED_PRIMARY | H15: 2026-10-02 | P15: 10 | Q15: Red | R15: 1 | S15: BCBS 22 Table 2
A16: Interest rate | B16: 5 | C16: 1000000000 | D16: 4 | E16: 12 CFR Part 45 (OCC), eCFR as of 2026-09-30 | F16: Appendix A to Part 45, Table A (Standardized Minimum Gross Initial Margin Requirements) | G16: VERIFIED_PRIMARY | H16: 2026-10-02
A17: Other | B17: 0 | C17: 1000000000 | D17: 15 | E17: 12 CFR Part 45 (OCC), eCFR as of 2026-09-30 | F17: Appendix A to Part 45, Table A (Standardized Minimum Gross Initial Margin Requirements) | G17: VERIFIED_PRIMARY | H17: 2026-10-02

Sheet Portfolio
A1: Sample portfolio and PV (typed from Python; SYNTHETIC). PV is in USD.
A4: trade_id | B4: counterparty | C4: product | D4: ccy | E4: ccy2 | F4: notional | G4: direction | H4: start | I4: maturity | J4: expiry | K4: strike | L4: opt_type | M4: pv
A5: IRS_USD_2Y | B5: CPTY_B | C5: IRS | D5: USD | F5: 60000000 | G5: 1 | H5: 0 | I5: 2 | K5: 0.039627916 | M5: 475770.62
A6: IRS_USD_5Y | B6: CPTY_B | C6: IRS | D6: USD | F6: 40000000 | G6: -1 | H6: 0 | I6: 5 | K6: 0.039874146 | M6: -1042407.8
A7: IRS_USD_10Y | B7: CPTY_B | C7: IRS | D7: USD | F7: 25000000 | G7: 1 | H7: 0 | I7: 10 | K7: 0.042921378 | M7: 904650.83
A8: IRS_USD_30Y | B8: CPTY_B | C8: IRS | D8: USD | F8: 10000000 | G8: -1 | H8: 0 | I8: 30 | K8: 0.04576694 | M8: -539620.16
A9: IRS_EUR_5Y | B9: CPTY_B | C9: IRS | D9: EUR | F9: 30000000 | G9: 1 | H9: 0 | I9: 5 | K9: 0.024061862 | M9: 362788
A10: IRS_EUR_10Y | B10: CPTY_B | C10: IRS | D10: EUR | F10: 20000000 | G10: -1 | H10: 0 | I10: 10 | K10: 0.02748556 | M10: 179763.15
A11: IRS_GBP_7Y | B11: CPTY_B | C11: IRS | D11: GBP | F11: 25000000 | G11: 1 | H11: 0 | I11: 7 | K11: 0.041455329 | M11: 152323.83
A12: IRS_JPY_10Y | B12: CPTY_B | C12: IRS | D12: JPY | F12: 4000000000 | G12: -1 | H12: 0 | I12: 10 | K12: 0.013896767 | M12: -865234.25
A13: IRS_MXN_3Y | B13: CPTY_B | C13: IRS | D13: MXN | F13: 500000000 | G13: 1 | H13: 0 | I13: 3 | K13: 0.088246362 | M13: 1891311.2
A14: SWPT_USD_1Yx5Y | B14: CPTY_B | C14: SWAPTION | D14: USD | F14: 50000000 | G14: 1 | H14: 1 | I14: 6 | J14: 1 | K14: 0.042878843 | L14: payer | M14: 1213662.4
A15: SWPT_EUR_4Yx10Y | B15: CPTY_B | C15: SWAPTION | D15: EUR | F15: 30000000 | G15: 1 | H15: 4 | I15: 14 | J15: 4 | K15: 0.02697646 | L15: receiver | M15: 2062559.8
A16: SWPT_GBP_5Yx5Y | B16: CPTY_B | C16: SWAPTION | D16: GBP | F16: 25000000 | G16: -1 | H16: 5 | I16: 10 | J16: 5 | K16: 0.042747772 | L16: payer | M16: -1037840.3
A17: FXF_EURUSD_6M | B17: CPTY_B | C17: FXFWD | D17: EUR | E17: USD | F17: 25000000 | G17: 1 | H17: 0 | I17: 0.5 | K17: 1.0924328 | M17: 3371586.7
A18: FXF_GBPUSD_1Y | B18: CPTY_B | C18: FXFWD | D18: GBP | E18: USD | F18: 15000000 | G18: -1 | H18: 0 | I18: 1 | K18: 1.2629756 | M18: -299975.15
A19: FXF_USDJPY_3M | B19: CPTY_B | C19: FXFWD | D19: USD | E19: JPY | F19: 20000000 | G19: 1 | H19: 0 | I19: 0.25 | K19: 148.35089 | M19: -250225.03
A20: FXF_USDMXN_6M | B20: CPTY_B | C20: FXFWD | D20: USD | E20: MXN | F20: 10000000 | G20: -1 | H20: 0 | I20: 0.5 | K20: 18.635531 | M20: 918421.29
A21: FXO_EURUSD_C3M | B21: CPTY_B | C21: FXOPT | D21: EUR | E21: USD | F21: 20000000 | G21: 1 | H21: 0 | I21: 0.25 | J21: 0.25 | K21: 1.094884 | L21: call | M21: 2572583.6
A22: FXO_USDMXN_C1Y | B22: CPTY_B | C22: FXOPT | D22: USD | E22: MXN | F22: 10000000 | G22: 1 | H22: 0 | I22: 1 | J22: 1 | K22: 19.689494 | L22: call | M22: 187279.15
A23: FXO_GBPUSD_STRADDLE_C | B23: CPTY_B | C23: FXOPT | D23: GBP | E23: USD | F23: 15000000 | G23: 1 | H23: 0 | I23: 0.5 | J23: 0.5 | K23: 1.2704373 | L23: call | M23: 796644.11
A24: FXO_GBPUSD_STRADDLE_P | B24: CPTY_B | C24: FXOPT | D24: GBP | E24: USD | F24: 15000000 | G24: 1 | H24: 0 | I24: 0.5 | J24: 0.5 | K24: 1.2704373 | L24: put | M24: 627283.68

Sheet Sensitivities
A1: CRIF (typed from Python) with live helper columns, and closed-form Bachelier and Garman-Kohlhagen checks (columns O to P).
A4: TradeID | B4: RiskType | C4: Qualifier | D4: Bucket | E4: Label1 | F4: Label2 | G4: Amount | H4: AmountCurrency | I4: AmountUSD | J4: SigmaMarket | K4: fx_vega_per_unit_vol_usd | L4: sf_of_vertex | M4: fx_vega_x_sf | O4: Bachelier swaption (typed inputs, live formulas)
A5: IRS_USD_2Y | B5: Risk_IRCurve | C5: USD | D5: regular_well_traded | E5: 1y | F5: OIS | G5: -22.329121 | H5: USD | I5: -22.329121 | K5: =IF(AND(B5="Risk_FXVol",ISNUMBER(J5)),I5/J5,0) -> 0 | L5: =IF(OR(B5="Risk_FXVol",B5="Risk_IRVol"),INDEX(SIMM_Curvature!$D$15:$D$26,MATCH(E5,SIMM_Curvature!$A$15:$A$26,0)),0) -> 0 | M5: =K5*L5 -> 0 | O5: trade_id | P5: SWPT_USD_1Yx5Y
A6: IRS_USD_2Y | B6: Risk_IRCurve | C6: USD | D6: regular_well_traded | E6: 2y | F6: OIS | G6: 11213.54 | H6: USD | I6: 11213.54 | K6: =IF(AND(B6="Risk_FXVol",ISNUMBER(J6)),I6/J6,0) -> 0 | L6: =IF(OR(B6="Risk_FXVol",B6="Risk_IRVol"),INDEX(SIMM_Curvature!$D$15:$D$26,MATCH(E6,SIMM_Curvature!$A$15:$A$26,0)),0) -> 0 | M6: =K6*L6 -> 0 | O6: notional | P6: 50000000
A7: IRS_USD_5Y | B7: Risk_IRCurve | C7: USD | D7: regular_well_traded | E7: 1y | F7: OIS | G7: 18.262285 | H7: USD | I7: 18.262285 | K7: =IF(AND(B7="Risk_FXVol",ISNUMBER(J7)),I7/J7,0) -> 0 | L7: =IF(OR(B7="Risk_FXVol",B7="Risk_IRVol"),INDEX(SIMM_Curvature!$D$15:$D$26,MATCH(E7,SIMM_Curvature!$A$15:$A$26,0)),0) -> 0 | M7: =K7*L7 -> 0 | O7: direction | P7: 1
A8: IRS_USD_5Y | B8: Risk_IRCurve | C8: USD | D8: regular_well_traded | E8: 2y | F8: OIS | G8: 37.277051 | H8: USD | I8: 37.277051 | K8: =IF(AND(B8="Risk_FXVol",ISNUMBER(J8)),I8/J8,0) -> 0 | L8: =IF(OR(B8="Risk_FXVol",B8="Risk_IRVol"),INDEX(SIMM_Curvature!$D$15:$D$26,MATCH(E8,SIMM_Curvature!$A$15:$A$26,0)),0) -> 0 | M8: =K8*L8 -> 0 | O8: forward swap rate | P8: 0.046903477
A9: IRS_USD_5Y | B9: Risk_IRCurve | C9: USD | D9: regular_well_traded | E9: 3y | F9: OIS | G9: 96.183415 | H9: USD | I9: 96.183415 | K9: =IF(AND(B9="Risk_FXVol",ISNUMBER(J9)),I9/J9,0) -> 0 | L9: =IF(OR(B9="Risk_FXVol",B9="Risk_IRVol"),INDEX(SIMM_Curvature!$D$15:$D$26,MATCH(E9,SIMM_Curvature!$A$15:$A$26,0)),0) -> 0 | M9: =K9*L9 -> 0 | O9: annuity | P9: 4.1934646
A10: IRS_USD_5Y | B10: Risk_IRCurve | C10: USD | D10: regular_well_traded | E10: 5y | F10: OIS | G10: -17421.686 | H10: USD | I10: -17421.686 | K10: =IF(AND(B10="Risk_FXVol",ISNUMBER(J10)),I10/J10,0) -> 0 | L10: =IF(OR(B10="Risk_FXVol",B10="Risk_IRVol"),INDEX(SIMM_Curvature!$D$15:$D$26,MATCH(E10,SIMM_Curvature!$A$15:$A$26,0)),0) -> 0 | M10: =K10*L10 -> 0 | O10: strike | P10: 0.042878843
A11: IRS_USD_10Y | B11: Risk_IRCurve | C11: USD | D11: regular_well_traded | E11: 1y | F11: OIS | G11: -6.9223531 | H11: USD | I11: -6.9223531 | K11: =IF(AND(B11="Risk_FXVol",ISNUMBER(J11)),I11/J11,0) -> 0 | L11: =IF(OR(B11="Risk_FXVol",B11="Risk_IRVol"),INDEX(SIMM_Curvature!$D$15:$D$26,MATCH(E11,SIMM_Curvature!$A$15:$A$26,0)),0) -> 0 | M11: =K11*L11 -> 0 | O11: normal vol (bp) | P11: 85.332318
A12: IRS_USD_10Y | B12: Risk_IRCurve | C12: USD | D12: regular_well_traded | E12: 2y | F12: OIS | G12: -14.129935 | H12: USD | I12: -14.129935 | K12: =IF(AND(B12="Risk_FXVol",ISNUMBER(J12)),I12/J12,0) -> 0 | L12: =IF(OR(B12="Risk_FXVol",B12="Risk_IRVol"),INDEX(SIMM_Curvature!$D$15:$D$26,MATCH(E12,SIMM_Curvature!$A$15:$A$26,0)),0) -> 0 | M12: =K12*L12 -> 0 | O12: expiry (years) | P12: 1
A13: IRS_USD_10Y | B13: Risk_IRCurve | C13: USD | D13: regular_well_traded | E13: 3y | F13: OIS | G13: -36.458501 | H13: USD | I13: -36.458501 | K13: =IF(AND(B13="Risk_FXVol",ISNUMBER(J13)),I13/J13,0) -> 0 | L13: =IF(OR(B13="Risk_FXVol",B13="Risk_IRVol"),INDEX(SIMM_Curvature!$D$15:$D$26,MATCH(E13,SIMM_Curvature!$A$15:$A$26,0)),0) -> 0 | M13: =K13*L13 -> 0 | O13: fx to USD | P13: 1
A14: IRS_USD_10Y | B14: Risk_IRCurve | C14: USD | D14: regular_well_traded | E14: 5y | F14: OIS | G14: -165.78332 | H14: USD | I14: -165.78332 | K14: =IF(AND(B14="Risk_FXVol",ISNUMBER(J14)),I14/J14,0) -> 0 | L14: =IF(OR(B14="Risk_FXVol",B14="Risk_IRVol"),INDEX(SIMM_Curvature!$D$15:$D$26,MATCH(E14,SIMM_Curvature!$A$15:$A$26,0)),0) -> 0 | M14: =K14*L14 -> 0 | O14: normal vol (fraction) | P14: =$P$11/10000 -> 0.0085332318
A15: IRS_USD_10Y | B15: Risk_IRCurve | C15: USD | D15: regular_well_traded | E15: 10y | F15: OIS | G15: 19420.058 | H15: USD | I15: 19420.058 | K15: =IF(AND(B15="Risk_FXVol",ISNUMBER(J15)),I15/J15,0) -> 0 | L15: =IF(OR(B15="Risk_FXVol",B15="Risk_IRVol"),INDEX(SIMM_Curvature!$D$15:$D$26,MATCH(E15,SIMM_Curvature!$A$15:$A$26,0)),0) -> 0 | M15: =K15*L15 -> 0 | O15: vol * sqrt(T) | P15: =$P$14*SQRT($P$12) -> 0.0085332318
A16: IRS_USD_30Y | B16: Risk_IRCurve | C16: USD | D16: regular_well_traded | E16: 1y | F16: OIS | G16: 0.78593511 | H16: USD | I16: 0.78593511 | K16: =IF(AND(B16="Risk_FXVol",ISNUMBER(J16)),I16/J16,0) -> 0 | L16: =IF(OR(B16="Risk_FXVol",B16="Risk_IRVol"),INDEX(SIMM_Curvature!$D$15:$D$26,MATCH(E16,SIMM_Curvature!$A$15:$A$26,0)),0) -> 0 | M16: =K16*L16 -> 0 | O16: d | P16: =($P$8-$P$10)/$P$15 -> 0.47164239
A17: IRS_USD_30Y | B17: Risk_IRCurve | C17: USD | D17: regular_well_traded | E17: 2y | F17: OIS | G17: 1.6042539 | H17: USD | I17: 1.6042539 | K17: =IF(AND(B17="Risk_FXVol",ISNUMBER(J17)),I17/J17,0) -> 0 | L17: =IF(OR(B17="Risk_FXVol",B17="Risk_IRVol"),INDEX(SIMM_Curvature!$D$15:$D$26,MATCH(E17,SIMM_Curvature!$A$15:$A$26,0)),0) -> 0 | M17: =K17*L17 -> 0 | O17: pdf(d) | P17: =EXP(-0.5*$P$16^2)/SQRT(2*PI()) -> 0.3569492
A18: IRS_USD_30Y | B18: Risk_IRCurve | C18: USD | D18: regular_well_traded | E18: 3y | F18: OIS | G18: 4.1393455 | H18: USD | I18: 4.1393455 | K18: =IF(AND(B18="Risk_FXVol",ISNUMBER(J18)),I18/J18,0) -> 0 | L18: =IF(OR(B18="Risk_FXVol",B18="Risk_IRVol"),INDEX(SIMM_Curvature!$D$15:$D$26,MATCH(E18,SIMM_Curvature!$A$15:$A$26,0)),0) -> 0 | M18: =K18*L18 -> 0 | O18: vega per 1bp (USD) | P18: =$P$6*$P$7*$P$9*SQRT($P$12)*$P$17*0.0001*$P$13 -> 7484.2691
A19: IRS_USD_30Y | B19: Risk_IRCurve | C19: USD | D19: regular_well_traded | E19: 5y | F19: OIS | G19: 18.82234 | H19: USD | I19: 18.82234 | K19: =IF(AND(B19="Risk_FXVol",ISNUMBER(J19)),I19/J19,0) -> 0 | L19: =IF(OR(B19="Risk_FXVol",B19="Risk_IRVol"),INDEX(SIMM_Curvature!$D$15:$D$26,MATCH(E19,SIMM_Curvature!$A$15:$A$26,0)),0) -> 0 | M19: =K19*L19 -> 0 | O19: CRIF vega amount, closed form (USD) | P19: =$P$18*$P$11 -> 638650.03
A20: IRS_USD_30Y | B20: Risk_IRCurve | C20: USD | D20: regular_well_traded | E20: 10y | F20: OIS | G20: 49.88731 | H20: USD | I20: 49.88731 | K20: =IF(AND(B20="Risk_FXVol",ISNUMBER(J20)),I20/J20,0) -> 0 | L20: =IF(OR(B20="Risk_FXVol",B20="Risk_IRVol"),INDEX(SIMM_Curvature!$D$15:$D$26,MATCH(E20,SIMM_Curvature!$A$15:$A$26,0)),0) -> 0 | M20: =K20*L20 -> 0 | O20: CRIF vega amount, typed CRIF (USD) | P20: =SUMIFS(Sensitivities!$I$5:$I$100,Sensitivities!$A$5:$A$100,$P$5,Sensitivities!$B$5:$B$100,"Risk_IRVol") -> 638647.77
A21: IRS_USD_30Y | B21: Risk_IRCurve | C21: USD | D21: regular_well_traded | E21: 15y | F21: OIS | G21: 84.79268 | H21: USD | I21: 84.79268 | K21: =IF(AND(B21="Risk_FXVol",ISNUMBER(J21)),I21/J21,0) -> 0 | L21: =IF(OR(B21="Risk_FXVol",B21="Risk_IRVol"),INDEX(SIMM_Curvature!$D$15:$D$26,MATCH(E21,SIMM_Curvature!$A$15:$A$26,0)),0) -> 0 | M21: =K21*L21 -> 0 | O21: PV, closed form payer (USD) | P21: =$P$6*$P$7*$P$9*(($P$8-$P$10)*NORMSDIST($P$16)+$P$15*$P$17)*$P$13 -> 1213662.4
A22: IRS_USD_30Y | B22: Risk_IRCurve | C22: USD | D22: regular_well_traded | E22: 20y | F22: OIS | G22: 221.01489 | H22: USD | I22: 221.01489 | K22: =IF(AND(B22="Risk_FXVol",ISNUMBER(J22)),I22/J22,0) -> 0 | L22: =IF(OR(B22="Risk_FXVol",B22="Risk_IRVol"),INDEX(SIMM_Curvature!$D$15:$D$26,MATCH(E22,SIMM_Curvature!$A$15:$A$26,0)),0) -> 0 | M22: =K22*L22 -> 0 | O22: PV, typed portfolio (USD) | P22: =INDEX(Portfolio!$M$5:$M$24,MATCH($P$5,Portfolio!$A$5:$A$24,0)) -> 1213662.4
A23: IRS_USD_30Y | B23: Risk_IRCurve | C23: USD | D23: regular_well_traded | E23: 30y | F23: OIS | G23: -15368.977 | H23: USD | I23: -15368.977 | K23: =IF(AND(B23="Risk_FXVol",ISNUMBER(J23)),I23/J23,0) -> 0 | L23: =IF(OR(B23="Risk_FXVol",B23="Risk_IRVol"),INDEX(SIMM_Curvature!$D$15:$D$26,MATCH(E23,SIMM_Curvature!$A$15:$A$26,0)),0) -> 0 | M23: =K23*L23 -> 0
A24: IRS_EUR_5Y | B24: Risk_IRCurve | C24: EUR | D24: regular_well_traded | E24: 1y | F24: OIS | G24: -5.5068625 | H24: EUR | I24: -6.715979 | K24: =IF(AND(B24="Risk_FXVol",ISNUMBER(J24)),I24/J24,0) -> 0 | L24: =IF(OR(B24="Risk_FXVol",B24="Risk_IRVol"),INDEX(SIMM_Curvature!$D$15:$D$26,MATCH(E24,SIMM_Curvature!$A$15:$A$26,0)),0) -> 0 | M24: =K24*L24 -> 0
A25: IRS_EUR_5Y | B25: Risk_IRCurve | C25: EUR | D25: regular_well_traded | E25: 2y | F25: OIS | G25: -11.146153 | H25: EUR | I25: -13.593462 | K25: =IF(AND(B25="Risk_FXVol",ISNUMBER(J25)),I25/J25,0) -> 0 | L25: =IF(OR(B25="Risk_FXVol",B25="Risk_IRVol"),INDEX(SIMM_Curvature!$D$15:$D$26,MATCH(E25,SIMM_Curvature!$A$15:$A$26,0)),0) -> 0 | M25: =K25*L25 -> 0
A26: IRS_EUR_5Y | B26: Risk_IRCurve | C26: EUR | D26: regular_well_traded | E26: 3y | F26: OIS | G26: -28.396314 | H26: EUR | I26: -34.631163 | K26: =IF(AND(B26="Risk_FXVol",ISNUMBER(J26)),I26/J26,0) -> 0 | L26: =IF(OR(B26="Risk_FXVol",B26="Risk_IRVol"),INDEX(SIMM_Curvature!$D$15:$D$26,MATCH(E26,SIMM_Curvature!$A$15:$A$26,0)),0) -> 0 | M26: =K26*L26 -> 0 | O26: Garman-Kohlhagen FX call (typed inputs, live formulas)
A27: IRS_EUR_5Y | B27: Risk_IRCurve | C27: EUR | D27: regular_well_traded | E27: 5y | F27: OIS | G27: 13859.96 | H27: EUR | I27: 16903.127 | K27: =IF(AND(B27="Risk_FXVol",ISNUMBER(J27)),I27/J27,0) -> 0 | L27: =IF(OR(B27="Risk_FXVol",B27="Risk_IRVol"),INDEX(SIMM_Curvature!$D$15:$D$26,MATCH(E27,SIMM_Curvature!$A$15:$A$26,0)),0) -> 0 | M27: =K27*L27 -> 0 | O27: trade_id | P27: FXO_GBPUSD_STRADDLE_C
A28: IRS_EUR_5Y | B28: Risk_FX | C28: EUR | G28: 3627.88 | H28: USD | I28: 3627.88 | K28: =IF(AND(B28="Risk_FXVol",ISNUMBER(J28)),I28/J28,0) -> 0 | L28: =IF(OR(B28="Risk_FXVol",B28="Risk_IRVol"),INDEX(SIMM_Curvature!$D$15:$D$26,MATCH(E28,SIMM_Curvature!$A$15:$A$26,0)),0) -> 0 | M28: =K28*L28 -> 0 | O28: notional (base) | P28: 15000000
A29: IRS_EUR_10Y | B29: Risk_IRCurve | C29: EUR | D29: regular_well_traded | E29: 1y | F29: OIS | G29: -1.2634655 | H29: EUR | I29: -1.5408788 | K29: =IF(AND(B29="Risk_FXVol",ISNUMBER(J29)),I29/J29,0) -> 0 | L29: =IF(OR(B29="Risk_FXVol",B29="Risk_IRVol"),INDEX(SIMM_Curvature!$D$15:$D$26,MATCH(E29,SIMM_Curvature!$A$15:$A$26,0)),0) -> 0 | M29: =K29*L29 -> 0 | O29: direction | P29: 1
A30: IRS_EUR_10Y | B30: Risk_IRCurve | C30: EUR | D30: regular_well_traded | E30: 2y | F30: OIS | G30: -2.5573147 | H30: EUR | I30: -3.1188125 | K30: =IF(AND(B30="Risk_FXVol",ISNUMBER(J30)),I30/J30,0) -> 0 | L30: =IF(OR(B30="Risk_FXVol",B30="Risk_IRVol"),INDEX(SIMM_Curvature!$D$15:$D$26,MATCH(E30,SIMM_Curvature!$A$15:$A$26,0)),0) -> 0 | M30: =K30*L30 -> 0 | O30: forward | P30: 1.2819657
A31: IRS_EUR_10Y | B31: Risk_IRCurve | C31: EUR | D31: regular_well_traded | E31: 3y | F31: OIS | G31: -6.5151022 | H31: EUR | I31: -7.9455932 | K31: =IF(AND(B31="Risk_FXVol",ISNUMBER(J31)),I31/J31,0) -> 0 | L31: =IF(OR(B31="Risk_FXVol",B31="Risk_IRVol"),INDEX(SIMM_Curvature!$D$15:$D$26,MATCH(E31,SIMM_Curvature!$A$15:$A$26,0)),0) -> 0 | M31: =K31*L31 -> 0 | O31: strike | P31: 1.2704373
A32: IRS_EUR_10Y | B32: Risk_IRCurve | C32: EUR | D32: regular_well_traded | E32: 5y | F32: OIS | G32: -28.690101 | H32: EUR | I32: -34.989455 | K32: =IF(AND(B32="Risk_FXVol",ISNUMBER(J32)),I32/J32,0) -> 0 | L32: =IF(OR(B32="Risk_FXVol",B32="Risk_IRVol"),INDEX(SIMM_Curvature!$D$15:$D$26,MATCH(E32,SIMM_Curvature!$A$15:$A$26,0)),0) -> 0 | M32: =K32*L32 -> 0 | O32: lognormal vol | P32: 0.13405935
A33: IRS_EUR_10Y | B33: Risk_IRCurve | C33: EUR | D33: regular_well_traded | E33: 10y | F33: OIS | G33: -17420.253 | H33: EUR | I33: -21245.138 | K33: =IF(AND(B33="Risk_FXVol",ISNUMBER(J33)),I33/J33,0) -> 0 | L33: =IF(OR(B33="Risk_FXVol",B33="Risk_IRVol"),INDEX(SIMM_Curvature!$D$15:$D$26,MATCH(E33,SIMM_Curvature!$A$15:$A$26,0)),0) -> 0 | M33: =K33*L33 -> 0 | O33: expiry (years) | P33: 0.5
A34: IRS_EUR_10Y | B34: Risk_FX | C34: EUR | G34: 1797.6315 | H34: USD | I34: 1797.6315 | K34: =IF(AND(B34="Risk_FXVol",ISNUMBER(J34)),I34/J34,0) -> 0 | L34: =IF(OR(B34="Risk_FXVol",B34="Risk_IRVol"),INDEX(SIMM_Curvature!$D$15:$D$26,MATCH(E34,SIMM_Curvature!$A$15:$A$26,0)),0) -> 0 | M34: =K34*L34 -> 0 | O34: discount factor, quote ccy | P34: 0.97938484
A35: IRS_GBP_7Y | B35: Risk_IRCurve | C35: GBP | D35: regular_well_traded | E35: 1y | F35: OIS | G35: -10.719322 | H35: GBP | I35: -13.716418 | K35: =IF(AND(B35="Risk_FXVol",ISNUMBER(J35)),I35/J35,0) -> 0 | L35: =IF(OR(B35="Risk_FXVol",B35="Risk_IRVol"),INDEX(SIMM_Curvature!$D$15:$D$26,MATCH(E35,SIMM_Curvature!$A$15:$A$26,0)),0) -> 0 | M35: =K35*L35 -> 0 | O35: discount factor, base ccy | P35: 0.98119738
A36: IRS_GBP_7Y | B36: Risk_IRCurve | C36: GBP | D36: regular_well_traded | E36: 2y | F36: OIS | G36: -21.837346 | H36: GBP | I36: -27.943014 | K36: =IF(AND(B36="Risk_FXVol",ISNUMBER(J36)),I36/J36,0) -> 0 | L36: =IF(OR(B36="Risk_FXVol",B36="Risk_IRVol"),INDEX(SIMM_Curvature!$D$15:$D$26,MATCH(E36,SIMM_Curvature!$A$15:$A$26,0)),0) -> 0 | M36: =K36*L36 -> 0 | O36: spot of base in USD | P36: 1.2795975
A37: IRS_GBP_7Y | B37: Risk_IRCurve | C37: GBP | D37: regular_well_traded | E37: 3y | F37: OIS | G37: -56.235414 | H37: GBP | I37: -71.958697 | K37: =IF(AND(B37="Risk_FXVol",ISNUMBER(J37)),I37/J37,0) -> 0 | L37: =IF(OR(B37="Risk_FXVol",B37="Risk_IRVol"),INDEX(SIMM_Curvature!$D$15:$D$26,MATCH(E37,SIMM_Curvature!$A$15:$A$26,0)),0) -> 0 | M37: =K37*L37 -> 0 | O37: quote ccy to USD | P37: 1
A38: IRS_GBP_7Y | B38: Risk_IRCurve | C38: GBP | D38: regular_well_traded | E38: 5y | F38: OIS | G38: 8895.5289 | H38: GBP | I38: 11382.697 | K38: =IF(AND(B38="Risk_FXVol",ISNUMBER(J38)),I38/J38,0) -> 0 | L38: =IF(OR(B38="Risk_FXVol",B38="Risk_IRVol"),INDEX(SIMM_Curvature!$D$15:$D$26,MATCH(E38,SIMM_Curvature!$A$15:$A$26,0)),0) -> 0 | M38: =K38*L38 -> 0 | O38: vol * sqrt(T) | P38: =$P$32*SQRT($P$33) -> 0.094794273
A39: IRS_GBP_7Y | B39: Risk_IRCurve | C39: GBP | D39: regular_well_traded | E39: 10y | F39: OIS | G39: 6054.1928 | H39: GBP | I39: 7746.9301 | K39: =IF(AND(B39="Risk_FXVol",ISNUMBER(J39)),I39/J39,0) -> 0 | L39: =IF(OR(B39="Risk_FXVol",B39="Risk_IRVol"),INDEX(SIMM_Curvature!$D$15:$D$26,MATCH(E39,SIMM_Curvature!$A$15:$A$26,0)),0) -> 0 | M39: =K39*L39 -> 0 | O39: d1 | P39: =(LN($P$30/$P$31)+0.5*$P$38^2)/$P$38 -> 0.14269187
A40: IRS_GBP_7Y | B40: Risk_FX | C40: GBP | G40: 1523.2383 | H40: USD | I40: 1523.2383 | K40: =IF(AND(B40="Risk_FXVol",ISNUMBER(J40)),I40/J40,0) -> 0 | L40: =IF(OR(B40="Risk_FXVol",B40="Risk_IRVol"),INDEX(SIMM_Curvature!$D$15:$D$26,MATCH(E40,SIMM_Curvature!$A$15:$A$26,0)),0) -> 0 | M40: =K40*L40 -> 0 | O40: d2 | P40: =$P$39-$P$38 -> 0.0478976
A41: IRS_JPY_10Y | B41: Risk_IRCurve | C41: JPY | D41: regular_low_vol | E41: 1y | F41: OIS | G41: 1186.7528 | H41: JPY | I41: 8.0344351 | K41: =IF(AND(B41="Risk_FXVol",ISNUMBER(J41)),I41/J41,0) -> 0 | L41: =IF(OR(B41="Risk_FXVol",B41="Risk_IRVol"),INDEX(SIMM_Curvature!$D$15:$D$26,MATCH(E41,SIMM_Curvature!$A$15:$A$26,0)),0) -> 0 | M41: =K41*L41 -> 0 | O41: PV, closed form (USD) | P41: =$P$28*$P$29*$P$34*($P$30*NORMSDIST($P$39)-$P$31*NORMSDIST($P$40))*$P$37 -> 796644.11
A42: IRS_JPY_10Y | B42: Risk_IRCurve | C42: JPY | D42: regular_low_vol | E42: 2y | F42: OIS | G42: 2381.7844 | H42: JPY | I42: 16.124919 | K42: =IF(AND(B42="Risk_FXVol",ISNUMBER(J42)),I42/J42,0) -> 0 | L42: =IF(OR(B42="Risk_FXVol",B42="Risk_IRVol"),INDEX(SIMM_Curvature!$D$15:$D$26,MATCH(E42,SIMM_Curvature!$A$15:$A$26,0)),0) -> 0 | M42: =K42*L42 -> 0 | O42: CRIF vega amount, closed form (USD) | P42: =$P$28*$P$29*$P$34*$P$30*EXP(-0.5*$P$39^2)/SQRT(2*PI())*SQRT($P$33)*$P$32*$P$37 -> 705004.47
A43: IRS_JPY_10Y | B43: Risk_IRCurve | C43: JPY | D43: regular_low_vol | E43: 3y | F43: OIS | G43: 5991.4 | H43: JPY | I43: 40.562378 | K43: =IF(AND(B43="Risk_FXVol",ISNUMBER(J43)),I43/J43,0) -> 0 | L43: =IF(OR(B43="Risk_FXVol",B43="Risk_IRVol"),INDEX(SIMM_Curvature!$D$15:$D$26,MATCH(E43,SIMM_Curvature!$A$15:$A$26,0)),0) -> 0 | M43: =K43*L43 -> 0 | O43: CRIF FX delta per 1 percent, closed form (USD) | P43: =$P$28*$P$29*$P$35*NORMSDIST($P$39)*$P$36*0.01 -> 104849.94
A44: IRS_JPY_10Y | B44: Risk_IRCurve | C44: JPY | D44: regular_low_vol | E44: 5y | F44: OIS | G44: 25635.376 | H44: JPY | I44: 173.55406 | K44: =IF(AND(B44="Risk_FXVol",ISNUMBER(J44)),I44/J44,0) -> 0 | L44: =IF(OR(B44="Risk_FXVol",B44="Risk_IRVol"),INDEX(SIMM_Curvature!$D$15:$D$26,MATCH(E44,SIMM_Curvature!$A$15:$A$26,0)),0) -> 0 | M44: =K44*L44 -> 0
A45: IRS_JPY_10Y | B45: Risk_IRCurve | C45: JPY | D45: regular_low_vol | E45: 10y | F45: OIS | G45: -3644956.2 | H45: JPY | I45: -24676.718 | K45: =IF(AND(B45="Risk_FXVol",ISNUMBER(J45)),I45/J45,0) -> 0 | L45: =IF(OR(B45="Risk_FXVol",B45="Risk_IRVol"),INDEX(SIMM_Curvature!$D$15:$D$26,MATCH(E45,SIMM_Curvature!$A$15:$A$26,0)),0) -> 0 | M45: =K45*L45 -> 0
A46: IRS_JPY_10Y | B46: Risk_FX | C46: JPY | G46: -8652.3425 | H46: USD | I46: -8652.3425 | K46: =IF(AND(B46="Risk_FXVol",ISNUMBER(J46)),I46/J46,0) -> 0 | L46: =IF(OR(B46="Risk_FXVol",B46="Risk_IRVol"),INDEX(SIMM_Curvature!$D$15:$D$26,MATCH(E46,SIMM_Curvature!$A$15:$A$26,0)),0) -> 0 | M46: =K46*L46 -> 0
A47: IRS_MXN_3Y | B47: Risk_IRCurve | C47: MXN | D47: high_vol | E47: 1y | F47: OIS | G47: -835.84748 | H47: MXN | I47: -50.713107 | K47: =IF(AND(B47="Risk_FXVol",ISNUMBER(J47)),I47/J47,0) -> 0 | L47: =IF(OR(B47="Risk_FXVol",B47="Risk_IRVol"),INDEX(SIMM_Curvature!$D$15:$D$26,MATCH(E47,SIMM_Curvature!$A$15:$A$26,0)),0) -> 0 | M47: =K47*L47 -> 0
A48: IRS_MXN_3Y | B48: Risk_IRCurve | C48: MXN | D48: high_vol | E48: 2y | F48: OIS | G48: -1765.0785 | H48: MXN | I48: -107.09205 | K48: =IF(AND(B48="Risk_FXVol",ISNUMBER(J48)),I48/J48,0) -> 0 | L48: =IF(OR(B48="Risk_FXVol",B48="Risk_IRVol"),INDEX(SIMM_Curvature!$D$15:$D$26,MATCH(E48,SIMM_Curvature!$A$15:$A$26,0)),0) -> 0 | M48: =K48*L48 -> 0
A49: IRS_MXN_3Y | B49: Risk_IRCurve | C49: MXN | D49: high_vol | E49: 3y | F49: OIS | G49: 118641.17 | H49: MXN | I49: 7198.2781 | K49: =IF(AND(B49="Risk_FXVol",ISNUMBER(J49)),I49/J49,0) -> 0 | L49: =IF(OR(B49="Risk_FXVol",B49="Risk_IRVol"),INDEX(SIMM_Curvature!$D$15:$D$26,MATCH(E49,SIMM_Curvature!$A$15:$A$26,0)),0) -> 0 | M49: =K49*L49 -> 0
A50: IRS_MXN_3Y | B50: Risk_FX | C50: MXN | G50: 18913.112 | H50: USD | I50: 18913.112 | K50: =IF(AND(B50="Risk_FXVol",ISNUMBER(J50)),I50/J50,0) -> 0 | L50: =IF(OR(B50="Risk_FXVol",B50="Risk_IRVol"),INDEX(SIMM_Curvature!$D$15:$D$26,MATCH(E50,SIMM_Curvature!$A$15:$A$26,0)),0) -> 0 | M50: =K50*L50 -> 0
A51: SWPT_USD_1Yx5Y | B51: Risk_IRCurve | C51: USD | D51: regular_well_traded | E51: 1y | F51: OIS | G51: -3280.7326 | H51: USD | I51: -3280.7326 | K51: =IF(AND(B51="Risk_FXVol",ISNUMBER(J51)),I51/J51,0) -> 0 | L51: =IF(OR(B51="Risk_FXVol",B51="Risk_IRVol"),INDEX(SIMM_Curvature!$D$15:$D$26,MATCH(E51,SIMM_Curvature!$A$15:$A$26,0)),0) -> 0 | M51: =K51*L51 -> 0
A52: SWPT_USD_1Yx5Y | B52: Risk_IRCurve | C52: USD | D52: regular_well_traded | E52: 2y | F52: OIS | G52: -57.696143 | H52: USD | I52: -57.696143 | K52: =IF(AND(B52="Risk_FXVol",ISNUMBER(J52)),I52/J52,0) -> 0 | L52: =IF(OR(B52="Risk_FXVol",B52="Risk_IRVol"),INDEX(SIMM_Curvature!$D$15:$D$26,MATCH(E52,SIMM_Curvature!$A$15:$A$26,0)),0) -> 0 | M52: =K52*L52 -> 0
A53: SWPT_USD_1Yx5Y | B53: Risk_IRCurve | C53: USD | D53: regular_well_traded | E53: 3y | F53: OIS | G53: -148.8694 | H53: USD | I53: -148.8694 | K53: =IF(AND(B53="Risk_FXVol",ISNUMBER(J53)),I53/J53,0) -> 0 | L53: =IF(OR(B53="Risk_FXVol",B53="Risk_IRVol"),INDEX(SIMM_Curvature!$D$15:$D$26,MATCH(E53,SIMM_Curvature!$A$15:$A$26,0)),0) -> 0 | M53: =K53*L53 -> 0
A54: SWPT_USD_1Yx5Y | B54: Risk_IRCurve | C54: USD | D54: regular_well_traded | E54: 5y | F54: OIS | G54: 13768.379 | H54: USD | I54: 13768.379 | K54: =IF(AND(B54="Risk_FXVol",ISNUMBER(J54)),I54/J54,0) -> 0 | L54: =IF(OR(B54="Risk_FXVol",B54="Risk_IRVol"),INDEX(SIMM_Curvature!$D$15:$D$26,MATCH(E54,SIMM_Curvature!$A$15:$A$26,0)),0) -> 0 | M54: =K54*L54 -> 0
A55: SWPT_USD_1Yx5Y | B55: Risk_IRCurve | C55: USD | D55: regular_well_traded | E55: 10y | F55: OIS | G55: 3586.5837 | H55: USD | I55: 3586.5837 | K55: =IF(AND(B55="Risk_FXVol",ISNUMBER(J55)),I55/J55,0) -> 0 | L55: =IF(OR(B55="Risk_FXVol",B55="Risk_IRVol"),INDEX(SIMM_Curvature!$D$15:$D$26,MATCH(E55,SIMM_Curvature!$A$15:$A$26,0)),0) -> 0 | M55: =K55*L55 -> 0
A56: SWPT_USD_1Yx5Y | B56: Risk_IRVol | C56: USD | D56: regular_well_traded | E56: 1y | G56: 638647.77 | H56: USD | I56: 638647.77 | K56: =IF(AND(B56="Risk_FXVol",ISNUMBER(J56)),I56/J56,0) -> 0 | L56: =IF(OR(B56="Risk_FXVol",B56="Risk_IRVol"),INDEX(SIMM_Curvature!$D$15:$D$26,MATCH(E56,SIMM_Curvature!$A$15:$A$26,0)),0) -> 0.019178082 | M56: =K56*L56 -> 0
A57: SWPT_EUR_4Yx10Y | B57: Risk_IRCurve | C57: EUR | D57: regular_well_traded | E57: 1y | F57: OIS | G57: 4.3696375 | H57: EUR | I57: 5.3290587 | K57: =IF(AND(B57="Risk_FXVol",ISNUMBER(J57)),I57/J57,0) -> 0 | L57: =IF(OR(B57="Risk_FXVol",B57="Risk_IRVol"),INDEX(SIMM_Curvature!$D$15:$D$26,MATCH(E57,SIMM_Curvature!$A$15:$A$26,0)),0) -> 0 | M57: =K57*L57 -> 0
A58: SWPT_EUR_4Yx10Y | B58: Risk_IRCurve | C58: EUR | D58: regular_well_traded | E58: 2y | F58: OIS | G58: 8.8443552 | H58: EUR | I58: 10.78627 | K58: =IF(AND(B58="Risk_FXVol",ISNUMBER(J58)),I58/J58,0) -> 0 | L58: =IF(OR(B58="Risk_FXVol",B58="Risk_IRVol"),INDEX(SIMM_Curvature!$D$15:$D$26,MATCH(E58,SIMM_Curvature!$A$15:$A$26,0)),0) -> 0 | M58: =K58*L58 -> 0
A59: SWPT_EUR_4Yx10Y | B59: Risk_IRCurve | C59: EUR | D59: regular_well_traded | E59: 3y | F59: OIS | G59: 2802.6338 | H59: EUR | I59: 3417.9953 | K59: =IF(AND(B59="Risk_FXVol",ISNUMBER(J59)),I59/J59,0) -> 0 | L59: =IF(OR(B59="Risk_FXVol",B59="Risk_IRVol"),INDEX(SIMM_Curvature!$D$15:$D$26,MATCH(E59,SIMM_Curvature!$A$15:$A$26,0)),0) -> 0 | M59: =K59*L59 -> 0
A60: SWPT_EUR_4Yx10Y | B60: Risk_IRCurve | C60: EUR | D60: regular_well_traded | E60: 5y | F60: OIS | G60: 2499.9146 | H60: EUR | I60: 3048.8094 | K60: =IF(AND(B60="Risk_FXVol",ISNUMBER(J60)),I60/J60,0) -> 0 | L60: =IF(OR(B60="Risk_FXVol",B60="Risk_IRVol"),INDEX(SIMM_Curvature!$D$15:$D$26,MATCH(E60,SIMM_Curvature!$A$15:$A$26,0)),0) -> 0 | M60: =K60*L60 -> 0
A61: SWPT_EUR_4Yx10Y | B61: Risk_IRCurve | C61: EUR | D61: regular_well_traded | E61: 10y | F61: OIS | G61: -4239.0651 | H61: EUR | I61: -5169.8171 | K61: =IF(AND(B61="Risk_FXVol",ISNUMBER(J61)),I61/J61,0) -> 0 | L61: =IF(OR(B61="Risk_FXVol",B61="Risk_IRVol"),INDEX(SIMM_Curvature!$D$15:$D$26,MATCH(E61,SIMM_Curvature!$A$15:$A$26,0)),0) -> 0 | M61: =K61*L61 -> 0
A62: SWPT_EUR_4Yx10Y | B62: Risk_IRCurve | C62: EUR | D62: regular_well_traded | E62: 15y | F62: OIS | G62: -14164.157 | H62: EUR | I62: -17274.115 | K62: =IF(AND(B62="Risk_FXVol",ISNUMBER(J62)),I62/J62,0) -> 0 | L62: =IF(OR(B62="Risk_FXVol",B62="Risk_IRVol"),INDEX(SIMM_Curvature!$D$15:$D$26,MATCH(E62,SIMM_Curvature!$A$15:$A$26,0)),0) -> 0 | M62: =K62*L62 -> 0
A63: SWPT_EUR_4Yx10Y | B63: Risk_FX | C63: EUR | G63: 20625.598 | H63: USD | I63: 20625.598 | K63: =IF(AND(B63="Risk_FXVol",ISNUMBER(J63)),I63/J63,0) -> 0 | L63: =IF(OR(B63="Risk_FXVol",B63="Risk_IRVol"),INDEX(SIMM_Curvature!$D$15:$D$26,MATCH(E63,SIMM_Curvature!$A$15:$A$26,0)),0) -> 0 | M63: =K63*L63 -> 0
A64: SWPT_EUR_4Yx10Y | B64: Risk_IRVol | C64: EUR | D64: regular_well_traded | E64: 3y | G64: 867486.07 | H64: EUR | I64: 1057956 | K64: =IF(AND(B64="Risk_FXVol",ISNUMBER(J64)),I64/J64,0) -> 0 | L64: =IF(OR(B64="Risk_FXVol",B64="Risk_IRVol"),INDEX(SIMM_Curvature!$D$15:$D$26,MATCH(E64,SIMM_Curvature!$A$15:$A$26,0)),0) -> 0.0063926941 | M64: =K64*L64 -> 0
A65: SWPT_EUR_4Yx10Y | B65: Risk_IRVol | C65: EUR | D65: regular_well_traded | E65: 5y | G65: 867486.07 | H65: EUR | I65: 1057956 | K65: =IF(AND(B65="Risk_FXVol",ISNUMBER(J65)),I65/J65,0) -> 0 | L65: =IF(OR(B65="Risk_FXVol",B65="Risk_IRVol"),INDEX(SIMM_Curvature!$D$15:$D$26,MATCH(E65,SIMM_Curvature!$A$15:$A$26,0)),0) -> 0.0038356164 | M65: =K65*L65 -> 0
A66: SWPT_GBP_5Yx5Y | B66: Risk_IRCurve | C66: GBP | D66: regular_well_traded | E66: 1y | F66: OIS | G66: -3.1427218 | H66: GBP | I66: -4.0214191 | K66: =IF(AND(B66="Risk_FXVol",ISNUMBER(J66)),I66/J66,0) -> 0 | L66: =IF(OR(B66="Risk_FXVol",B66="Risk_IRVol"),INDEX(SIMM_Curvature!$D$15:$D$26,MATCH(E66,SIMM_Curvature!$A$15:$A$26,0)),0) -> 0 | M66: =K66*L66 -> 0
A67: SWPT_GBP_5Yx5Y | B67: Risk_IRCurve | C67: GBP | D67: regular_well_traded | E67: 2y | F67: OIS | G67: -6.4023361 | H67: GBP | I67: -8.1924135 | K67: =IF(AND(B67="Risk_FXVol",ISNUMBER(J67)),I67/J67,0) -> 0 | L67: =IF(OR(B67="Risk_FXVol",B67="Risk_IRVol"),INDEX(SIMM_Curvature!$D$15:$D$26,MATCH(E67,SIMM_Curvature!$A$15:$A$26,0)),0) -> 0 | M67: =K67*L67 -> 0
A68: SWPT_GBP_5Yx5Y | B68: Risk_IRCurve | C68: GBP | D68: regular_well_traded | E68: 3y | F68: OIS | G68: -16.487262 | H68: GBP | I68: -21.097059 | K68: =IF(AND(B68="Risk_FXVol",ISNUMBER(J68)),I68/J68,0) -> 0 | L68: =IF(OR(B68="Risk_FXVol",B68="Risk_IRVol"),INDEX(SIMM_Curvature!$D$15:$D$26,MATCH(E68,SIMM_Curvature!$A$15:$A$26,0)),0) -> 0 | M68: =K68*L68 -> 0
A69: SWPT_GBP_5Yx5Y | B69: Risk_IRCurve | C69: GBP | D69: regular_well_traded | E69: 5y | F69: OIS | G69: 5763.3671 | H69: GBP | I69: 7374.7903 | K69: =IF(AND(B69="Risk_FXVol",ISNUMBER(J69)),I69/J69,0) -> 0 | L69: =IF(OR(B69="Risk_FXVol",B69="Risk_IRVol"),INDEX(SIMM_Curvature!$D$15:$D$26,MATCH(E69,SIMM_Curvature!$A$15:$A$26,0)),0) -> 0 | M69: =K69*L69 -> 0
A70: SWPT_GBP_5Yx5Y | B70: Risk_IRCurve | C70: GBP | D70: regular_well_traded | E70: 10y | F70: OIS | G70: -9637.7545 | H70: GBP | I70: -12332.447 | K70: =IF(AND(B70="Risk_FXVol",ISNUMBER(J70)),I70/J70,0) -> 0 | L70: =IF(OR(B70="Risk_FXVol",B70="Risk_IRVol"),INDEX(SIMM_Curvature!$D$15:$D$26,MATCH(E70,SIMM_Curvature!$A$15:$A$26,0)),0) -> 0 | M70: =K70*L70 -> 0
A71: SWPT_GBP_5Yx5Y | B71: Risk_FX | C71: GBP | G71: -10378.403 | H71: USD | I71: -10378.403 | K71: =IF(AND(B71="Risk_FXVol",ISNUMBER(J71)),I71/J71,0) -> 0 | L71: =IF(OR(B71="Risk_FXVol",B71="Risk_IRVol"),INDEX(SIMM_Curvature!$D$15:$D$26,MATCH(E71,SIMM_Curvature!$A$15:$A$26,0)),0) -> 0 | M71: =K71*L71 -> 0
A72: SWPT_GBP_5Yx5Y | B72: Risk_IRVol | C72: GBP | D72: regular_well_traded | E72: 5y | G72: -806056.68 | H72: GBP | I72: -1031428.1 | K72: =IF(AND(B72="Risk_FXVol",ISNUMBER(J72)),I72/J72,0) -> 0 | L72: =IF(OR(B72="Risk_FXVol",B72="Risk_IRVol"),INDEX(SIMM_Curvature!$D$15:$D$26,MATCH(E72,SIMM_Curvature!$A$15:$A$26,0)),0) -> 0.0038356164 | M72: =K72*L72 -> 0
A73: FXF_EURUSD_6M | B73: Risk_IRCurve | C73: EUR | D73: regular_well_traded | E73: 6m | F73: OIS | G73: -1219.8661 | H73: EUR | I73: -1487.7065 | K73: =IF(AND(B73="Risk_FXVol",ISNUMBER(J73)),I73/J73,0) -> 0 | L73: =IF(OR(B73="Risk_FXVol",B73="Risk_IRVol"),INDEX(SIMM_Curvature!$D$15:$D$26,MATCH(E73,SIMM_Curvature!$A$15:$A$26,0)),0) -> 0 | M73: =K73*L73 -> 0
A74: FXF_EURUSD_6M | B74: Risk_IRCurve | C74: USD | D74: regular_well_traded | E74: 6m | F74: OIS | G74: 1309.8197 | H74: USD | I74: 1309.8197 | K74: =IF(AND(B74="Risk_FXVol",ISNUMBER(J74)),I74/J74,0) -> 0 | L74: =IF(OR(B74="Risk_FXVol",B74="Risk_IRVol"),INDEX(SIMM_Curvature!$D$15:$D$26,MATCH(E74,SIMM_Curvature!$A$15:$A$26,0)),0) -> 0 | M74: =K74*L74 -> 0
A75: FXF_EURUSD_6M | B75: Risk_FX | C75: EUR | G75: 301193.9 | H75: USD | I75: 301193.9 | K75: =IF(AND(B75="Risk_FXVol",ISNUMBER(J75)),I75/J75,0) -> 0 | L75: =IF(OR(B75="Risk_FXVol",B75="Risk_IRVol"),INDEX(SIMM_Curvature!$D$15:$D$26,MATCH(E75,SIMM_Curvature!$A$15:$A$26,0)),0) -> 0 | M75: =K75*L75 -> 0
A76: FXF_GBPUSD_1Y | B76: Risk_IRCurve | C76: GBP | D76: regular_well_traded | E76: 1y | F76: OIS | G76: 1388.124 | H76: GBP | I76: 1776.24 | K76: =IF(AND(B76="Risk_FXVol",ISNUMBER(J76)),I76/J76,0) -> 0 | L76: =IF(OR(B76="Risk_FXVol",B76="Risk_IRVol"),INDEX(SIMM_Curvature!$D$15:$D$26,MATCH(E76,SIMM_Curvature!$A$15:$A$26,0)),0) -> 0 | M76: =K76*L76 -> 0
A77: FXF_GBPUSD_1Y | B77: Risk_IRCurve | C77: USD | D77: regular_well_traded | E77: 1y | F77: OIS | G77: -1741.618 | H77: USD | I77: -1741.618 | K77: =IF(AND(B77="Risk_FXVol",ISNUMBER(J77)),I77/J77,0) -> 0 | L77: =IF(OR(B77="Risk_FXVol",B77="Risk_IRVol"),INDEX(SIMM_Curvature!$D$15:$D$26,MATCH(E77,SIMM_Curvature!$A$15:$A$26,0)),0) -> 0 | M77: =K77*L77 -> 0
A78: FXF_GBPUSD_1Y | B78: Risk_FX | C78: GBP | G78: -184643.13 | H78: USD | I78: -184643.13 | K78: =IF(AND(B78="Risk_FXVol",ISNUMBER(J78)),I78/J78,0) -> 0 | L78: =IF(OR(B78="Risk_FXVol",B78="Risk_IRVol"),INDEX(SIMM_Curvature!$D$15:$D$26,MATCH(E78,SIMM_Curvature!$A$15:$A$26,0)),0) -> 0 | M78: =K78*L78 -> 0
A79: FXF_USDJPY_3M | B79: Risk_IRCurve | C79: USD | D79: regular_well_traded | E79: 3m | F79: OIS | G79: -489.74508 | H79: USD | I79: -489.74508 | K79: =IF(AND(B79="Risk_FXVol",ISNUMBER(J79)),I79/J79,0) -> 0 | L79: =IF(OR(B79="Risk_FXVol",B79="Risk_IRVol"),INDEX(SIMM_Curvature!$D$15:$D$26,MATCH(E79,SIMM_Curvature!$A$15:$A$26,0)),0) -> 0 | M79: =K79*L79 -> 0
A80: FXF_USDJPY_3M | B80: Risk_IRCurve | C80: JPY | D80: regular_low_vol | E80: 3m | F80: OIS | G80: 73858.631 | H80: JPY | I80: 500.03033 | K80: =IF(AND(B80="Risk_FXVol",ISNUMBER(J80)),I80/J80,0) -> 0 | L80: =IF(OR(B80="Risk_FXVol",B80="Risk_IRVol"),INDEX(SIMM_Curvature!$D$15:$D$26,MATCH(E80,SIMM_Curvature!$A$15:$A$26,0)),0) -> 0 | M80: =K80*L80 -> 0
A81: FXF_USDJPY_3M | B81: Risk_FX | C81: JPY | G81: -200440.64 | H81: USD | I81: -200440.64 | K81: =IF(AND(B81="Risk_FXVol",ISNUMBER(J81)),I81/J81,0) -> 0 | L81: =IF(OR(B81="Risk_FXVol",B81="Risk_IRVol"),INDEX(SIMM_Curvature!$D$15:$D$26,MATCH(E81,SIMM_Curvature!$A$15:$A$26,0)),0) -> 0 | M81: =K81*L81 -> 0
A82: FXF_USDMXN_6M | B82: Risk_IRCurve | C82: USD | D82: regular_well_traded | E82: 6m | F82: OIS | G82: 479.59733 | H82: USD | I82: 479.59733 | K82: =IF(AND(B82="Risk_FXVol",ISNUMBER(J82)),I82/J82,0) -> 0 | L82: =IF(OR(B82="Risk_FXVol",B82="Risk_IRVol"),INDEX(SIMM_Curvature!$D$15:$D$26,MATCH(E82,SIMM_Curvature!$A$15:$A$26,0)),0) -> 0 | M82: =K82*L82 -> 0
A83: FXF_USDMXN_6M | B83: Risk_IRCurve | C83: MXN | D83: high_vol | E83: 6m | F83: OIS | G83: -8363.8234 | H83: MXN | I83: -507.45559 | K83: =IF(AND(B83="Risk_FXVol",ISNUMBER(J83)),I83/J83,0) -> 0 | L83: =IF(OR(B83="Risk_FXVol",B83="Risk_IRVol"),INDEX(SIMM_Curvature!$D$15:$D$26,MATCH(E83,SIMM_Curvature!$A$15:$A$26,0)),0) -> 0 | M83: =K83*L83 -> 0
A84: FXF_USDMXN_6M | B84: Risk_FX | C84: MXN | G84: 107122.7 | H84: USD | I84: 107122.7 | K84: =IF(AND(B84="Risk_FXVol",ISNUMBER(J84)),I84/J84,0) -> 0 | L84: =IF(OR(B84="Risk_FXVol",B84="Risk_IRVol"),INDEX(SIMM_Curvature!$D$15:$D$26,MATCH(E84,SIMM_Curvature!$A$15:$A$26,0)),0) -> 0 | M84: =K84*L84 -> 0
A85: FXO_EURUSD_C3M | B85: Risk_IRCurve | C85: EUR | D85: regular_well_traded | E85: 3m | F85: OIS | G85: -493.27242 | H85: EUR | I85: -601.57798 | K85: =IF(AND(B85="Risk_FXVol",ISNUMBER(J85)),I85/J85,0) -> 0 | L85: =IF(OR(B85="Risk_FXVol",B85="Risk_IRVol"),INDEX(SIMM_Curvature!$D$15:$D$26,MATCH(E85,SIMM_Curvature!$A$15:$A$26,0)),0) -> 0 | M85: =K85*L85 -> 0
A86: FXO_EURUSD_C3M | B86: Risk_IRCurve | C86: USD | D86: regular_well_traded | E86: 3m | F86: OIS | G86: 535.33885 | H86: USD | I86: 535.33885 | K86: =IF(AND(B86="Risk_FXVol",ISNUMBER(J86)),I86/J86,0) -> 0 | L86: =IF(OR(B86="Risk_FXVol",B86="Risk_IRVol"),INDEX(SIMM_Curvature!$D$15:$D$26,MATCH(E86,SIMM_Curvature!$A$15:$A$26,0)),0) -> 0 | M86: =K86*L86 -> 0
A87: FXO_EURUSD_C3M | B87: Risk_FX | C87: EUR | G87: 242081.62 | H87: USD | I87: 242081.62 | K87: =IF(AND(B87="Risk_FXVol",ISNUMBER(J87)),I87/J87,0) -> 0 | L87: =IF(OR(B87="Risk_FXVol",B87="Risk_IRVol"),INDEX(SIMM_Curvature!$D$15:$D$26,MATCH(E87,SIMM_Curvature!$A$15:$A$26,0)),0) -> 0 | M87: =K87*L87 -> 0
A88: FXO_EURUSD_C3M | B88: Risk_FXVol | C88: EURUSD | E88: 3m | G88: 4484.873 | H88: USD | I88: 4484.873 | J88: 0.075765621 | K88: =IF(AND(B88="Risk_FXVol",ISNUMBER(J88)),I88/J88,0) -> 59194.037 | L88: =IF(OR(B88="Risk_FXVol",B88="Risk_IRVol"),INDEX(SIMM_Curvature!$D$15:$D$26,MATCH(E88,SIMM_Curvature!$A$15:$A$26,0)),0) -> 0.076712329 | M88: =K88*L88 -> 4540.9124
A89: FXO_USDMXN_C1Y | B89: Risk_IRCurve | C89: USD | D89: regular_well_traded | E89: 1y | F89: OIS | G89: -222.788 | H89: USD | I89: -222.788 | K89: =IF(AND(B89="Risk_FXVol",ISNUMBER(J89)),I89/J89,0) -> 0 | L89: =IF(OR(B89="Risk_FXVol",B89="Risk_IRVol"),INDEX(SIMM_Curvature!$D$15:$D$26,MATCH(E89,SIMM_Curvature!$A$15:$A$26,0)),0) -> 0 | M89: =K89*L89 -> 0
A90: FXO_USDMXN_C1Y | B90: Risk_IRCurve | C90: MXN | D90: high_vol | E90: 1y | F90: OIS | G90: 3164.2702 | H90: MXN | I90: 191.98476 | K90: =IF(AND(B90="Risk_FXVol",ISNUMBER(J90)),I90/J90,0) -> 0 | L90: =IF(OR(B90="Risk_FXVol",B90="Risk_IRVol"),INDEX(SIMM_Curvature!$D$15:$D$26,MATCH(E90,SIMM_Curvature!$A$15:$A$26,0)),0) -> 0 | M90: =K90*L90 -> 0
A91: FXO_USDMXN_C1Y | B91: Risk_FX | C91: MXN | G91: -21368.824 | H91: USD | I91: -21368.824 | K91: =IF(AND(B91="Risk_FXVol",ISNUMBER(J91)),I91/J91,0) -> 0 | L91: =IF(OR(B91="Risk_FXVol",B91="Risk_IRVol"),INDEX(SIMM_Curvature!$D$15:$D$26,MATCH(E91,SIMM_Curvature!$A$15:$A$26,0)),0) -> 0 | M91: =K91*L91 -> 0
A92: FXO_USDMXN_C1Y | B92: Risk_FXVol | C92: USDMXN | E92: 1y | G92: 438670.24 | H92: USD | I92: 438670.24 | J92: 0.14643772 | K92: =IF(AND(B92="Risk_FXVol",ISNUMBER(J92)),I92/J92,0) -> 2995609.6 | L92: =IF(OR(B92="Risk_FXVol",B92="Risk_IRVol"),INDEX(SIMM_Curvature!$D$15:$D$26,MATCH(E92,SIMM_Curvature!$A$15:$A$26,0)),0) -> 0.019178082 | M92: =K92*L92 -> 57450.047
A93: FXO_GBPUSD_STRADDLE_C | B93: Risk_IRCurve | C93: GBP | D93: regular_well_traded | E93: 6m | F93: OIS | G93: -401.99548 | H93: GBP | I93: -514.39242 | K93: =IF(AND(B93="Risk_FXVol",ISNUMBER(J93)),I93/J93,0) -> 0 | L93: =IF(OR(B93="Risk_FXVol",B93="Risk_IRVol"),INDEX(SIMM_Curvature!$D$15:$D$26,MATCH(E93,SIMM_Curvature!$A$15:$A$26,0)),0) -> 0 | M93: =K93*L93 -> 0
A94: FXO_GBPUSD_STRADDLE_C | B94: Risk_IRCurve | C94: USD | D94: regular_well_traded | E94: 6m | F94: OIS | G94: 474.43114 | H94: USD | I94: 474.43114 | K94: =IF(AND(B94="Risk_FXVol",ISNUMBER(J94)),I94/J94,0) -> 0 | L94: =IF(OR(B94="Risk_FXVol",B94="Risk_IRVol"),INDEX(SIMM_Curvature!$D$15:$D$26,MATCH(E94,SIMM_Curvature!$A$15:$A$26,0)),0) -> 0 | M94: =K94*L94 -> 0
A95: FXO_GBPUSD_STRADDLE_C | B95: Risk_FX | C95: GBP | G95: 104841.75 | H95: USD | I95: 104841.75 | K95: =IF(AND(B95="Risk_FXVol",ISNUMBER(J95)),I95/J95,0) -> 0 | L95: =IF(OR(B95="Risk_FXVol",B95="Risk_IRVol"),INDEX(SIMM_Curvature!$D$15:$D$26,MATCH(E95,SIMM_Curvature!$A$15:$A$26,0)),0) -> 0 | M95: =K95*L95 -> 0
A96: FXO_GBPUSD_STRADDLE_C | B96: Risk_FXVol | C96: GBPUSD | E96: 6m | G96: 704999.65 | H96: USD | I96: 704999.65 | J96: 0.13405935 | K96: =IF(AND(B96="Risk_FXVol",ISNUMBER(J96)),I96/J96,0) -> 5258862.3 | L96: =IF(OR(B96="Risk_FXVol",B96="Risk_IRVol"),INDEX(SIMM_Curvature!$D$15:$D$26,MATCH(E96,SIMM_Curvature!$A$15:$A$26,0)),0) -> 0.038356164 | M96: =K96*L96 -> 201709.79
A97: FXO_GBPUSD_STRADDLE_P | B97: Risk_IRCurve | C97: GBP | D97: regular_well_traded | E97: 6m | F97: OIS | G97: 320.06574 | H97: GBP | I97: 409.55533 | K97: =IF(AND(B97="Risk_FXVol",ISNUMBER(J97)),I97/J97,0) -> 0 | L97: =IF(OR(B97="Risk_FXVol",B97="Risk_IRVol"),INDEX(SIMM_Curvature!$D$15:$D$26,MATCH(E97,SIMM_Curvature!$A$15:$A$26,0)),0) -> 0 | M97: =K97*L97 -> 0
A98: FXO_GBPUSD_STRADDLE_P | B98: Risk_IRCurve | C98: USD | D98: regular_well_traded | E98: 6m | F98: OIS | G98: -439.51638 | H98: USD | I98: -439.51638 | K98: =IF(AND(B98="Risk_FXVol",ISNUMBER(J98)),I98/J98,0) -> 0 | L98: =IF(OR(B98="Risk_FXVol",B98="Risk_IRVol"),INDEX(SIMM_Curvature!$D$15:$D$26,MATCH(E98,SIMM_Curvature!$A$15:$A$26,0)),0) -> 0 | M98: =K98*L98 -> 0
A99: FXO_GBPUSD_STRADDLE_P | B99: Risk_FX | C99: GBP | G99: -83488.908 | H99: USD | I99: -83488.908 | K99: =IF(AND(B99="Risk_FXVol",ISNUMBER(J99)),I99/J99,0) -> 0 | L99: =IF(OR(B99="Risk_FXVol",B99="Risk_IRVol"),INDEX(SIMM_Curvature!$D$15:$D$26,MATCH(E99,SIMM_Curvature!$A$15:$A$26,0)),0) -> 0 | M99: =K99*L99 -> 0
A100: FXO_GBPUSD_STRADDLE_P | B100: Risk_FXVol | C100: GBPUSD | E100: 6m | G100: 704999.65 | H100: USD | I100: 704999.65 | J100: 0.13405935 | K100: =IF(AND(B100="Risk_FXVol",ISNUMBER(J100)),I100/J100,0) -> 5258862.3 | L100: =IF(OR(B100="Risk_FXVol",B100="Risk_IRVol"),INDEX(SIMM_Curvature!$D$15:$D$26,MATCH(E100,SIMM_Curvature!$A$15:$A$26,0)),0) -> 0.038356164 | M100: =K100*L100 -> 201709.79

Sheet SIMM_Delta
A1: IR and FX delta. All numbers are formulas: risk weights and thresholds by lookup on Parameters, CR, WS, K, S, aggregation.
A4: Parameter set | B4: =Inputs!$B$4 -> 2.8+2512
A6: IR tenor correlation (12x12)
B7: =Inputs!$B$14 -> 2w | C7: =Inputs!$C$14 -> 1m | D7: =Inputs!$D$14 -> 3m | E7: =Inputs!$E$14 -> 6m | F7: =Inputs!$F$14 -> 1y | G7: =Inputs!$G$14 -> 2y | H7: =Inputs!$H$14 -> 3y | I7: =Inputs!$I$14 -> 5y | J7: =Inputs!$J$14 -> 10y | K7: =Inputs!$K$14 -> 15y | L7: =Inputs!$L$14 -> 20y | M7: =Inputs!$M$14 -> 30y
A8: =Inputs!$B$14 -> 2w | B8: =INDEX(Parameters!$G$5:$G$689,MATCH(Inputs!$B$4&"|IR|"&"delta_tenor_corr"&"|"&$A8&"|"&B$7,Parameters!$A$5:$A$689,0)) -> 1 | C8: =INDEX(Parameters!$G$5:$G$689,MATCH(Inputs!$B$4&"|IR|"&"delta_tenor_corr"&"|"&$A8&"|"&C$7,Parameters!$A$5:$A$689,0)) -> 0.74 | D8: =INDEX(Parameters!$G$5:$G$689,MATCH(Inputs!$B$4&"|IR|"&"delta_tenor_corr"&"|"&$A8&"|"&D$7,Parameters!$A$5:$A$689,0)) -> 0.65 | E8: =INDEX(Parameters!$G$5:$G$689,MATCH(Inputs!$B$4&"|IR|"&"delta_tenor_corr"&"|"&$A8&"|"&E$7,Parameters!$A$5:$A$689,0)) -> 0.54 | F8: =INDEX(Parameters!$G$5:$G$689,MATCH(Inputs!$B$4&"|IR|"&"delta_tenor_corr"&"|"&$A8&"|"&F$7,Parameters!$A$5:$A$689,0)) -> 0.4 | G8: =INDEX(Parameters!$G$5:$G$689,MATCH(Inputs!$B$4&"|IR|"&"delta_tenor_corr"&"|"&$A8&"|"&G$7,Parameters!$A$5:$A$689,0)) -> 0.29 | H8: =INDEX(Parameters!$G$5:$G$689,MATCH(Inputs!$B$4&"|IR|"&"delta_tenor_corr"&"|"&$A8&"|"&H$7,Parameters!$A$5:$A$689,0)) -> 0.25 | I8: =INDEX(Parameters!$G$5:$G$689,MATCH(Inputs!$B$4&"|IR|"&"delta_tenor_corr"&"|"&$A8&"|"&I$7,Parameters!$A$5:$A$689,0)) -> 0.22 | ... M8: =INDEX(Parameters!$G$5:$G$689,MATCH(Inputs!$B$4&"|IR|"&"delta_tenor_corr"&"|"&$A8&"|"&M$7,Parameters!$A$5:$A$689,0)) -> 0.14
A9: =Inputs!$C$14 -> 1m | B9: =INDEX(Parameters!$G$5:$G$689,MATCH(Inputs!$B$4&"|IR|"&"delta_tenor_corr"&"|"&$A9&"|"&B$7,Parameters!$A$5:$A$689,0)) -> 0.74 | C9: =INDEX(Parameters!$G$5:$G$689,MATCH(Inputs!$B$4&"|IR|"&"delta_tenor_corr"&"|"&$A9&"|"&C$7,Parameters!$A$5:$A$689,0)) -> 1 | D9: =INDEX(Parameters!$G$5:$G$689,MATCH(Inputs!$B$4&"|IR|"&"delta_tenor_corr"&"|"&$A9&"|"&D$7,Parameters!$A$5:$A$689,0)) -> 0.85 | E9: =INDEX(Parameters!$G$5:$G$689,MATCH(Inputs!$B$4&"|IR|"&"delta_tenor_corr"&"|"&$A9&"|"&E$7,Parameters!$A$5:$A$689,0)) -> 0.72 | F9: =INDEX(Parameters!$G$5:$G$689,MATCH(Inputs!$B$4&"|IR|"&"delta_tenor_corr"&"|"&$A9&"|"&F$7,Parameters!$A$5:$A$689,0)) -> 0.5 | G9: =INDEX(Parameters!$G$5:$G$689,MATCH(Inputs!$B$4&"|IR|"&"delta_tenor_corr"&"|"&$A9&"|"&G$7,Parameters!$A$5:$A$689,0)) -> 0.36 | H9: =INDEX(Parameters!$G$5:$G$689,MATCH(Inputs!$B$4&"|IR|"&"delta_tenor_corr"&"|"&$A9&"|"&H$7,Parameters!$A$5:$A$689,0)) -> 0.3 | I9: =INDEX(Parameters!$G$5:$G$689,MATCH(Inputs!$B$4&"|IR|"&"delta_tenor_corr"&"|"&$A9&"|"&I$7,Parameters!$A$5:$A$689,0)) -> 0.25 | ... M9: =INDEX(Parameters!$G$5:$G$689,MATCH(Inputs!$B$4&"|IR|"&"delta_tenor_corr"&"|"&$A9&"|"&M$7,Parameters!$A$5:$A$689,0)) -> 0.14
A10: =Inputs!$D$14 -> 3m | B10: =INDEX(Parameters!$G$5:$G$689,MATCH(Inputs!$B$4&"|IR|"&"delta_tenor_corr"&"|"&$A10&"|"&B$7,Parameters!$A$5:$A$689,0)) -> 0.65 | C10: =INDEX(Parameters!$G$5:$G$689,MATCH(Inputs!$B$4&"|IR|"&"delta_tenor_corr"&"|"&$A10&"|"&C$7,Parameters!$A$5:$A$689,0)) -> 0.85 | D10: =INDEX(Parameters!$G$5:$G$689,MATCH(Inputs!$B$4&"|IR|"&"delta_tenor_corr"&"|"&$A10&"|"&D$7,Parameters!$A$5:$A$689,0)) -> 1 | E10: =INDEX(Parameters!$G$5:$G$689,MATCH(Inputs!$B$4&"|IR|"&"delta_tenor_corr"&"|"&$A10&"|"&E$7,Parameters!$A$5:$A$689,0)) -> 0.9 | F10: =INDEX(Parameters!$G$5:$G$689,MATCH(Inputs!$B$4&"|IR|"&"delta_tenor_corr"&"|"&$A10&"|"&F$7,Parameters!$A$5:$A$689,0)) -> 0.69 | G10: =INDEX(Parameters!$G$5:$G$689,MATCH(Inputs!$B$4&"|IR|"&"delta_tenor_corr"&"|"&$A10&"|"&G$7,Parameters!$A$5:$A$689,0)) -> 0.53 | H10: =INDEX(Parameters!$G$5:$G$689,MATCH(Inputs!$B$4&"|IR|"&"delta_tenor_corr"&"|"&$A10&"|"&H$7,Parameters!$A$5:$A$689,0)) -> 0.46 | I10: =INDEX(Parameters!$G$5:$G$689,MATCH(Inputs!$B$4&"|IR|"&"delta_tenor_corr"&"|"&$A10&"|"&I$7,Parameters!$A$5:$A$689,0)) -> 0.4 | ... M10: =INDEX(Parameters!$G$5:$G$689,MATCH(Inputs!$B$4&"|IR|"&"delta_tenor_corr"&"|"&$A10&"|"&M$7,Parameters!$A$5:$A$689,0)) -> 0.25
A11: =Inputs!$E$14 -> 6m | B11: =INDEX(Parameters!$G$5:$G$689,MATCH(Inputs!$B$4&"|IR|"&"delta_tenor_corr"&"|"&$A11&"|"&B$7,Parameters!$A$5:$A$689,0)) -> 0.54 | C11: =INDEX(Parameters!$G$5:$G$689,MATCH(Inputs!$B$4&"|IR|"&"delta_tenor_corr"&"|"&$A11&"|"&C$7,Parameters!$A$5:$A$689,0)) -> 0.72 | D11: =INDEX(Parameters!$G$5:$G$689,MATCH(Inputs!$B$4&"|IR|"&"delta_tenor_corr"&"|"&$A11&"|"&D$7,Parameters!$A$5:$A$689,0)) -> 0.9 | E11: =INDEX(Parameters!$G$5:$G$689,MATCH(Inputs!$B$4&"|IR|"&"delta_tenor_corr"&"|"&$A11&"|"&E$7,Parameters!$A$5:$A$689,0)) -> 1 | F11: =INDEX(Parameters!$G$5:$G$689,MATCH(Inputs!$B$4&"|IR|"&"delta_tenor_corr"&"|"&$A11&"|"&F$7,Parameters!$A$5:$A$689,0)) -> 0.86 | G11: =INDEX(Parameters!$G$5:$G$689,MATCH(Inputs!$B$4&"|IR|"&"delta_tenor_corr"&"|"&$A11&"|"&G$7,Parameters!$A$5:$A$689,0)) -> 0.73 | H11: =INDEX(Parameters!$G$5:$G$689,MATCH(Inputs!$B$4&"|IR|"&"delta_tenor_corr"&"|"&$A11&"|"&H$7,Parameters!$A$5:$A$689,0)) -> 0.65 | I11: =INDEX(Parameters!$G$5:$G$689,MATCH(Inputs!$B$4&"|IR|"&"delta_tenor_corr"&"|"&$A11&"|"&I$7,Parameters!$A$5:$A$689,0)) -> 0.58 | ... M11: =INDEX(Parameters!$G$5:$G$689,MATCH(Inputs!$B$4&"|IR|"&"delta_tenor_corr"&"|"&$A11&"|"&M$7,Parameters!$A$5:$A$689,0)) -> 0.42
A12: =Inputs!$F$14 -> 1y | B12: =INDEX(Parameters!$G$5:$G$689,MATCH(Inputs!$B$4&"|IR|"&"delta_tenor_corr"&"|"&$A12&"|"&B$7,Parameters!$A$5:$A$689,0)) -> 0.4 | C12: =INDEX(Parameters!$G$5:$G$689,MATCH(Inputs!$B$4&"|IR|"&"delta_tenor_corr"&"|"&$A12&"|"&C$7,Parameters!$A$5:$A$689,0)) -> 0.5 | D12: =INDEX(Parameters!$G$5:$G$689,MATCH(Inputs!$B$4&"|IR|"&"delta_tenor_corr"&"|"&$A12&"|"&D$7,Parameters!$A$5:$A$689,0)) -> 0.69 | E12: =INDEX(Parameters!$G$5:$G$689,MATCH(Inputs!$B$4&"|IR|"&"delta_tenor_corr"&"|"&$A12&"|"&E$7,Parameters!$A$5:$A$689,0)) -> 0.86 | F12: =INDEX(Parameters!$G$5:$G$689,MATCH(Inputs!$B$4&"|IR|"&"delta_tenor_corr"&"|"&$A12&"|"&F$7,Parameters!$A$5:$A$689,0)) -> 1 | G12: =INDEX(Parameters!$G$5:$G$689,MATCH(Inputs!$B$4&"|IR|"&"delta_tenor_corr"&"|"&$A12&"|"&G$7,Parameters!$A$5:$A$689,0)) -> 0.94 | H12: =INDEX(Parameters!$G$5:$G$689,MATCH(Inputs!$B$4&"|IR|"&"delta_tenor_corr"&"|"&$A12&"|"&H$7,Parameters!$A$5:$A$689,0)) -> 0.87 | I12: =INDEX(Parameters!$G$5:$G$689,MATCH(Inputs!$B$4&"|IR|"&"delta_tenor_corr"&"|"&$A12&"|"&I$7,Parameters!$A$5:$A$689,0)) -> 0.81 | ... M12: =INDEX(Parameters!$G$5:$G$689,MATCH(Inputs!$B$4&"|IR|"&"delta_tenor_corr"&"|"&$A12&"|"&M$7,Parameters!$A$5:$A$689,0)) -> 0.63
A13: =Inputs!$G$14 -> 2y | B13: =INDEX(Parameters!$G$5:$G$689,MATCH(Inputs!$B$4&"|IR|"&"delta_tenor_corr"&"|"&$A13&"|"&B$7,Parameters!$A$5:$A$689,0)) -> 0.29 | C13: =INDEX(Parameters!$G$5:$G$689,MATCH(Inputs!$B$4&"|IR|"&"delta_tenor_corr"&"|"&$A13&"|"&C$7,Parameters!$A$5:$A$689,0)) -> 0.36 | D13: =INDEX(Parameters!$G$5:$G$689,MATCH(Inputs!$B$4&"|IR|"&"delta_tenor_corr"&"|"&$A13&"|"&D$7,Parameters!$A$5:$A$689,0)) -> 0.53 | E13: =INDEX(Parameters!$G$5:$G$689,MATCH(Inputs!$B$4&"|IR|"&"delta_tenor_corr"&"|"&$A13&"|"&E$7,Parameters!$A$5:$A$689,0)) -> 0.73 | F13: =INDEX(Parameters!$G$5:$G$689,MATCH(Inputs!$B$4&"|IR|"&"delta_tenor_corr"&"|"&$A13&"|"&F$7,Parameters!$A$5:$A$689,0)) -> 0.94 | G13: =INDEX(Parameters!$G$5:$G$689,MATCH(Inputs!$B$4&"|IR|"&"delta_tenor_corr"&"|"&$A13&"|"&G$7,Parameters!$A$5:$A$689,0)) -> 1 | H13: =INDEX(Parameters!$G$5:$G$689,MATCH(Inputs!$B$4&"|IR|"&"delta_tenor_corr"&"|"&$A13&"|"&H$7,Parameters!$A$5:$A$689,0)) -> 0.97 | I13: =INDEX(Parameters!$G$5:$G$689,MATCH(Inputs!$B$4&"|IR|"&"delta_tenor_corr"&"|"&$A13&"|"&I$7,Parameters!$A$5:$A$689,0)) -> 0.92 | ... M13: =INDEX(Parameters!$G$5:$G$689,MATCH(Inputs!$B$4&"|IR|"&"delta_tenor_corr"&"|"&$A13&"|"&M$7,Parameters!$A$5:$A$689,0)) -> 0.76
A14: =Inputs!$H$14 -> 3y | B14: =INDEX(Parameters!$G$5:$G$689,MATCH(Inputs!$B$4&"|IR|"&"delta_tenor_corr"&"|"&$A14&"|"&B$7,Parameters!$A$5:$A$689,0)) -> 0.25 | C14: =INDEX(Parameters!$G$5:$G$689,MATCH(Inputs!$B$4&"|IR|"&"delta_tenor_corr"&"|"&$A14&"|"&C$7,Parameters!$A$5:$A$689,0)) -> 0.3 | D14: =INDEX(Parameters!$G$5:$G$689,MATCH(Inputs!$B$4&"|IR|"&"delta_tenor_corr"&"|"&$A14&"|"&D$7,Parameters!$A$5:$A$689,0)) -> 0.46 | E14: =INDEX(Parameters!$G$5:$G$689,MATCH(Inputs!$B$4&"|IR|"&"delta_tenor_corr"&"|"&$A14&"|"&E$7,Parameters!$A$5:$A$689,0)) -> 0.65 | F14: =INDEX(Parameters!$G$5:$G$689,MATCH(Inputs!$B$4&"|IR|"&"delta_tenor_corr"&"|"&$A14&"|"&F$7,Parameters!$A$5:$A$689,0)) -> 0.87 | G14: =INDEX(Parameters!$G$5:$G$689,MATCH(Inputs!$B$4&"|IR|"&"delta_tenor_corr"&"|"&$A14&"|"&G$7,Parameters!$A$5:$A$689,0)) -> 0.97 | H14: =INDEX(Parameters!$G$5:$G$689,MATCH(Inputs!$B$4&"|IR|"&"delta_tenor_corr"&"|"&$A14&"|"&H$7,Parameters!$A$5:$A$689,0)) -> 1 | I14: =INDEX(Parameters!$G$5:$G$689,MATCH(Inputs!$B$4&"|IR|"&"delta_tenor_corr"&"|"&$A14&"|"&I$7,Parameters!$A$5:$A$689,0)) -> 0.97 | ... M14: =INDEX(Parameters!$G$5:$G$689,MATCH(Inputs!$B$4&"|IR|"&"delta_tenor_corr"&"|"&$A14&"|"&M$7,Parameters!$A$5:$A$689,0)) -> 0.81
A15: =Inputs!$I$14 -> 5y | B15: =INDEX(Parameters!$G$5:$G$689,MATCH(Inputs!$B$4&"|IR|"&"delta_tenor_corr"&"|"&$A15&"|"&B$7,Parameters!$A$5:$A$689,0)) -> 0.22 | C15: =INDEX(Parameters!$G$5:$G$689,MATCH(Inputs!$B$4&"|IR|"&"delta_tenor_corr"&"|"&$A15&"|"&C$7,Parameters!$A$5:$A$689,0)) -> 0.25 | D15: =INDEX(Parameters!$G$5:$G$689,MATCH(Inputs!$B$4&"|IR|"&"delta_tenor_corr"&"|"&$A15&"|"&D$7,Parameters!$A$5:$A$689,0)) -> 0.4 | E15: =INDEX(Parameters!$G$5:$G$689,MATCH(Inputs!$B$4&"|IR|"&"delta_tenor_corr"&"|"&$A15&"|"&E$7,Parameters!$A$5:$A$689,0)) -> 0.58 | F15: =INDEX(Parameters!$G$5:$G$689,MATCH(Inputs!$B$4&"|IR|"&"delta_tenor_corr"&"|"&$A15&"|"&F$7,Parameters!$A$5:$A$689,0)) -> 0.81 | G15: =INDEX(Parameters!$G$5:$G$689,MATCH(Inputs!$B$4&"|IR|"&"delta_tenor_corr"&"|"&$A15&"|"&G$7,Parameters!$A$5:$A$689,0)) -> 0.92 | H15: =INDEX(Parameters!$G$5:$G$689,MATCH(Inputs!$B$4&"|IR|"&"delta_tenor_corr"&"|"&$A15&"|"&H$7,Parameters!$A$5:$A$689,0)) -> 0.97 | I15: =INDEX(Parameters!$G$5:$G$689,MATCH(Inputs!$B$4&"|IR|"&"delta_tenor_corr"&"|"&$A15&"|"&I$7,Parameters!$A$5:$A$689,0)) -> 1 | ... M15: =INDEX(Parameters!$G$5:$G$689,MATCH(Inputs!$B$4&"|IR|"&"delta_tenor_corr"&"|"&$A15&"|"&M$7,Parameters!$A$5:$A$689,0)) -> 0.88
A16: =Inputs!$J$14 -> 10y | B16: =INDEX(Parameters!$G$5:$G$689,MATCH(Inputs!$B$4&"|IR|"&"delta_tenor_corr"&"|"&$A16&"|"&B$7,Parameters!$A$5:$A$689,0)) -> 0.17 | C16: =INDEX(Parameters!$G$5:$G$689,MATCH(Inputs!$B$4&"|IR|"&"delta_tenor_corr"&"|"&$A16&"|"&C$7,Parameters!$A$5:$A$689,0)) -> 0.2 | D16: =INDEX(Parameters!$G$5:$G$689,MATCH(Inputs!$B$4&"|IR|"&"delta_tenor_corr"&"|"&$A16&"|"&D$7,Parameters!$A$5:$A$689,0)) -> 0.34 | E16: =INDEX(Parameters!$G$5:$G$689,MATCH(Inputs!$B$4&"|IR|"&"delta_tenor_corr"&"|"&$A16&"|"&E$7,Parameters!$A$5:$A$689,0)) -> 0.52 | F16: =INDEX(Parameters!$G$5:$G$689,MATCH(Inputs!$B$4&"|IR|"&"delta_tenor_corr"&"|"&$A16&"|"&F$7,Parameters!$A$5:$A$689,0)) -> 0.73 | G16: =INDEX(Parameters!$G$5:$G$689,MATCH(Inputs!$B$4&"|IR|"&"delta_tenor_corr"&"|"&$A16&"|"&G$7,Parameters!$A$5:$A$689,0)) -> 0.86 | H16: =INDEX(Parameters!$G$5:$G$689,MATCH(Inputs!$B$4&"|IR|"&"delta_tenor_corr"&"|"&$A16&"|"&H$7,Parameters!$A$5:$A$689,0)) -> 0.91 | I16: =INDEX(Parameters!$G$5:$G$689,MATCH(Inputs!$B$4&"|IR|"&"delta_tenor_corr"&"|"&$A16&"|"&I$7,Parameters!$A$5:$A$689,0)) -> 0.96 | ... M16: =INDEX(Parameters!$G$5:$G$689,MATCH(Inputs!$B$4&"|IR|"&"delta_tenor_corr"&"|"&$A16&"|"&M$7,Parameters!$A$5:$A$689,0)) -> 0.95
A17: =Inputs!$K$14 -> 15y | B17: =INDEX(Parameters!$G$5:$G$689,MATCH(Inputs!$B$4&"|IR|"&"delta_tenor_corr"&"|"&$A17&"|"&B$7,Parameters!$A$5:$A$689,0)) -> 0.16 | C17: =INDEX(Parameters!$G$5:$G$689,MATCH(Inputs!$B$4&"|IR|"&"delta_tenor_corr"&"|"&$A17&"|"&C$7,Parameters!$A$5:$A$689,0)) -> 0.16 | D17: =INDEX(Parameters!$G$5:$G$689,MATCH(Inputs!$B$4&"|IR|"&"delta_tenor_corr"&"|"&$A17&"|"&D$7,Parameters!$A$5:$A$689,0)) -> 0.27 | E17: =INDEX(Parameters!$G$5:$G$689,MATCH(Inputs!$B$4&"|IR|"&"delta_tenor_corr"&"|"&$A17&"|"&E$7,Parameters!$A$5:$A$689,0)) -> 0.47 | F17: =INDEX(Parameters!$G$5:$G$689,MATCH(Inputs!$B$4&"|IR|"&"delta_tenor_corr"&"|"&$A17&"|"&F$7,Parameters!$A$5:$A$689,0)) -> 0.69 | G17: =INDEX(Parameters!$G$5:$G$689,MATCH(Inputs!$B$4&"|IR|"&"delta_tenor_corr"&"|"&$A17&"|"&G$7,Parameters!$A$5:$A$689,0)) -> 0.82 | H17: =INDEX(Parameters!$G$5:$G$689,MATCH(Inputs!$B$4&"|IR|"&"delta_tenor_corr"&"|"&$A17&"|"&H$7,Parameters!$A$5:$A$689,0)) -> 0.87 | I17: =INDEX(Parameters!$G$5:$G$689,MATCH(Inputs!$B$4&"|IR|"&"delta_tenor_corr"&"|"&$A17&"|"&I$7,Parameters!$A$5:$A$689,0)) -> 0.93 | ... M17: =INDEX(Parameters!$G$5:$G$689,MATCH(Inputs!$B$4&"|IR|"&"delta_tenor_corr"&"|"&$A17&"|"&M$7,Parameters!$A$5:$A$689,0)) -> 0.97
A18: =Inputs!$L$14 -> 20y | B18: =INDEX(Parameters!$G$5:$G$689,MATCH(Inputs!$B$4&"|IR|"&"delta_tenor_corr"&"|"&$A18&"|"&B$7,Parameters!$A$5:$A$689,0)) -> 0.14 | C18: =INDEX(Parameters!$G$5:$G$689,MATCH(Inputs!$B$4&"|IR|"&"delta_tenor_corr"&"|"&$A18&"|"&C$7,Parameters!$A$5:$A$689,0)) -> 0.14 | D18: =INDEX(Parameters!$G$5:$G$689,MATCH(Inputs!$B$4&"|IR|"&"delta_tenor_corr"&"|"&$A18&"|"&D$7,Parameters!$A$5:$A$689,0)) -> 0.25 | E18: =INDEX(Parameters!$G$5:$G$689,MATCH(Inputs!$B$4&"|IR|"&"delta_tenor_corr"&"|"&$A18&"|"&E$7,Parameters!$A$5:$A$689,0)) -> 0.44 | F18: =INDEX(Parameters!$G$5:$G$689,MATCH(Inputs!$B$4&"|IR|"&"delta_tenor_corr"&"|"&$A18&"|"&F$7,Parameters!$A$5:$A$689,0)) -> 0.64 | G18: =INDEX(Parameters!$G$5:$G$689,MATCH(Inputs!$B$4&"|IR|"&"delta_tenor_corr"&"|"&$A18&"|"&G$7,Parameters!$A$5:$A$689,0)) -> 0.77 | H18: =INDEX(Parameters!$G$5:$G$689,MATCH(Inputs!$B$4&"|IR|"&"delta_tenor_corr"&"|"&$A18&"|"&H$7,Parameters!$A$5:$A$689,0)) -> 0.82 | I18: =INDEX(Parameters!$G$5:$G$689,MATCH(Inputs!$B$4&"|IR|"&"delta_tenor_corr"&"|"&$A18&"|"&I$7,Parameters!$A$5:$A$689,0)) -> 0.89 | ... M18: =INDEX(Parameters!$G$5:$G$689,MATCH(Inputs!$B$4&"|IR|"&"delta_tenor_corr"&"|"&$A18&"|"&M$7,Parameters!$A$5:$A$689,0)) -> 0.98
A19: =Inputs!$M$14 -> 30y | B19: =INDEX(Parameters!$G$5:$G$689,MATCH(Inputs!$B$4&"|IR|"&"delta_tenor_corr"&"|"&$A19&"|"&B$7,Parameters!$A$5:$A$689,0)) -> 0.14 | C19: =INDEX(Parameters!$G$5:$G$689,MATCH(Inputs!$B$4&"|IR|"&"delta_tenor_corr"&"|"&$A19&"|"&C$7,Parameters!$A$5:$A$689,0)) -> 0.14 | D19: =INDEX(Parameters!$G$5:$G$689,MATCH(Inputs!$B$4&"|IR|"&"delta_tenor_corr"&"|"&$A19&"|"&D$7,Parameters!$A$5:$A$689,0)) -> 0.25 | E19: =INDEX(Parameters!$G$5:$G$689,MATCH(Inputs!$B$4&"|IR|"&"delta_tenor_corr"&"|"&$A19&"|"&E$7,Parameters!$A$5:$A$689,0)) -> 0.42 | F19: =INDEX(Parameters!$G$5:$G$689,MATCH(Inputs!$B$4&"|IR|"&"delta_tenor_corr"&"|"&$A19&"|"&F$7,Parameters!$A$5:$A$689,0)) -> 0.63 | G19: =INDEX(Parameters!$G$5:$G$689,MATCH(Inputs!$B$4&"|IR|"&"delta_tenor_corr"&"|"&$A19&"|"&G$7,Parameters!$A$5:$A$689,0)) -> 0.76 | H19: =INDEX(Parameters!$G$5:$G$689,MATCH(Inputs!$B$4&"|IR|"&"delta_tenor_corr"&"|"&$A19&"|"&H$7,Parameters!$A$5:$A$689,0)) -> 0.81 | I19: =INDEX(Parameters!$G$5:$G$689,MATCH(Inputs!$B$4&"|IR|"&"delta_tenor_corr"&"|"&$A19&"|"&I$7,Parameters!$A$5:$A$689,0)) -> 0.88 | ... M19: =INDEX(Parameters!$G$5:$G$689,MATCH(Inputs!$B$4&"|IR|"&"delta_tenor_corr"&"|"&$A19&"|"&M$7,Parameters!$A$5:$A$689,0)) -> 1
A23: Currency | B23: =Inputs!$B$13 -> USD
A24: RW group | B24: =IF(ISNUMBER(MATCH(Inputs!$B$4&"|IR|rw_group_member|regular|"&$B$23,Parameters!$A$5:$A$689,0)),"regular",IF(ISNUMBER(MATCH(Inputs!$B$4&"|IR|rw_group_member|low|"&$B$23,Parameters!$A$5:$A$689,0)),"low","high")) -> regular
A25: Concentration group | B25: =IF(ISNUMBER(MATCH(Inputs!$B$4&"|IR|ct_group_member|regular_well_traded|"&$B$23,Parameters!$A$5:$A$689,0)),"regular_well_traded",IF(ISNUMBER(MATCH(Inputs!$B$4&"|IR|ct_group_member|regular_less_well_traded|"&$B$23,Parameters!$A$5:$A$689,0)),"regular_less_well_traded",IF(ISNUMBER(MATCH(Inputs!$B$4&"|IR|ct_group_member|low|"&$B$23,Parameters!$A$5:$A$689,0)),"low","high"))) -> regular_well_traded
A26: Concentration threshold (USD mm per bp) | B26: =INDEX(Parameters!$G$5:$G$689,MATCH(Inputs!$B$4&"|IR|"&"delta_ct"&"|"&$B$25&"|"&"",Parameters!$A$5:$A$689,0)) -> 220
A27: Sum of net sensitivities | B27: =SUM(B33:B44) -> 11903.266
A28: CR | B28: =MAX(1,SQRT(ABS($B$27)/Inputs!$B$9/$B$26)) -> 1
A29: K | B29: =SQRT(MAX(0,SUM(E33:P44))) -> 808937.05
A30: Sum of WS | B30: =SUM(D33:D44) -> 693429.6
A31: S | B31: =MAX(-$B$29,MIN($B$29,$B$30)) -> 693429.6
A32: Tenor | B32: Net sensitivity | C32: RW | D32: WS | E32: =Inputs!$B$14 -> 2w | F32: =Inputs!$C$14 -> 1m | G32: =Inputs!$D$14 -> 3m | H32: =Inputs!$E$14 -> 6m | I32: =Inputs!$F$14 -> 1y | J32: =Inputs!$G$14 -> 2y | K32: =Inputs!$H$14 -> 3y | L32: =Inputs!$I$14 -> 5y | M32: =Inputs!$J$14 -> 10y | N32: =Inputs!$K$14 -> 15y | O32: =Inputs!$L$14 -> 20y | P32: =Inputs!$M$14 -> 30y
A33: =Inputs!$B$14 -> 2w | B33: =SUMIFS(Sensitivities!$I$5:$I$100,Sensitivities!$B$5:$B$100,"Risk_IRCurve",Sensitivities!$C$5:$C$100,$B$23,Sensitivities!$E$5:$E$100,$A33) -> 0 | C33: =INDEX(Parameters!$G$5:$G$689,MATCH(Inputs!$B$4&"|IR|"&"delta_rw"&"|"&$B$24&"|"&$A33,Parameters!$A$5:$A$689,0)) -> 107 | D33: =C33*B33*$B$28 -> 0 | E33: =SIMM_Delta!$B$8*$D$33*$D$33 -> 0 | F33: =SIMM_Delta!$C$8*$D$33*$D$34 -> 0 | G33: =SIMM_Delta!$D$8*$D$33*$D$35 -> 0 | H33: =SIMM_Delta!$E$8*$D$33*$D$36 -> 0 | I33: =SIMM_Delta!$F$8*$D$33*$D$37 -> 0 | J33: =SIMM_Delta!$G$8*$D$33*$D$38 -> 0 | K33: =SIMM_Delta!$H$8*$D$33*$D$39 -> 0 | L33: =SIMM_Delta!$I$8*$D$33*$D$40 -> 0 | M33: =SIMM_Delta!$J$8*$D$33*$D$41 -> 0 | N33: =SIMM_Delta!$K$8*$D$33*$D$42 -> 0 | O33: =SIMM_Delta!$L$8*$D$33*$D$43 -> 0 | P33: =SIMM_Delta!$M$8*$D$33*$D$44 -> 0
A34: =Inputs!$C$14 -> 1m | B34: =SUMIFS(Sensitivities!$I$5:$I$100,Sensitivities!$B$5:$B$100,"Risk_IRCurve",Sensitivities!$C$5:$C$100,$B$23,Sensitivities!$E$5:$E$100,$A34) -> 0 | C34: =INDEX(Parameters!$G$5:$G$689,MATCH(Inputs!$B$4&"|IR|"&"delta_rw"&"|"&$B$24&"|"&$A34,Parameters!$A$5:$A$689,0)) -> 101 | D34: =C34*B34*$B$28 -> 0 | E34: =SIMM_Delta!$B$9*$D$34*$D$33 -> 0 | F34: =SIMM_Delta!$C$9*$D$34*$D$34 -> 0 | G34: =SIMM_Delta!$D$9*$D$34*$D$35 -> 0 | H34: =SIMM_Delta!$E$9*$D$34*$D$36 -> 0 | I34: =SIMM_Delta!$F$9*$D$34*$D$37 -> 0 | J34: =SIMM_Delta!$G$9*$D$34*$D$38 -> 0 | K34: =SIMM_Delta!$H$9*$D$34*$D$39 -> 0 | L34: =SIMM_Delta!$I$9*$D$34*$D$40 -> 0 | M34: =SIMM_Delta!$J$9*$D$34*$D$41 -> 0 | N34: =SIMM_Delta!$K$9*$D$34*$D$42 -> 0 | O34: =SIMM_Delta!$L$9*$D$34*$D$43 -> 0 | P34: =SIMM_Delta!$M$9*$D$34*$D$44 -> 0
A35: =Inputs!$D$14 -> 3m | B35: =SUMIFS(Sensitivities!$I$5:$I$100,Sensitivities!$B$5:$B$100,"Risk_IRCurve",Sensitivities!$C$5:$C$100,$B$23,Sensitivities!$E$5:$E$100,$A35) -> 45.593765 | C35: =INDEX(Parameters!$G$5:$G$689,MATCH(Inputs!$B$4&"|IR|"&"delta_rw"&"|"&$B$24&"|"&$A35,Parameters!$A$5:$A$689,0)) -> 90 | D35: =C35*B35*$B$28 -> 4103.4388 | E35: =SIMM_Delta!$B$10*$D$35*$D$33 -> 0 | F35: =SIMM_Delta!$C$10*$D$35*$D$34 -> 0 | G35: =SIMM_Delta!$D$10*$D$35*$D$35 -> 16838210 | H35: =SIMM_Delta!$E$10*$D$35*$D$36 -> 4.6488269e+08 | I35: =SIMM_Delta!$F$10*$D$35*$D$37 -> -1.0118286e+09 | J35: =SIMM_Delta!$G$10*$D$35*$D$38 -> 1.6777909e+09 | K35: =SIMM_Delta!$H$10*$D$35*$D$39 -> -10589975 | L35: =SIMM_Delta!$I$10*$D$35*$D$40 -> -3.8049766e+08 | M35: =SIMM_Delta!$J$10*$D$35*$D$41 -> 1.9300656e+09 | N35: =SIMM_Delta!$K$10*$D$35*$D$42 -> 5448765.1 | O35: =SIMM_Delta!$L$10*$D$35*$D$43 -> 13150356 | P35: =SIMM_Delta!$M$10*$D$35*$D$44 -> -1.0405833e+09
A36: =Inputs!$E$14 -> 6m | B36: =SUMIFS(Sensitivities!$I$5:$I$100,Sensitivities!$B$5:$B$100,"Risk_IRCurve",Sensitivities!$C$5:$C$100,$B$23,Sensitivities!$E$5:$E$100,$A36) -> 1824.3318 | C36: =INDEX(Parameters!$G$5:$G$689,MATCH(Inputs!$B$4&"|IR|"&"delta_rw"&"|"&$B$24&"|"&$A36,Parameters!$A$5:$A$689,0)) -> 69 | D36: =C36*B36*$B$28 -> 125878.89 | E36: =SIMM_Delta!$B$11*$D$36*$D$33 -> 0 | F36: =SIMM_Delta!$C$11*$D$36*$D$34 -> 0 | G36: =SIMM_Delta!$D$11*$D$36*$D$35 -> 4.6488269e+08 | H36: =SIMM_Delta!$E$11*$D$36*$D$36 -> 1.5845495e+10 | I36: =SIMM_Delta!$F$11*$D$36*$D$37 -> -3.8686661e+10 | J36: =SIMM_Delta!$G$11*$D$36*$D$38 -> 7.0890783e+10 | K36: =SIMM_Delta!$H$11*$D$36*$D$39 -> -4.5904514e+08 | L36: =SIMM_Delta!$I$11*$D$36*$D$40 -> -1.6924854e+10 | M36: =SIMM_Delta!$J$11*$D$36*$D$41 -> 9.0552707e+10 | N36: =SIMM_Delta!$K$11*$D$36*$D$42 -> 2.9096257e+08 | O36: =SIMM_Delta!$L$11*$D$36*$D$43 -> 7.0999471e+08 | P36: =SIMM_Delta!$M$11*$D$36*$D$44 -> -5.3627937e+10
A37: =Inputs!$F$14 -> 1y | B37: =SUMIFS(Sensitivities!$I$5:$I$100,Sensitivities!$B$5:$B$100,"Risk_IRCurve",Sensitivities!$C$5:$C$100,$B$23,Sensitivities!$E$5:$E$100,$A37) -> -5255.3418 | C37: =INDEX(Parameters!$G$5:$G$689,MATCH(Inputs!$B$4&"|IR|"&"delta_rw"&"|"&$B$24&"|"&$A37,Parameters!$A$5:$A$689,0)) -> 68 | D37: =C37*B37*$B$28 -> -357363.24 | E37: =SIMM_Delta!$B$12*$D$37*$D$33 -> 0 | F37: =SIMM_Delta!$C$12*$D$37*$D$34 -> 0 | G37: =SIMM_Delta!$D$12*$D$37*$D$35 -> -1.0118286e+09 | H37: =SIMM_Delta!$E$12*$D$37*$D$36 -> -3.8686661e+10 | I37: =SIMM_Delta!$F$12*$D$37*$D$37 -> 1.2770849e+11 | J37: =SIMM_Delta!$G$12*$D$37*$D$38 -> -2.5915032e+11 | K37: =SIMM_Delta!$H$12*$D$37*$D$39 -> 1.7442883e+09 | L37: =SIMM_Delta!$I$12*$D$37*$D$40 -> 6.7102536e+10 | M37: =SIMM_Delta!$J$12*$D$37*$D$41 -> -3.6089256e+11 | N37: =SIMM_Delta!$K$12*$D$37*$D$42 -> -1.2126775e+09 | O37: =SIMM_Delta!$L$12*$D$37*$D$43 -> -2.931834e+09 | P37: =SIMM_Delta!$M$12*$D$37*$D$44 -> 2.2837014e+11
A38: =Inputs!$G$14 -> 2y | B38: =SUMIFS(Sensitivities!$I$5:$I$100,Sensitivities!$B$5:$B$100,"Risk_IRCurve",Sensitivities!$C$5:$C$100,$B$23,Sensitivities!$E$5:$E$100,$A38) -> 11180.595 | C38: =INDEX(Parameters!$G$5:$G$689,MATCH(Inputs!$B$4&"|IR|"&"delta_rw"&"|"&$B$24&"|"&$A38,Parameters!$A$5:$A$689,0)) -> 69 | D38: =C38*B38*$B$28 -> 771461.05 | E38: =SIMM_Delta!$B$13*$D$38*$D$33 -> 0 | F38: =SIMM_Delta!$C$13*$D$38*$D$34 -> 0 | G38: =SIMM_Delta!$D$13*$D$38*$D$35 -> 1.6777909e+09 | H38: =SIMM_Delta!$E$13*$D$38*$D$36 -> 7.0890783e+10 | I38: =SIMM_Delta!$F$13*$D$38*$D$37 -> -2.5915032e+11 | J38: =SIMM_Delta!$G$13*$D$38*$D$38 -> 5.9515216e+11 | K38: =SIMM_Delta!$H$13*$D$38*$D$39 -> -4.1983136e+09 | L38: =SIMM_Delta!$I$13*$D$38*$D$40 -> -1.6453029e+11 | M38: =SIMM_Delta!$J$13*$D$38*$D$41 -> 9.1782026e+11 | N38: =SIMM_Delta!$K$13*$D$38*$D$42 -> 3.1111017e+09 | O38: =SIMM_Delta!$L$13*$D$38*$D$43 -> 7.6147256e+09 | P38: =SIMM_Delta!$M$13*$D$38*$D$44 -> -5.947254e+11
A39: =Inputs!$H$14 -> 3y | B39: =SUMIFS(Sensitivities!$I$5:$I$100,Sensitivities!$B$5:$B$100,"Risk_IRCurve",Sensitivities!$C$5:$C$100,$B$23,Sensitivities!$E$5:$E$100,$A39) -> -85.005142 | C39: =INDEX(Parameters!$G$5:$G$689,MATCH(Inputs!$B$4&"|IR|"&"delta_rw"&"|"&$B$24&"|"&$A39,Parameters!$A$5:$A$689,0)) -> 66 | D39: =C39*B39*$B$28 -> -5610.3394 | E39: =SIMM_Delta!$B$14*$D$39*$D$33 -> 0 | F39: =SIMM_Delta!$C$14*$D$39*$D$34 -> 0 | G39: =SIMM_Delta!$D$14*$D$39*$D$35 -> -10589975 | H39: =SIMM_Delta!$E$14*$D$39*$D$36 -> -4.5904514e+08 | I39: =SIMM_Delta!$F$14*$D$39*$D$37 -> 1.7442883e+09 | J39: =SIMM_Delta!$G$14*$D$39*$D$38 -> -4.1983136e+09 | K39: =SIMM_Delta!$H$14*$D$39*$D$39 -> 31475908 | L39: =SIMM_Delta!$I$14*$D$39*$D$40 -> 1.2615513e+09 | M39: =SIMM_Delta!$J$14*$D$39*$D$41 -> -7.0627805e+09 | N39: =SIMM_Delta!$K$14*$D$39*$D$42 -> -24004615 | O39: =SIMM_Delta!$L$14*$D$39*$D$43 -> -58972903 | P39: =SIMM_Delta!$M$14*$D$39*$D$44 -> 4.6095978e+09
A40: =Inputs!$I$14 -> 5y | B40: =SUMIFS(Sensitivities!$I$5:$I$100,Sensitivities!$B$5:$B$100,"Risk_IRCurve",Sensitivities!$C$5:$C$100,$B$23,Sensitivities!$E$5:$E$100,$A40) -> -3800.2678 | C40: =INDEX(Parameters!$G$5:$G$689,MATCH(Inputs!$B$4&"|IR|"&"delta_rw"&"|"&$B$24&"|"&$A40,Parameters!$A$5:$A$689,0)) -> 61 | D40: =C40*B40*$B$28 -> -231816.33 | E40: =SIMM_Delta!$B$15*$D$40*$D$33 -> 0 | F40: =SIMM_Delta!$C$15*$D$40*$D$34 -> 0 | G40: =SIMM_Delta!$D$15*$D$40*$D$35 -> -3.8049766e+08 | H40: =SIMM_Delta!$E$15*$D$40*$D$36 -> -1.6924854e+10 | I40: =SIMM_Delta!$F$15*$D$40*$D$37 -> 6.7102536e+10 | J40: =SIMM_Delta!$G$15*$D$40*$D$38 -> -1.6453029e+11 | K40: =SIMM_Delta!$H$15*$D$40*$D$39 -> 1.2615513e+09 | L40: =SIMM_Delta!$I$15*$D$40*$D$40 -> 5.3738813e+10 | M40: =SIMM_Delta!$J$15*$D$40*$D$41 -> -3.0786509e+11 | N40: =SIMM_Delta!$K$15*$D$40*$D$42 -> -1.0602623e+09 | O40: =SIMM_Delta!$L$15*$D$40*$D$43 -> -2.6447435e+09 | P40: =SIMM_Delta!$M$15*$D$40*$D$44 -> 2.0692625e+11
A41: =Inputs!$J$14 -> 10y | B41: =SUMIFS(Sensitivities!$I$5:$I$100,Sensitivities!$B$5:$B$100,"Risk_IRCurve",Sensitivities!$C$5:$C$100,$B$23,Sensitivities!$E$5:$E$100,$A41) -> 23056.529 | C41: =INDEX(Parameters!$G$5:$G$689,MATCH(Inputs!$B$4&"|IR|"&"delta_rw"&"|"&$B$24&"|"&$A41,Parameters!$A$5:$A$689,0)) -> 60 | D41: =C41*B41*$B$28 -> 1383391.8 | E41: =SIMM_Delta!$B$16*$D$41*$D$33 -> 0 | F41: =SIMM_Delta!$C$16*$D$41*$D$34 -> 0 | G41: =SIMM_Delta!$D$16*$D$41*$D$35 -> 1.9300656e+09 | H41: =SIMM_Delta!$E$16*$D$41*$D$36 -> 9.0552707e+10 | I41: =SIMM_Delta!$F$16*$D$41*$D$37 -> -3.6089256e+11 | J41: =SIMM_Delta!$G$16*$D$41*$D$38 -> 9.1782026e+11 | K41: =SIMM_Delta!$H$16*$D$41*$D$39 -> -7.0627805e+09 | L41: =SIMM_Delta!$I$16*$D$41*$D$40 -> -3.0786509e+11 | M41: =SIMM_Delta!$J$16*$D$41*$D$41 -> 1.9137728e+12 | N41: =SIMM_Delta!$K$16*$D$41*$D$42 -> 6.667417e+09 | O41: =SIMM_Delta!$L$16*$D$41*$D$43 -> 1.6846835e+10 | P41: =SIMM_Delta!$M$16*$D$41*$D$44 -> -1.3330845e+12
A42: =Inputs!$K$14 -> 15y | B42: =SUMIFS(Sensitivities!$I$5:$I$100,Sensitivities!$B$5:$B$100,"Risk_IRCurve",Sensitivities!$C$5:$C$100,$B$23,Sensitivities!$E$5:$E$100,$A42) -> 84.79268 | C42: =INDEX(Parameters!$G$5:$G$689,MATCH(Inputs!$B$4&"|IR|"&"delta_rw"&"|"&$B$24&"|"&$A42,Parameters!$A$5:$A$689,0)) -> 58 | D42: =C42*B42*$B$28 -> 4917.9754 | E42: =SIMM_Delta!$B$17*$D$42*$D$33 -> 0 | F42: =SIMM_Delta!$C$17*$D$42*$D$34 -> 0 | G42: =SIMM_Delta!$D$17*$D$42*$D$35 -> 5448765.1 | H42: =SIMM_Delta!$E$17*$D$42*$D$36 -> 2.9096257e+08 | I42: =SIMM_Delta!$F$17*$D$42*$D$37 -> -1.2126775e+09 | J42: =SIMM_Delta!$G$17*$D$42*$D$38 -> 3.1111017e+09 | K42: =SIMM_Delta!$H$17*$D$42*$D$39 -> -24004615 | L42: =SIMM_Delta!$I$17*$D$42*$D$40 -> -1.0602623e+09 | M42: =SIMM_Delta!$J$17*$D$42*$D$41 -> 6.667417e+09 | N42: =SIMM_Delta!$K$17*$D$42*$D$42 -> 24186483 | O42: =SIMM_Delta!$L$17*$D$42*$D$43 -> 61781999 | P42: =SIMM_Delta!$M$17*$D$42*$D$44 -> -4.8389037e+09
A43: =Inputs!$L$14 -> 20y | B43: =SUMIFS(Sensitivities!$I$5:$I$100,Sensitivities!$B$5:$B$100,"Risk_IRCurve",Sensitivities!$C$5:$C$100,$B$23,Sensitivities!$E$5:$E$100,$A43) -> 221.01489 | C43: =INDEX(Parameters!$G$5:$G$689,MATCH(Inputs!$B$4&"|IR|"&"delta_rw"&"|"&$B$24&"|"&$A43,Parameters!$A$5:$A$689,0)) -> 58 | D43: =C43*B43*$B$28 -> 12818.864 | E43: =SIMM_Delta!$B$18*$D$43*$D$33 -> 0 | F43: =SIMM_Delta!$C$18*$D$43*$D$34 -> 0 | G43: =SIMM_Delta!$D$18*$D$43*$D$35 -> 13150356 | H43: =SIMM_Delta!$E$18*$D$43*$D$36 -> 7.0999471e+08 | I43: =SIMM_Delta!$F$18*$D$43*$D$37 -> -2.931834e+09 | J43: =SIMM_Delta!$G$18*$D$43*$D$38 -> 7.6147256e+09 | K43: =SIMM_Delta!$H$18*$D$43*$D$39 -> -58972903 | L43: =SIMM_Delta!$I$18*$D$43*$D$40 -> -2.6447435e+09 | M43: =SIMM_Delta!$J$18*$D$43*$D$41 -> 1.6846835e+10 | N43: =SIMM_Delta!$K$18*$D$43*$D$42 -> 61781999 | O43: =SIMM_Delta!$L$18*$D$43*$D$43 -> 1.6432326e+08 | P43: =SIMM_Delta!$M$18*$D$43*$D$44 -> -1.2742789e+10
A44: =Inputs!$M$14 -> 30y | B44: =SUMIFS(Sensitivities!$I$5:$I$100,Sensitivities!$B$5:$B$100,"Risk_IRCurve",Sensitivities!$C$5:$C$100,$B$23,Sensitivities!$E$5:$E$100,$A44) -> -15368.977 | C44: =INDEX(Parameters!$G$5:$G$689,MATCH(Inputs!$B$4&"|IR|"&"delta_rw"&"|"&$B$24&"|"&$A44,Parameters!$A$5:$A$689,0)) -> 66 | D44: =C44*B44*$B$28 -> -1014352.5 | E44: =SIMM_Delta!$B$19*$D$44*$D$33 -> 0 | F44: =SIMM_Delta!$C$19*$D$44*$D$34 -> 0 | G44: =SIMM_Delta!$D$19*$D$44*$D$35 -> -1.0405833e+09 | H44: =SIMM_Delta!$E$19*$D$44*$D$36 -> -5.3627937e+10 | I44: =SIMM_Delta!$F$19*$D$44*$D$37 -> 2.2837014e+11 | J44: =SIMM_Delta!$G$19*$D$44*$D$38 -> -5.947254e+11 | K44: =SIMM_Delta!$H$19*$D$44*$D$39 -> 4.6095978e+09 | L44: =SIMM_Delta!$I$19*$D$44*$D$40 -> 2.0692625e+11 | M44: =SIMM_Delta!$J$19*$D$44*$D$41 -> -1.3330845e+12 | N44: =SIMM_Delta!$K$19*$D$44*$D$42 -> -4.8389037e+09 | O44: =SIMM_Delta!$L$19*$D$44*$D$43 -> -1.2742789e+10 | P44: =SIMM_Delta!$M$19*$D$44*$D$44 -> 1.0289109e+12
A48: Currency | B48: =Inputs!$C$13 -> EUR
A49: RW group | B49: =IF(ISNUMBER(MATCH(Inputs!$B$4&"|IR|rw_group_member|regular|"&$B$48,Parameters!$A$5:$A$689,0)),"regular",IF(ISNUMBER(MATCH(Inputs!$B$4&"|IR|rw_group_member|low|"&$B$48,Parameters!$A$5:$A$689,0)),"low","high")) -> regular
A50: Concentration group | B50: =IF(ISNUMBER(MATCH(Inputs!$B$4&"|IR|ct_group_member|regular_well_traded|"&$B$48,Parameters!$A$5:$A$689,0)),"regular_well_traded",IF(ISNUMBER(MATCH(Inputs!$B$4&"|IR|ct_group_member|regular_less_well_traded|"&$B$48,Parameters!$A$5:$A$689,0)),"regular_less_well_traded",IF(ISNUMBER(MATCH(Inputs!$B$4&"|IR|ct_group_member|low|"&$B$48,Parameters!$A$5:$A$689,0)),"low","high"))) -> regular_well_traded
A51: Concentration threshold (USD mm per bp) | B51: =INDEX(Parameters!$G$5:$G$689,MATCH(Inputs!$B$4&"|IR|"&"delta_ct"&"|"&$B$50&"|"&"",Parameters!$A$5:$A$689,0)) -> 220
A52: Sum of net sensitivities | B52: =SUM(B58:B69) -> -22494.843
A53: CR | B53: =MAX(1,SQRT(ABS($B$52)/Inputs!$B$9/$B$51)) -> 1
A54: K | B54: =SQRT(MAX(0,SUM(E58:P69))) -> 1351537.7
A55: Sum of WS | B55: =SUM(D58:D69) -> -1306486.3
A56: S | B56: =MAX(-$B$54,MIN($B$54,$B$55)) -> -1306486.3
A57: Tenor | B57: Net sensitivity | C57: RW | D57: WS | E57: =Inputs!$B$14 -> 2w | F57: =Inputs!$C$14 -> 1m | G57: =Inputs!$D$14 -> 3m | H57: =Inputs!$E$14 -> 6m | I57: =Inputs!$F$14 -> 1y | J57: =Inputs!$G$14 -> 2y | K57: =Inputs!$H$14 -> 3y | L57: =Inputs!$I$14 -> 5y | M57: =Inputs!$J$14 -> 10y | N57: =Inputs!$K$14 -> 15y | O57: =Inputs!$L$14 -> 20y | P57: =Inputs!$M$14 -> 30y
A58: =Inputs!$B$14 -> 2w | B58: =SUMIFS(Sensitivities!$I$5:$I$100,Sensitivities!$B$5:$B$100,"Risk_IRCurve",Sensitivities!$C$5:$C$100,$B$48,Sensitivities!$E$5:$E$100,$A58) -> 0 | C58: =INDEX(Parameters!$G$5:$G$689,MATCH(Inputs!$B$4&"|IR|"&"delta_rw"&"|"&$B$49&"|"&$A58,Parameters!$A$5:$A$689,0)) -> 107 | D58: =C58*B58*$B$53 -> 0 | E58: =SIMM_Delta!$B$8*$D$58*$D$58 -> 0 | F58: =SIMM_Delta!$C$8*$D$58*$D$59 -> 0 | G58: =SIMM_Delta!$D$8*$D$58*$D$60 -> 0 | H58: =SIMM_Delta!$E$8*$D$58*$D$61 -> 0 | I58: =SIMM_Delta!$F$8*$D$58*$D$62 -> 0 | J58: =SIMM_Delta!$G$8*$D$58*$D$63 -> 0 | K58: =SIMM_Delta!$H$8*$D$58*$D$64 -> 0 | L58: =SIMM_Delta!$I$8*$D$58*$D$65 -> 0 | M58: =SIMM_Delta!$J$8*$D$58*$D$66 -> 0 | N58: =SIMM_Delta!$K$8*$D$58*$D$67 -> 0 | O58: =SIMM_Delta!$L$8*$D$58*$D$68 -> 0 | P58: =SIMM_Delta!$M$8*$D$58*$D$69 -> 0
A59: =Inputs!$C$14 -> 1m | B59: =SUMIFS(Sensitivities!$I$5:$I$100,Sensitivities!$B$5:$B$100,"Risk_IRCurve",Sensitivities!$C$5:$C$100,$B$48,Sensitivities!$E$5:$E$100,$A59) -> 0 | C59: =INDEX(Parameters!$G$5:$G$689,MATCH(Inputs!$B$4&"|IR|"&"delta_rw"&"|"&$B$49&"|"&$A59,Parameters!$A$5:$A$689,0)) -> 101 | D59: =C59*B59*$B$53 -> 0 | E59: =SIMM_Delta!$B$9*$D$59*$D$58 -> 0 | F59: =SIMM_Delta!$C$9*$D$59*$D$59 -> 0 | G59: =SIMM_Delta!$D$9*$D$59*$D$60 -> 0 | H59: =SIMM_Delta!$E$9*$D$59*$D$61 -> 0 | I59: =SIMM_Delta!$F$9*$D$59*$D$62 -> 0 | J59: =SIMM_Delta!$G$9*$D$59*$D$63 -> 0 | K59: =SIMM_Delta!$H$9*$D$59*$D$64 -> 0 | L59: =SIMM_Delta!$I$9*$D$59*$D$65 -> 0 | M59: =SIMM_Delta!$J$9*$D$59*$D$66 -> 0 | N59: =SIMM_Delta!$K$9*$D$59*$D$67 -> 0 | O59: =SIMM_Delta!$L$9*$D$59*$D$68 -> 0 | P59: =SIMM_Delta!$M$9*$D$59*$D$69 -> 0
A60: =Inputs!$D$14 -> 3m | B60: =SUMIFS(Sensitivities!$I$5:$I$100,Sensitivities!$B$5:$B$100,"Risk_IRCurve",Sensitivities!$C$5:$C$100,$B$48,Sensitivities!$E$5:$E$100,$A60) -> -601.57798 | C60: =INDEX(Parameters!$G$5:$G$689,MATCH(Inputs!$B$4&"|IR|"&"delta_rw"&"|"&$B$49&"|"&$A60,Parameters!$A$5:$A$689,0)) -> 90 | D60: =C60*B60*$B$53 -> -54142.018 | E60: =SIMM_Delta!$B$10*$D$60*$D$58 -> 0 | F60: =SIMM_Delta!$C$10*$D$60*$D$59 -> 0 | G60: =SIMM_Delta!$D$10*$D$60*$D$60 -> 2.9313581e+09 | H60: =SIMM_Delta!$E$10*$D$60*$D$61 -> 5.0019954e+09 | I60: =SIMM_Delta!$F$10*$D$60*$D$62 -> 7437615.3 | J60: =SIMM_Delta!$G$10*$D$60*$D$63 -> 11733334 | K60: =SIMM_Delta!$H$10*$D$60*$D$64 -> -5.5483498e+09 | L60: =SIMM_Delta!$I$10*$D$60*$D$65 -> -2.6311587e+10 | M60: =SIMM_Delta!$J$10*$D$60*$D$66 -> 2.9175243e+10 | N60: =SIMM_Delta!$K$10*$D$60*$D$67 -> 1.4646101e+10 | O60: =SIMM_Delta!$L$10*$D$60*$D$68 -> 0 | P60: =SIMM_Delta!$M$10*$D$60*$D$69 -> 0
A61: =Inputs!$E$14 -> 6m | B61: =SUMIFS(Sensitivities!$I$5:$I$100,Sensitivities!$B$5:$B$100,"Risk_IRCurve",Sensitivities!$C$5:$C$100,$B$48,Sensitivities!$E$5:$E$100,$A61) -> -1487.7065 | C61: =INDEX(Parameters!$G$5:$G$689,MATCH(Inputs!$B$4&"|IR|"&"delta_rw"&"|"&$B$49&"|"&$A61,Parameters!$A$5:$A$689,0)) -> 69 | D61: =C61*B61*$B$53 -> -102651.75 | E61: =SIMM_Delta!$B$11*$D$61*$D$58 -> 0 | F61: =SIMM_Delta!$C$11*$D$61*$D$59 -> 0 | G61: =SIMM_Delta!$D$11*$D$61*$D$60 -> 5.0019954e+09 | H61: =SIMM_Delta!$E$11*$D$61*$D$61 -> 1.0537381e+10 | I61: =SIMM_Delta!$F$11*$D$61*$D$62 -> 17575795 | J61: =SIMM_Delta!$G$11*$D$61*$D$63 -> 30640816 | K61: =SIMM_Delta!$H$11*$D$61*$D$64 -> -1.4864533e+10 | L61: =SIMM_Delta!$I$11*$D$61*$D$65 -> -7.2334743e+10 | M61: =SIMM_Delta!$J$11*$D$61*$D$66 -> 8.4600086e+10 | N61: =SIMM_Delta!$K$11*$D$61*$D$67 -> 4.8337925e+10 | O61: =SIMM_Delta!$L$11*$D$61*$D$68 -> 0 | P61: =SIMM_Delta!$M$11*$D$61*$D$69 -> 0
A62: =Inputs!$F$14 -> 1y | B62: =SUMIFS(Sensitivities!$I$5:$I$100,Sensitivities!$B$5:$B$100,"Risk_IRCurve",Sensitivities!$C$5:$C$100,$B$48,Sensitivities!$E$5:$E$100,$A62) -> -2.9277991 | C62: =INDEX(Parameters!$G$5:$G$689,MATCH(Inputs!$B$4&"|IR|"&"delta_rw"&"|"&$B$49&"|"&$A62,Parameters!$A$5:$A$689,0)) -> 68 | D62: =C62*B62*$B$53 -> -199.09034 | E62: =SIMM_Delta!$B$12*$D$62*$D$58 -> 0 | F62: =SIMM_Delta!$C$12*$D$62*$D$59 -> 0 | G62: =SIMM_Delta!$D$12*$D$62*$D$60 -> 7437615.3 | H62: =SIMM_Delta!$E$12*$D$62*$D$61 -> 17575795 | I62: =SIMM_Delta!$F$12*$D$62*$D$62 -> 39636.962 | J62: =SIMM_Delta!$G$12*$D$62*$D$63 -> 76522.502 | K62: =SIMM_Delta!$H$12*$D$62*$D$64 -> -38586998 | L62: =SIMM_Delta!$I$12*$D$62*$D$65 -> -1.9592408e+08 | M62: =SIMM_Delta!$J$12*$D$62*$D$66 -> 2.3034255e+08 | N62: =SIMM_Delta!$K$12*$D$62*$D$67 -> 1.3763316e+08 | O62: =SIMM_Delta!$L$12*$D$62*$D$68 -> 0 | P62: =SIMM_Delta!$M$12*$D$62*$D$69 -> 0
A63: =Inputs!$G$14 -> 2y | B63: =SUMIFS(Sensitivities!$I$5:$I$100,Sensitivities!$B$5:$B$100,"Risk_IRCurve",Sensitivities!$C$5:$C$100,$B$48,Sensitivities!$E$5:$E$100,$A63) -> -5.9260053 | C63: =INDEX(Parameters!$G$5:$G$689,MATCH(Inputs!$B$4&"|IR|"&"delta_rw"&"|"&$B$49&"|"&$A63,Parameters!$A$5:$A$689,0)) -> 69 | D63: =C63*B63*$B$53 -> -408.89436 | E63: =SIMM_Delta!$B$13*$D$63*$D$58 -> 0 | F63: =SIMM_Delta!$C$13*$D$63*$D$59 -> 0 | G63: =SIMM_Delta!$D$13*$D$63*$D$60 -> 11733334 | H63: =SIMM_Delta!$E$13*$D$63*$D$61 -> 30640816 | I63: =SIMM_Delta!$F$13*$D$63*$D$62 -> 76522.502 | J63: =SIMM_Delta!$G$13*$D$63*$D$63 -> 167194.6 | K63: =SIMM_Delta!$H$13*$D$63*$D$64 -> -88359738 | L63: =SIMM_Delta!$I$13*$D$63*$D$65 -> -4.5703721e+08 | M63: =SIMM_Delta!$J$13*$D$63*$D$66 -> 5.5732779e+08 | N63: =SIMM_Delta!$K$13*$D$63*$D$67 -> 3.3593e+08 | O63: =SIMM_Delta!$L$13*$D$63*$D$68 -> 0 | P63: =SIMM_Delta!$M$13*$D$63*$D$69 -> 0
A64: =Inputs!$H$14 -> 3y | B64: =SUMIFS(Sensitivities!$I$5:$I$100,Sensitivities!$B$5:$B$100,"Risk_IRCurve",Sensitivities!$C$5:$C$100,$B$48,Sensitivities!$E$5:$E$100,$A64) -> 3375.4185 | C64: =INDEX(Parameters!$G$5:$G$689,MATCH(Inputs!$B$4&"|IR|"&"delta_rw"&"|"&$B$49&"|"&$A64,Parameters!$A$5:$A$689,0)) -> 66 | D64: =C64*B64*$B$53 -> 222777.62 | E64: =SIMM_Delta!$B$14*$D$64*$D$58 -> 0 | F64: =SIMM_Delta!$C$14*$D$64*$D$59 -> 0 | G64: =SIMM_Delta!$D$14*$D$64*$D$60 -> -5.5483498e+09 | H64: =SIMM_Delta!$E$14*$D$64*$D$61 -> -1.4864533e+10 | I64: =SIMM_Delta!$F$14*$D$64*$D$62 -> -38586998 | J64: =SIMM_Delta!$G$14*$D$64*$D$63 -> -88359738 | K64: =SIMM_Delta!$H$14*$D$64*$D$64 -> 4.9629868e+10 | L64: =SIMM_Delta!$I$14*$D$64*$D$65 -> 2.6254026e+11 | M64: =SIMM_Delta!$J$14*$D$64*$D$66 -> -3.2130248e+11 | N64: =SIMM_Delta!$K$14*$D$64*$D$67 -> -1.9418453e+11 | O64: =SIMM_Delta!$L$14*$D$64*$D$68 -> 0 | P64: =SIMM_Delta!$M$14*$D$64*$D$69 -> 0
A65: =Inputs!$I$14 -> 5y | B65: =SUMIFS(Sensitivities!$I$5:$I$100,Sensitivities!$B$5:$B$100,"Risk_IRCurve",Sensitivities!$C$5:$C$100,$B$48,Sensitivities!$E$5:$E$100,$A65) -> 19916.947 | C65: =INDEX(Parameters!$G$5:$G$689,MATCH(Inputs!$B$4&"|IR|"&"delta_rw"&"|"&$B$49&"|"&$A65,Parameters!$A$5:$A$689,0)) -> 61 | D65: =C65*B65*$B$53 -> 1214933.8 | E65: =SIMM_Delta!$B$15*$D$65*$D$58 -> 0 | F65: =SIMM_Delta!$C$15*$D$65*$D$59 -> 0 | G65: =SIMM_Delta!$D$15*$D$65*$D$60 -> -2.6311587e+10 | H65: =SIMM_Delta!$E$15*$D$65*$D$61 -> -7.2334743e+10 | I65: =SIMM_Delta!$F$15*$D$65*$D$62 -> -1.9592408e+08 | J65: =SIMM_Delta!$G$15*$D$65*$D$63 -> -4.5703721e+08 | K65: =SIMM_Delta!$H$15*$D$65*$D$64 -> 2.6254026e+11 | L65: =SIMM_Delta!$I$15*$D$65*$D$65 -> 1.4760641e+12 | M65: =SIMM_Delta!$J$15*$D$65*$D$66 -> -1.8485235e+12 | N65: =SIMM_Delta!$K$15*$D$65*$D$67 -> -1.1320337e+12 | O65: =SIMM_Delta!$L$15*$D$65*$D$68 -> 0 | P65: =SIMM_Delta!$M$15*$D$65*$D$69 -> 0
A66: =Inputs!$J$14 -> 10y | B66: =SUMIFS(Sensitivities!$I$5:$I$100,Sensitivities!$B$5:$B$100,"Risk_IRCurve",Sensitivities!$C$5:$C$100,$B$48,Sensitivities!$E$5:$E$100,$A66) -> -26414.955 | C66: =INDEX(Parameters!$G$5:$G$689,MATCH(Inputs!$B$4&"|IR|"&"delta_rw"&"|"&$B$49&"|"&$A66,Parameters!$A$5:$A$689,0)) -> 60 | D66: =C66*B66*$B$53 -> -1584897.3 | E66: =SIMM_Delta!$B$16*$D$66*$D$58 -> 0 | F66: =SIMM_Delta!$C$16*$D$66*$D$59 -> 0 | G66: =SIMM_Delta!$D$16*$D$66*$D$60 -> 2.9175243e+10 | H66: =SIMM_Delta!$E$16*$D$66*$D$61 -> 8.4600086e+10 | I66: =SIMM_Delta!$F$16*$D$66*$D$62 -> 2.3034255e+08 | J66: =SIMM_Delta!$G$16*$D$66*$D$63 -> 5.5732779e+08 | K66: =SIMM_Delta!$H$16*$D$66*$D$64 -> -3.2130248e+11 | L66: =SIMM_Delta!$I$16*$D$66*$D$65 -> -1.8485235e+12 | M66: =SIMM_Delta!$J$16*$D$66*$D$66 -> 2.5118994e+12 | N66: =SIMM_Delta!$K$16*$D$66*$D$67 -> 1.5561484e+12 | O66: =SIMM_Delta!$L$16*$D$66*$D$68 -> 0 | P66: =SIMM_Delta!$M$16*$D$66*$D$69 -> 0
A67: =Inputs!$K$14 -> 15y | B67: =SUMIFS(Sensitivities!$I$5:$I$100,Sensitivities!$B$5:$B$100,"Risk_IRCurve",Sensitivities!$C$5:$C$100,$B$48,Sensitivities!$E$5:$E$100,$A67) -> -17274.115 | C67: =INDEX(Parameters!$G$5:$G$689,MATCH(Inputs!$B$4&"|IR|"&"delta_rw"&"|"&$B$49&"|"&$A67,Parameters!$A$5:$A$689,0)) -> 58 | D67: =C67*B67*$B$53 -> -1001898.7 | E67: =SIMM_Delta!$B$17*$D$67*$D$58 -> 0 | F67: =SIMM_Delta!$C$17*$D$67*$D$59 -> 0 | G67: =SIMM_Delta!$D$17*$D$67*$D$60 -> 1.4646101e+10 | H67: =SIMM_Delta!$E$17*$D$67*$D$61 -> 4.8337925e+10 | I67: =SIMM_Delta!$F$17*$D$67*$D$62 -> 1.3763316e+08 | J67: =SIMM_Delta!$G$17*$D$67*$D$63 -> 3.3593e+08 | K67: =SIMM_Delta!$H$17*$D$67*$D$64 -> -1.9418453e+11 | L67: =SIMM_Delta!$I$17*$D$67*$D$65 -> -1.1320337e+12 | M67: =SIMM_Delta!$J$17*$D$67*$D$66 -> 1.5561484e+12 | N67: =SIMM_Delta!$K$17*$D$67*$D$67 -> 1.003801e+12 | O67: =SIMM_Delta!$L$17*$D$67*$D$68 -> 0 | P67: =SIMM_Delta!$M$17*$D$67*$D$69 -> 0
A68: =Inputs!$L$14 -> 20y | B68: =SUMIFS(Sensitivities!$I$5:$I$100,Sensitivities!$B$5:$B$100,"Risk_IRCurve",Sensitivities!$C$5:$C$100,$B$48,Sensitivities!$E$5:$E$100,$A68) -> 0 | C68: =INDEX(Parameters!$G$5:$G$689,MATCH(Inputs!$B$4&"|IR|"&"delta_rw"&"|"&$B$49&"|"&$A68,Parameters!$A$5:$A$689,0)) -> 58 | D68: =C68*B68*$B$53 -> 0 | E68: =SIMM_Delta!$B$18*$D$68*$D$58 -> 0 | F68: =SIMM_Delta!$C$18*$D$68*$D$59 -> 0 | G68: =SIMM_Delta!$D$18*$D$68*$D$60 -> 0 | H68: =SIMM_Delta!$E$18*$D$68*$D$61 -> 0 | I68: =SIMM_Delta!$F$18*$D$68*$D$62 -> 0 | J68: =SIMM_Delta!$G$18*$D$68*$D$63 -> 0 | K68: =SIMM_Delta!$H$18*$D$68*$D$64 -> 0 | L68: =SIMM_Delta!$I$18*$D$68*$D$65 -> 0 | M68: =SIMM_Delta!$J$18*$D$68*$D$66 -> 0 | N68: =SIMM_Delta!$K$18*$D$68*$D$67 -> 0 | O68: =SIMM_Delta!$L$18*$D$68*$D$68 -> 0 | P68: =SIMM_Delta!$M$18*$D$68*$D$69 -> 0
A69: =Inputs!$M$14 -> 30y | B69: =SUMIFS(Sensitivities!$I$5:$I$100,Sensitivities!$B$5:$B$100,"Risk_IRCurve",Sensitivities!$C$5:$C$100,$B$48,Sensitivities!$E$5:$E$100,$A69) -> 0 | C69: =INDEX(Parameters!$G$5:$G$689,MATCH(Inputs!$B$4&"|IR|"&"delta_rw"&"|"&$B$49&"|"&$A69,Parameters!$A$5:$A$689,0)) -> 66 | D69: =C69*B69*$B$53 -> 0 | E69: =SIMM_Delta!$B$19*$D$69*$D$58 -> 0 | F69: =SIMM_Delta!$C$19*$D$69*$D$59 -> 0 | G69: =SIMM_Delta!$D$19*$D$69*$D$60 -> 0 | H69: =SIMM_Delta!$E$19*$D$69*$D$61 -> 0 | I69: =SIMM_Delta!$F$19*$D$69*$D$62 -> 0 | J69: =SIMM_Delta!$G$19*$D$69*$D$63 -> 0 | K69: =SIMM_Delta!$H$19*$D$69*$D$64 -> 0 | L69: =SIMM_Delta!$I$19*$D$69*$D$65 -> 0 | M69: =SIMM_Delta!$J$19*$D$69*$D$66 -> 0 | N69: =SIMM_Delta!$K$19*$D$69*$D$67 -> 0 | O69: =SIMM_Delta!$L$19*$D$69*$D$68 -> 0 | P69: =SIMM_Delta!$M$19*$D$69*$D$69 -> 0
A73: Currency | B73: =Inputs!$D$13 -> GBP
A74: RW group | B74: =IF(ISNUMBER(MATCH(Inputs!$B$4&"|IR|rw_group_member|regular|"&$B$73,Parameters!$A$5:$A$689,0)),"regular",IF(ISNUMBER(MATCH(Inputs!$B$4&"|IR|rw_group_member|low|"&$B$73,Parameters!$A$5:$A$689,0)),"low","high")) -> regular
A75: Concentration group | B75: =IF(ISNUMBER(MATCH(Inputs!$B$4&"|IR|ct_group_member|regular_well_traded|"&$B$73,Parameters!$A$5:$A$689,0)),"regular_well_traded",IF(ISNUMBER(MATCH(Inputs!$B$4&"|IR|ct_group_member|regular_less_well_traded|"&$B$73,Parameters!$A$5:$A$689,0)),"regular_less_well_traded",IF(ISNUMBER(MATCH(Inputs!$B$4&"|IR|ct_group_member|low|"&$B$73,Parameters!$A$5:$A$689,0)),"low","high"))) -> regular_well_traded
A76: Concentration threshold (USD mm per bp) | B76: =INDEX(Parameters!$G$5:$G$689,MATCH(Inputs!$B$4&"|IR|"&"delta_ct"&"|"&$B$75&"|"&"",Parameters!$A$5:$A$689,0)) -> 220
A77: Sum of net sensitivities | B77: =SUM(B83:B94) -> 15696.444
A78: CR | B78: =MAX(1,SQRT(ABS($B$77)/Inputs!$B$9/$B$76)) -> 1
A79: K | B79: =SQRT(MAX(0,SUM(E83:P94))) -> 971143.53
A80: Sum of WS | B80: =SUM(D83:D94) -> 972785.07
A81: S | B81: =MAX(-$B$79,MIN($B$79,$B$80)) -> 971143.53
A82: Tenor | B82: Net sensitivity | C82: RW | D82: WS | E82: =Inputs!$B$14 -> 2w | F82: =Inputs!$C$14 -> 1m | G82: =Inputs!$D$14 -> 3m | H82: =Inputs!$E$14 -> 6m | I82: =Inputs!$F$14 -> 1y | J82: =Inputs!$G$14 -> 2y | K82: =Inputs!$H$14 -> 3y | L82: =Inputs!$I$14 -> 5y | M82: =Inputs!$J$14 -> 10y | N82: =Inputs!$K$14 -> 15y | O82: =Inputs!$L$14 -> 20y | P82: =Inputs!$M$14 -> 30y
A83: =Inputs!$B$14 -> 2w | B83: =SUMIFS(Sensitivities!$I$5:$I$100,Sensitivities!$B$5:$B$100,"Risk_IRCurve",Sensitivities!$C$5:$C$100,$B$73,Sensitivities!$E$5:$E$100,$A83) -> 0 | C83: =INDEX(Parameters!$G$5:$G$689,MATCH(Inputs!$B$4&"|IR|"&"delta_rw"&"|"&$B$74&"|"&$A83,Parameters!$A$5:$A$689,0)) -> 107 | D83: =C83*B83*$B$78 -> 0 | E83: =SIMM_Delta!$B$8*$D$83*$D$83 -> 0 | F83: =SIMM_Delta!$C$8*$D$83*$D$84 -> 0 | G83: =SIMM_Delta!$D$8*$D$83*$D$85 -> 0 | H83: =SIMM_Delta!$E$8*$D$83*$D$86 -> 0 | I83: =SIMM_Delta!$F$8*$D$83*$D$87 -> 0 | J83: =SIMM_Delta!$G$8*$D$83*$D$88 -> 0 | K83: =SIMM_Delta!$H$8*$D$83*$D$89 -> 0 | L83: =SIMM_Delta!$I$8*$D$83*$D$90 -> 0 | M83: =SIMM_Delta!$J$8*$D$83*$D$91 -> 0 | N83: =SIMM_Delta!$K$8*$D$83*$D$92 -> 0 | O83: =SIMM_Delta!$L$8*$D$83*$D$93 -> 0 | P83: =SIMM_Delta!$M$8*$D$83*$D$94 -> 0
A84: =Inputs!$C$14 -> 1m | B84: =SUMIFS(Sensitivities!$I$5:$I$100,Sensitivities!$B$5:$B$100,"Risk_IRCurve",Sensitivities!$C$5:$C$100,$B$73,Sensitivities!$E$5:$E$100,$A84) -> 0 | C84: =INDEX(Parameters!$G$5:$G$689,MATCH(Inputs!$B$4&"|IR|"&"delta_rw"&"|"&$B$74&"|"&$A84,Parameters!$A$5:$A$689,0)) -> 101 | D84: =C84*B84*$B$78 -> 0 | E84: =SIMM_Delta!$B$9*$D$84*$D$83 -> 0 | F84: =SIMM_Delta!$C$9*$D$84*$D$84 -> 0 | G84: =SIMM_Delta!$D$9*$D$84*$D$85 -> 0 | H84: =SIMM_Delta!$E$9*$D$84*$D$86 -> 0 | I84: =SIMM_Delta!$F$9*$D$84*$D$87 -> 0 | J84: =SIMM_Delta!$G$9*$D$84*$D$88 -> 0 | K84: =SIMM_Delta!$H$9*$D$84*$D$89 -> 0 | L84: =SIMM_Delta!$I$9*$D$84*$D$90 -> 0 | M84: =SIMM_Delta!$J$9*$D$84*$D$91 -> 0 | N84: =SIMM_Delta!$K$9*$D$84*$D$92 -> 0 | O84: =SIMM_Delta!$L$9*$D$84*$D$93 -> 0 | P84: =SIMM_Delta!$M$9*$D$84*$D$94 -> 0
A85: =Inputs!$D$14 -> 3m | B85: =SUMIFS(Sensitivities!$I$5:$I$100,Sensitivities!$B$5:$B$100,"Risk_IRCurve",Sensitivities!$C$5:$C$100,$B$73,Sensitivities!$E$5:$E$100,$A85) -> 0 | C85: =INDEX(Parameters!$G$5:$G$689,MATCH(Inputs!$B$4&"|IR|"&"delta_rw"&"|"&$B$74&"|"&$A85,Parameters!$A$5:$A$689,0)) -> 90 | D85: =C85*B85*$B$78 -> 0 | E85: =SIMM_Delta!$B$10*$D$85*$D$83 -> 0 | F85: =SIMM_Delta!$C$10*$D$85*$D$84 -> 0 | G85: =SIMM_Delta!$D$10*$D$85*$D$85 -> 0 | H85: =SIMM_Delta!$E$10*$D$85*$D$86 -> 0 | I85: =SIMM_Delta!$F$10*$D$85*$D$87 -> 0 | J85: =SIMM_Delta!$G$10*$D$85*$D$88 -> 0 | K85: =SIMM_Delta!$H$10*$D$85*$D$89 -> 0 | L85: =SIMM_Delta!$I$10*$D$85*$D$90 -> 0 | M85: =SIMM_Delta!$J$10*$D$85*$D$91 -> 0 | N85: =SIMM_Delta!$K$10*$D$85*$D$92 -> 0 | O85: =SIMM_Delta!$L$10*$D$85*$D$93 -> 0 | P85: =SIMM_Delta!$M$10*$D$85*$D$94 -> 0
A86: =Inputs!$E$14 -> 6m | B86: =SUMIFS(Sensitivities!$I$5:$I$100,Sensitivities!$B$5:$B$100,"Risk_IRCurve",Sensitivities!$C$5:$C$100,$B$73,Sensitivities!$E$5:$E$100,$A86) -> -104.83709 | C86: =INDEX(Parameters!$G$5:$G$689,MATCH(Inputs!$B$4&"|IR|"&"delta_rw"&"|"&$B$74&"|"&$A86,Parameters!$A$5:$A$689,0)) -> 69 | D86: =C86*B86*$B$78 -> -7233.7589 | E86: =SIMM_Delta!$B$11*$D$86*$D$83 -> 0 | F86: =SIMM_Delta!$C$11*$D$86*$D$84 -> 0 | G86: =SIMM_Delta!$D$11*$D$86*$D$85 -> 0 | H86: =SIMM_Delta!$E$11*$D$86*$D$86 -> 52327268 | I86: =SIMM_Delta!$F$11*$D$86*$D$87 -> -7.4389954e+08 | J86: =SIMM_Delta!$G$11*$D$86*$D$88 -> 13166465 | K86: =SIMM_Delta!$H$11*$D$86*$D$89 -> 28877830 | L86: =SIMM_Delta!$I$11*$D$86*$D$90 -> -4.8006109e+09 | M86: =SIMM_Delta!$J$11*$D$86*$D$91 -> 1.0349203e+09 | N86: =SIMM_Delta!$K$11*$D$86*$D$92 -> 0 | O86: =SIMM_Delta!$L$11*$D$86*$D$93 -> 0 | P86: =SIMM_Delta!$M$11*$D$86*$D$94 -> 0
A87: =Inputs!$F$14 -> 1y | B87: =SUMIFS(Sensitivities!$I$5:$I$100,Sensitivities!$B$5:$B$100,"Risk_IRCurve",Sensitivities!$C$5:$C$100,$B$73,Sensitivities!$E$5:$E$100,$A87) -> 1758.5021 | C87: =INDEX(Parameters!$G$5:$G$689,MATCH(Inputs!$B$4&"|IR|"&"delta_rw"&"|"&$B$74&"|"&$A87,Parameters!$A$5:$A$689,0)) -> 68 | D87: =C87*B87*$B$78 -> 119578.15 | E87: =SIMM_Delta!$B$12*$D$87*$D$83 -> 0 | F87: =SIMM_Delta!$C$12*$D$87*$D$84 -> 0 | G87: =SIMM_Delta!$D$12*$D$87*$D$85 -> 0 | H87: =SIMM_Delta!$E$12*$D$87*$D$86 -> -7.4389954e+08 | I87: =SIMM_Delta!$F$12*$D$87*$D$87 -> 1.4298933e+10 | J87: =SIMM_Delta!$G$12*$D$87*$D$88 -> -2.8026054e+08 | K87: =SIMM_Delta!$H$12*$D$87*$D$89 -> -6.389373e+08 | L87: =SIMM_Delta!$I$12*$D$87*$D$90 -> 1.1082591e+11 | M87: =SIMM_Delta!$J$12*$D$87*$D$91 -> -2.4016748e+10 | N87: =SIMM_Delta!$K$12*$D$87*$D$92 -> 0 | O87: =SIMM_Delta!$L$12*$D$87*$D$93 -> 0 | P87: =SIMM_Delta!$M$12*$D$87*$D$94 -> 0
A88: =Inputs!$G$14 -> 2y | B88: =SUMIFS(Sensitivities!$I$5:$I$100,Sensitivities!$B$5:$B$100,"Risk_IRCurve",Sensitivities!$C$5:$C$100,$B$73,Sensitivities!$E$5:$E$100,$A88) -> -36.135427 | C88: =INDEX(Parameters!$G$5:$G$689,MATCH(Inputs!$B$4&"|IR|"&"delta_rw"&"|"&$B$74&"|"&$A88,Parameters!$A$5:$A$689,0)) -> 69 | D88: =C88*B88*$B$78 -> -2493.3445 | E88: =SIMM_Delta!$B$13*$D$88*$D$83 -> 0 | F88: =SIMM_Delta!$C$13*$D$88*$D$84 -> 0 | G88: =SIMM_Delta!$D$13*$D$88*$D$85 -> 0 | H88: =SIMM_Delta!$E$13*$D$88*$D$86 -> 13166465 | I88: =SIMM_Delta!$F$13*$D$88*$D$87 -> -2.8026054e+08 | J88: =SIMM_Delta!$G$13*$D$88*$D$88 -> 6216766.8 | K88: =SIMM_Delta!$H$13*$D$88*$D$89 -> 14853924 | L88: =SIMM_Delta!$I$13*$D$88*$D$90 -> -2.6246694e+09 | M88: =SIMM_Delta!$J$13*$D$88*$D$91 -> 5.8995688e+08 | N88: =SIMM_Delta!$K$13*$D$88*$D$92 -> 0 | O88: =SIMM_Delta!$L$13*$D$88*$D$93 -> 0 | P88: =SIMM_Delta!$M$13*$D$88*$D$94 -> 0
A89: =Inputs!$H$14 -> 3y | B89: =SUMIFS(Sensitivities!$I$5:$I$100,Sensitivities!$B$5:$B$100,"Risk_IRCurve",Sensitivities!$C$5:$C$100,$B$73,Sensitivities!$E$5:$E$100,$A89) -> -93.055756 | C89: =INDEX(Parameters!$G$5:$G$689,MATCH(Inputs!$B$4&"|IR|"&"delta_rw"&"|"&$B$74&"|"&$A89,Parameters!$A$5:$A$689,0)) -> 66 | D89: =C89*B89*$B$78 -> -6141.6799 | E89: =SIMM_Delta!$B$14*$D$89*$D$83 -> 0 | F89: =SIMM_Delta!$C$14*$D$89*$D$84 -> 0 | G89: =SIMM_Delta!$D$14*$D$89*$D$85 -> 0 | H89: =SIMM_Delta!$E$14*$D$89*$D$86 -> 28877830 | I89: =SIMM_Delta!$F$14*$D$89*$D$87 -> -6.389373e+08 | J89: =SIMM_Delta!$G$14*$D$89*$D$88 -> 14853924 | K89: =SIMM_Delta!$H$14*$D$89*$D$89 -> 37720232 | L89: =SIMM_Delta!$I$14*$D$89*$D$90 -> -6.8165308e+09 | M89: =SIMM_Delta!$J$14*$D$89*$D$91 -> 1.5376876e+09 | N89: =SIMM_Delta!$K$14*$D$89*$D$92 -> 0 | O89: =SIMM_Delta!$L$14*$D$89*$D$93 -> 0 | P89: =SIMM_Delta!$M$14*$D$89*$D$94 -> 0
A90: =Inputs!$I$14 -> 5y | B90: =SUMIFS(Sensitivities!$I$5:$I$100,Sensitivities!$B$5:$B$100,"Risk_IRCurve",Sensitivities!$C$5:$C$100,$B$73,Sensitivities!$E$5:$E$100,$A90) -> 18757.487 | C90: =INDEX(Parameters!$G$5:$G$689,MATCH(Inputs!$B$4&"|IR|"&"delta_rw"&"|"&$B$74&"|"&$A90,Parameters!$A$5:$A$689,0)) -> 61 | D90: =C90*B90*$B$78 -> 1144206.7 | E90: =SIMM_Delta!$B$15*$D$90*$D$83 -> 0 | F90: =SIMM_Delta!$C$15*$D$90*$D$84 -> 0 | G90: =SIMM_Delta!$D$15*$D$90*$D$85 -> 0 | H90: =SIMM_Delta!$E$15*$D$90*$D$86 -> -4.8006109e+09 | I90: =SIMM_Delta!$F$15*$D$90*$D$87 -> 1.1082591e+11 | J90: =SIMM_Delta!$G$15*$D$90*$D$88 -> -2.6246694e+09 | K90: =SIMM_Delta!$H$15*$D$90*$D$89 -> -6.8165308e+09 | L90: =SIMM_Delta!$I$15*$D$90*$D$90 -> 1.309209e+12 | M90: =SIMM_Delta!$J$15*$D$90*$D$91 -> -3.0221447e+11 | N90: =SIMM_Delta!$K$15*$D$90*$D$92 -> 0 | O90: =SIMM_Delta!$L$15*$D$90*$D$93 -> 0 | P90: =SIMM_Delta!$M$15*$D$90*$D$94 -> 0
A91: =Inputs!$J$14 -> 10y | B91: =SUMIFS(Sensitivities!$I$5:$I$100,Sensitivities!$B$5:$B$100,"Risk_IRCurve",Sensitivities!$C$5:$C$100,$B$73,Sensitivities!$E$5:$E$100,$A91) -> -4585.5167 | C91: =INDEX(Parameters!$G$5:$G$689,MATCH(Inputs!$B$4&"|IR|"&"delta_rw"&"|"&$B$74&"|"&$A91,Parameters!$A$5:$A$689,0)) -> 60 | D91: =C91*B91*$B$78 -> -275131 | E91: =SIMM_Delta!$B$16*$D$91*$D$83 -> 0 | F91: =SIMM_Delta!$C$16*$D$91*$D$84 -> 0 | G91: =SIMM_Delta!$D$16*$D$91*$D$85 -> 0 | H91: =SIMM_Delta!$E$16*$D$91*$D$86 -> 1.0349203e+09 | I91: =SIMM_Delta!$F$16*$D$91*$D$87 -> -2.4016748e+10 | J91: =SIMM_Delta!$G$16*$D$91*$D$88 -> 5.8995688e+08 | K91: =SIMM_Delta!$H$16*$D$91*$D$89 -> 1.5376876e+09 | L91: =SIMM_Delta!$I$16*$D$91*$D$90 -> -3.0221447e+11 | M91: =SIMM_Delta!$J$16*$D$91*$D$91 -> 7.5697068e+10 | N91: =SIMM_Delta!$K$16*$D$91*$D$92 -> 0 | O91: =SIMM_Delta!$L$16*$D$91*$D$93 -> 0 | P91: =SIMM_Delta!$M$16*$D$91*$D$94 -> 0
A92: =Inputs!$K$14 -> 15y | B92: =SUMIFS(Sensitivities!$I$5:$I$100,Sensitivities!$B$5:$B$100,"Risk_IRCurve",Sensitivities!$C$5:$C$100,$B$73,Sensitivities!$E$5:$E$100,$A92) -> 0 | C92: =INDEX(Parameters!$G$5:$G$689,MATCH(Inputs!$B$4&"|IR|"&"delta_rw"&"|"&$B$74&"|"&$A92,Parameters!$A$5:$A$689,0)) -> 58 | D92: =C92*B92*$B$78 -> 0 | E92: =SIMM_Delta!$B$17*$D$92*$D$83 -> 0 | F92: =SIMM_Delta!$C$17*$D$92*$D$84 -> 0 | G92: =SIMM_Delta!$D$17*$D$92*$D$85 -> 0 | H92: =SIMM_Delta!$E$17*$D$92*$D$86 -> 0 | I92: =SIMM_Delta!$F$17*$D$92*$D$87 -> 0 | J92: =SIMM_Delta!$G$17*$D$92*$D$88 -> 0 | K92: =SIMM_Delta!$H$17*$D$92*$D$89 -> 0 | L92: =SIMM_Delta!$I$17*$D$92*$D$90 -> 0 | M92: =SIMM_Delta!$J$17*$D$92*$D$91 -> 0 | N92: =SIMM_Delta!$K$17*$D$92*$D$92 -> 0 | O92: =SIMM_Delta!$L$17*$D$92*$D$93 -> 0 | P92: =SIMM_Delta!$M$17*$D$92*$D$94 -> 0
A93: =Inputs!$L$14 -> 20y | B93: =SUMIFS(Sensitivities!$I$5:$I$100,Sensitivities!$B$5:$B$100,"Risk_IRCurve",Sensitivities!$C$5:$C$100,$B$73,Sensitivities!$E$5:$E$100,$A93) -> 0 | C93: =INDEX(Parameters!$G$5:$G$689,MATCH(Inputs!$B$4&"|IR|"&"delta_rw"&"|"&$B$74&"|"&$A93,Parameters!$A$5:$A$689,0)) -> 58 | D93: =C93*B93*$B$78 -> 0 | E93: =SIMM_Delta!$B$18*$D$93*$D$83 -> 0 | F93: =SIMM_Delta!$C$18*$D$93*$D$84 -> 0 | G93: =SIMM_Delta!$D$18*$D$93*$D$85 -> 0 | H93: =SIMM_Delta!$E$18*$D$93*$D$86 -> 0 | I93: =SIMM_Delta!$F$18*$D$93*$D$87 -> 0 | J93: =SIMM_Delta!$G$18*$D$93*$D$88 -> 0 | K93: =SIMM_Delta!$H$18*$D$93*$D$89 -> 0 | L93: =SIMM_Delta!$I$18*$D$93*$D$90 -> 0 | M93: =SIMM_Delta!$J$18*$D$93*$D$91 -> 0 | N93: =SIMM_Delta!$K$18*$D$93*$D$92 -> 0 | O93: =SIMM_Delta!$L$18*$D$93*$D$93 -> 0 | P93: =SIMM_Delta!$M$18*$D$93*$D$94 -> 0
A94: =Inputs!$M$14 -> 30y | B94: =SUMIFS(Sensitivities!$I$5:$I$100,Sensitivities!$B$5:$B$100,"Risk_IRCurve",Sensitivities!$C$5:$C$100,$B$73,Sensitivities!$E$5:$E$100,$A94) -> 0 | C94: =INDEX(Parameters!$G$5:$G$689,MATCH(Inputs!$B$4&"|IR|"&"delta_rw"&"|"&$B$74&"|"&$A94,Parameters!$A$5:$A$689,0)) -> 66 | D94: =C94*B94*$B$78 -> 0 | E94: =SIMM_Delta!$B$19*$D$94*$D$83 -> 0 | F94: =SIMM_Delta!$C$19*$D$94*$D$84 -> 0 | G94: =SIMM_Delta!$D$19*$D$94*$D$85 -> 0 | H94: =SIMM_Delta!$E$19*$D$94*$D$86 -> 0 | I94: =SIMM_Delta!$F$19*$D$94*$D$87 -> 0 | J94: =SIMM_Delta!$G$19*$D$94*$D$88 -> 0 | K94: =SIMM_Delta!$H$19*$D$94*$D$89 -> 0 | L94: =SIMM_Delta!$I$19*$D$94*$D$90 -> 0 | M94: =SIMM_Delta!$J$19*$D$94*$D$91 -> 0 | N94: =SIMM_Delta!$K$19*$D$94*$D$92 -> 0 | O94: =SIMM_Delta!$L$19*$D$94*$D$93 -> 0 | P94: =SIMM_Delta!$M$19*$D$94*$D$94 -> 0
A98: Currency | B98: =Inputs!$E$13 -> JPY
A99: RW group | B99: =IF(ISNUMBER(MATCH(Inputs!$B$4&"|IR|rw_group_member|regular|"&$B$98,Parameters!$A$5:$A$689,0)),"regular",IF(ISNUMBER(MATCH(Inputs!$B$4&"|IR|rw_group_member|low|"&$B$98,Parameters!$A$5:$A$689,0)),"low","high")) -> low
A100: Concentration group | B100: =IF(ISNUMBER(MATCH(Inputs!$B$4&"|IR|ct_group_member|regular_well_traded|"&$B$98,Parameters!$A$5:$A$689,0)),"regular_well_traded",IF(ISNUMBER(MATCH(Inputs!$B$4&"|IR|ct_group_member|regular_less_well_traded|"&$B$98,Parameters!$A$5:$A$689,0)),"regular_less_well_traded",IF(ISNUMBER(MATCH(Inputs!$B$4&"|IR|ct_group_member|low|"&$B$98,Parameters!$A$5:$A$689,0)),"low","high"))) -> low
A101: Concentration threshold (USD mm per bp) | B101: =INDEX(Parameters!$G$5:$G$689,MATCH(Inputs!$B$4&"|IR|"&"delta_ct"&"|"&$B$100&"|"&"",Parameters!$A$5:$A$689,0)) -> 370
A102: Sum of net sensitivities | B102: =SUM(B108:B119) -> -23938.412
A103: CR | B103: =MAX(1,SQRT(ABS($B$102)/Inputs!$B$9/$B$101)) -> 1
A104: K | B104: =SQRT(MAX(0,SUM(E108:P119))) -> 708220.89
A105: Sum of WS | B105: =SUM(D108:D119) -> -703893.54
A106: S | B106: =MAX(-$B$104,MIN($B$104,$B$105)) -> -703893.54
A107: Tenor | B107: Net sensitivity | C107: RW | D107: WS | E107: =Inputs!$B$14 -> 2w | F107: =Inputs!$C$14 -> 1m | G107: =Inputs!$D$14 -> 3m | H107: =Inputs!$E$14 -> 6m | I107: =Inputs!$F$14 -> 1y | J107: =Inputs!$G$14 -> 2y | K107: =Inputs!$H$14 -> 3y | L107: =Inputs!$I$14 -> 5y | M107: =Inputs!$J$14 -> 10y | N107: =Inputs!$K$14 -> 15y | O107: =Inputs!$L$14 -> 20y | P107: =Inputs!$M$14 -> 30y
A108: =Inputs!$B$14 -> 2w | B108: =SUMIFS(Sensitivities!$I$5:$I$100,Sensitivities!$B$5:$B$100,"Risk_IRCurve",Sensitivities!$C$5:$C$100,$B$98,Sensitivities!$E$5:$E$100,$A108) -> 0 | C108: =INDEX(Parameters!$G$5:$G$689,MATCH(Inputs!$B$4&"|IR|"&"delta_rw"&"|"&$B$99&"|"&$A108,Parameters!$A$5:$A$689,0)) -> 15 | D108: =C108*B108*$B$103 -> 0 | E108: =SIMM_Delta!$B$8*$D$108*$D$108 -> 0 | F108: =SIMM_Delta!$C$8*$D$108*$D$109 -> 0 | G108: =SIMM_Delta!$D$8*$D$108*$D$110 -> 0 | H108: =SIMM_Delta!$E$8*$D$108*$D$111 -> 0 | I108: =SIMM_Delta!$F$8*$D$108*$D$112 -> 0 | J108: =SIMM_Delta!$G$8*$D$108*$D$113 -> 0 | K108: =SIMM_Delta!$H$8*$D$108*$D$114 -> 0 | L108: =SIMM_Delta!$I$8*$D$108*$D$115 -> 0 | M108: =SIMM_Delta!$J$8*$D$108*$D$116 -> 0 | N108: =SIMM_Delta!$K$8*$D$108*$D$117 -> 0 | O108: =SIMM_Delta!$L$8*$D$108*$D$118 -> 0 | P108: =SIMM_Delta!$M$8*$D$108*$D$119 -> 0
A109: =Inputs!$C$14 -> 1m | B109: =SUMIFS(Sensitivities!$I$5:$I$100,Sensitivities!$B$5:$B$100,"Risk_IRCurve",Sensitivities!$C$5:$C$100,$B$98,Sensitivities!$E$5:$E$100,$A109) -> 0 | C109: =INDEX(Parameters!$G$5:$G$689,MATCH(Inputs!$B$4&"|IR|"&"delta_rw"&"|"&$B$99&"|"&$A109,Parameters!$A$5:$A$689,0)) -> 18 | D109: =C109*B109*$B$103 -> 0 | E109: =SIMM_Delta!$B$9*$D$109*$D$108 -> 0 | F109: =SIMM_Delta!$C$9*$D$109*$D$109 -> 0 | G109: =SIMM_Delta!$D$9*$D$109*$D$110 -> 0 | H109: =SIMM_Delta!$E$9*$D$109*$D$111 -> 0 | I109: =SIMM_Delta!$F$9*$D$109*$D$112 -> 0 | J109: =SIMM_Delta!$G$9*$D$109*$D$113 -> 0 | K109: =SIMM_Delta!$H$9*$D$109*$D$114 -> 0 | L109: =SIMM_Delta!$I$9*$D$109*$D$115 -> 0 | M109: =SIMM_Delta!$J$9*$D$109*$D$116 -> 0 | N109: =SIMM_Delta!$K$9*$D$109*$D$117 -> 0 | O109: =SIMM_Delta!$L$9*$D$109*$D$118 -> 0 | P109: =SIMM_Delta!$M$9*$D$109*$D$119 -> 0
A110: =Inputs!$D$14 -> 3m | B110: =SUMIFS(Sensitivities!$I$5:$I$100,Sensitivities!$B$5:$B$100,"Risk_IRCurve",Sensitivities!$C$5:$C$100,$B$98,Sensitivities!$E$5:$E$100,$A110) -> 500.03033 | C110: =INDEX(Parameters!$G$5:$G$689,MATCH(Inputs!$B$4&"|IR|"&"delta_rw"&"|"&$B$99&"|"&$A110,Parameters!$A$5:$A$689,0)) -> 12 | D110: =C110*B110*$B$103 -> 6000.3639 | E110: =SIMM_Delta!$B$10*$D$110*$D$108 -> 0 | F110: =SIMM_Delta!$C$10*$D$110*$D$109 -> 0 | G110: =SIMM_Delta!$D$10*$D$110*$D$110 -> 36004367 | H110: =SIMM_Delta!$E$10*$D$110*$D$111 -> 0 | I110: =SIMM_Delta!$F$10*$D$110*$D$112 -> 498968.68 | J110: =SIMM_Delta!$G$10*$D$110*$D$113 -> 1076887.4 | K110: =SIMM_Delta!$H$10*$D$110*$D$114 -> 2575055.9 | L110: =SIMM_Delta!$I$10*$D$110*$D$115 -> 10413875 | M110: =SIMM_Delta!$J$10*$D$110*$D$116 -> -1.4599632e+09 | N110: =SIMM_Delta!$K$10*$D$110*$D$117 -> 0 | O110: =SIMM_Delta!$L$10*$D$110*$D$118 -> 0 | P110: =SIMM_Delta!$M$10*$D$110*$D$119 -> 0
A111: =Inputs!$E$14 -> 6m | B111: =SUMIFS(Sensitivities!$I$5:$I$100,Sensitivities!$B$5:$B$100,"Risk_IRCurve",Sensitivities!$C$5:$C$100,$B$98,Sensitivities!$E$5:$E$100,$A111) -> 0 | C111: =INDEX(Parameters!$G$5:$G$689,MATCH(Inputs!$B$4&"|IR|"&"delta_rw"&"|"&$B$99&"|"&$A111,Parameters!$A$5:$A$689,0)) -> 11 | D111: =C111*B111*$B$103 -> 0 | E111: =SIMM_Delta!$B$11*$D$111*$D$108 -> 0 | F111: =SIMM_Delta!$C$11*$D$111*$D$109 -> 0 | G111: =SIMM_Delta!$D$11*$D$111*$D$110 -> 0 | H111: =SIMM_Delta!$E$11*$D$111*$D$111 -> 0 | I111: =SIMM_Delta!$F$11*$D$111*$D$112 -> 0 | J111: =SIMM_Delta!$G$11*$D$111*$D$113 -> 0 | K111: =SIMM_Delta!$H$11*$D$111*$D$114 -> 0 | L111: =SIMM_Delta!$I$11*$D$111*$D$115 -> 0 | M111: =SIMM_Delta!$J$11*$D$111*$D$116 -> 0 | N111: =SIMM_Delta!$K$11*$D$111*$D$117 -> 0 | O111: =SIMM_Delta!$L$11*$D$111*$D$118 -> 0 | P111: =SIMM_Delta!$M$11*$D$111*$D$119 -> 0
A112: =Inputs!$F$14 -> 1y | B112: =SUMIFS(Sensitivities!$I$5:$I$100,Sensitivities!$B$5:$B$100,"Risk_IRCurve",Sensitivities!$C$5:$C$100,$B$98,Sensitivities!$E$5:$E$100,$A112) -> 8.0344351 | C112: =INDEX(Parameters!$G$5:$G$689,MATCH(Inputs!$B$4&"|IR|"&"delta_rw"&"|"&$B$99&"|"&$A112,Parameters!$A$5:$A$689,0)) -> 15 | D112: =C112*B112*$B$103 -> 120.51653 | E112: =SIMM_Delta!$B$12*$D$112*$D$108 -> 0 | F112: =SIMM_Delta!$C$12*$D$112*$D$109 -> 0 | G112: =SIMM_Delta!$D$12*$D$112*$D$110 -> 498968.68 | H112: =SIMM_Delta!$E$12*$D$112*$D$111 -> 0 | I112: =SIMM_Delta!$F$12*$D$112*$D$112 -> 14524.233 | J112: =SIMM_Delta!$G$12*$D$112*$D$113 -> 38361.121 | K112: =SIMM_Delta!$H$12*$D$112*$D$114 -> 97817.623 | L112: =SIMM_Delta!$I$12*$D$112*$D$115 -> 423551.68 | M112: =SIMM_Delta!$J$12*$D$112*$D$116 -> -62958571 | N112: =SIMM_Delta!$K$12*$D$112*$D$117 -> 0 | O112: =SIMM_Delta!$L$12*$D$112*$D$118 -> 0 | P112: =SIMM_Delta!$M$12*$D$112*$D$119 -> 0
A113: =Inputs!$G$14 -> 2y | B113: =SUMIFS(Sensitivities!$I$5:$I$100,Sensitivities!$B$5:$B$100,"Risk_IRCurve",Sensitivities!$C$5:$C$100,$B$98,Sensitivities!$E$5:$E$100,$A113) -> 16.124919 | C113: =INDEX(Parameters!$G$5:$G$689,MATCH(Inputs!$B$4&"|IR|"&"delta_rw"&"|"&$B$99&"|"&$A113,Parameters!$A$5:$A$689,0)) -> 21 | D113: =C113*B113*$B$103 -> 338.62329 | E113: =SIMM_Delta!$B$13*$D$113*$D$108 -> 0 | F113: =SIMM_Delta!$C$13*$D$113*$D$109 -> 0 | G113: =SIMM_Delta!$D$13*$D$113*$D$110 -> 1076887.4 | H113: =SIMM_Delta!$E$13*$D$113*$D$111 -> 0 | I113: =SIMM_Delta!$F$13*$D$113*$D$112 -> 38361.121 | J113: =SIMM_Delta!$G$13*$D$113*$D$113 -> 114665.73 | K113: =SIMM_Delta!$H$13*$D$113*$D$114 -> 306436.01 | L113: =SIMM_Delta!$I$13*$D$113*$D$115 -> 1351697.3 | M113: =SIMM_Delta!$J$13*$D$113*$D$116 -> -2.0840142e+08 | N113: =SIMM_Delta!$K$13*$D$113*$D$117 -> 0 | O113: =SIMM_Delta!$L$13*$D$113*$D$118 -> 0 | P113: =SIMM_Delta!$M$13*$D$113*$D$119 -> 0
A114: =Inputs!$H$14 -> 3y | B114: =SUMIFS(Sensitivities!$I$5:$I$100,Sensitivities!$B$5:$B$100,"Risk_IRCurve",Sensitivities!$C$5:$C$100,$B$98,Sensitivities!$E$5:$E$100,$A114) -> 40.562378 | C114: =INDEX(Parameters!$G$5:$G$689,MATCH(Inputs!$B$4&"|IR|"&"delta_rw"&"|"&$B$99&"|"&$A114,Parameters!$A$5:$A$689,0)) -> 23 | D114: =C114*B114*$B$103 -> 932.9347 | E114: =SIMM_Delta!$B$14*$D$114*$D$108 -> 0 | F114: =SIMM_Delta!$C$14*$D$114*$D$109 -> 0 | G114: =SIMM_Delta!$D$14*$D$114*$D$110 -> 2575055.9 | H114: =SIMM_Delta!$E$14*$D$114*$D$111 -> 0 | I114: =SIMM_Delta!$F$14*$D$114*$D$112 -> 97817.623 | J114: =SIMM_Delta!$G$14*$D$114*$D$113 -> 306436.01 | K114: =SIMM_Delta!$H$14*$D$114*$D$114 -> 870367.15 | L114: =SIMM_Delta!$I$14*$D$114*$D$115 -> 3926429.2 | M114: =SIMM_Delta!$J$14*$D$114*$D$116 -> -6.0754442e+08 | N114: =SIMM_Delta!$K$14*$D$114*$D$117 -> 0 | O114: =SIMM_Delta!$L$14*$D$114*$D$118 -> 0 | P114: =SIMM_Delta!$M$14*$D$114*$D$119 -> 0
A115: =Inputs!$I$14 -> 5y | B115: =SUMIFS(Sensitivities!$I$5:$I$100,Sensitivities!$B$5:$B$100,"Risk_IRCurve",Sensitivities!$C$5:$C$100,$B$98,Sensitivities!$E$5:$E$100,$A115) -> 173.55406 | C115: =INDEX(Parameters!$G$5:$G$689,MATCH(Inputs!$B$4&"|IR|"&"delta_rw"&"|"&$B$99&"|"&$A115,Parameters!$A$5:$A$689,0)) -> 25 | D115: =C115*B115*$B$103 -> 4338.8515 | E115: =SIMM_Delta!$B$15*$D$115*$D$108 -> 0 | F115: =SIMM_Delta!$C$15*$D$115*$D$109 -> 0 | G115: =SIMM_Delta!$D$15*$D$115*$D$110 -> 10413875 | H115: =SIMM_Delta!$E$15*$D$115*$D$111 -> 0 | I115: =SIMM_Delta!$F$15*$D$115*$D$112 -> 423551.68 | J115: =SIMM_Delta!$G$15*$D$115*$D$113 -> 1351697.3 | K115: =SIMM_Delta!$H$15*$D$115*$D$114 -> 3926429.2 | L115: =SIMM_Delta!$I$15*$D$115*$D$115 -> 18825632 | M115: =SIMM_Delta!$J$15*$D$115*$D$116 -> -2.9807903e+09 | N115: =SIMM_Delta!$K$15*$D$115*$D$117 -> 0 | O115: =SIMM_Delta!$L$15*$D$115*$D$118 -> 0 | P115: =SIMM_Delta!$M$15*$D$115*$D$119 -> 0
...

Sheet SIMM_Vega
A1: IR vega and FX vega (formulas). IR vega uses the delta tenor correlation with f = 1; FX vega uses sigma_SIMM from RW.
A3: IR vega risk weight | B3: =INDEX(Parameters!$G$5:$G$689,MATCH(Inputs!$B$4&"|IR|"&"vega_rw"&"|"&""&"|"&"",Parameters!$A$5:$A$689,0)) -> 0.2
A4: IR gamma | B4: =INDEX(Parameters!$G$5:$G$689,MATCH(Inputs!$B$4&"|IR|"&"gamma"&"|"&""&"|"&"",Parameters!$A$5:$A$689,0)) -> 0.35
A8: Currency | B8: =Inputs!$B$13 -> USD
A9: Concentration group | B9: =IF(ISNUMBER(MATCH(Inputs!$B$4&"|IR|ct_group_member|regular_well_traded|"&$B$8,Parameters!$A$5:$A$689,0)),"regular_well_traded",IF(ISNUMBER(MATCH(Inputs!$B$4&"|IR|ct_group_member|regular_less_well_traded|"&$B$8,Parameters!$A$5:$A$689,0)),"regular_less_well_traded",IF(ISNUMBER(MATCH(Inputs!$B$4&"|IR|ct_group_member|low|"&$B$8,Parameters!$A$5:$A$689,0)),"low","high"))) -> regular_well_traded
A10: Vega threshold (USD mm) | B10: =INDEX(Parameters!$G$5:$G$689,MATCH(Inputs!$B$4&"|IR|"&"vega_ct"&"|"&$B$9&"|"&"",Parameters!$A$5:$A$689,0)) -> 3800
A11: Sum of net vega*vol | B11: =SUM(B17:B28) -> 638647.77
A12: VCR | B12: =MAX(1,SQRT(ABS($B$11)/Inputs!$B$9/$B$10)) -> 1
A13: K | B13: =SQRT(MAX(0,SUM(D17:O28))) -> 127729.55
A14: Sum of VR | B14: =SUM(C17:C28) -> 127729.55
A15: S | B15: =MAX(-$B$13,MIN($B$13,$B$14)) -> 127729.55
A16: Tenor | B16: Net vega*vol (USD) | C16: VR | D16: =Inputs!$B$14 -> 2w | E16: =Inputs!$C$14 -> 1m | F16: =Inputs!$D$14 -> 3m | G16: =Inputs!$E$14 -> 6m | H16: =Inputs!$F$14 -> 1y | I16: =Inputs!$G$14 -> 2y | J16: =Inputs!$H$14 -> 3y | K16: =Inputs!$I$14 -> 5y | L16: =Inputs!$J$14 -> 10y | M16: =Inputs!$K$14 -> 15y | N16: =Inputs!$L$14 -> 20y | O16: =Inputs!$M$14 -> 30y
A17: =Inputs!$B$14 -> 2w | B17: =SUMIFS(Sensitivities!$I$5:$I$100,Sensitivities!$B$5:$B$100,"Risk_IRVol",Sensitivities!$C$5:$C$100,$B$8,Sensitivities!$E$5:$E$100,$A17) -> 0 | C17: =$B$3*B17*$B$12 -> 0 | D17: =SIMM_Delta!$B$8*$C$17*$C$17 -> 0 | E17: =SIMM_Delta!$C$8*$C$17*$C$18 -> 0 | F17: =SIMM_Delta!$D$8*$C$17*$C$19 -> 0 | G17: =SIMM_Delta!$E$8*$C$17*$C$20 -> 0 | H17: =SIMM_Delta!$F$8*$C$17*$C$21 -> 0 | I17: =SIMM_Delta!$G$8*$C$17*$C$22 -> 0 | J17: =SIMM_Delta!$H$8*$C$17*$C$23 -> 0 | K17: =SIMM_Delta!$I$8*$C$17*$C$24 -> 0 | L17: =SIMM_Delta!$J$8*$C$17*$C$25 -> 0 | M17: =SIMM_Delta!$K$8*$C$17*$C$26 -> 0 | N17: =SIMM_Delta!$L$8*$C$17*$C$27 -> 0 | O17: =SIMM_Delta!$M$8*$C$17*$C$28 -> 0
A18: =Inputs!$C$14 -> 1m | B18: =SUMIFS(Sensitivities!$I$5:$I$100,Sensitivities!$B$5:$B$100,"Risk_IRVol",Sensitivities!$C$5:$C$100,$B$8,Sensitivities!$E$5:$E$100,$A18) -> 0 | C18: =$B$3*B18*$B$12 -> 0 | D18: =SIMM_Delta!$B$9*$C$18*$C$17 -> 0 | E18: =SIMM_Delta!$C$9*$C$18*$C$18 -> 0 | F18: =SIMM_Delta!$D$9*$C$18*$C$19 -> 0 | G18: =SIMM_Delta!$E$9*$C$18*$C$20 -> 0 | H18: =SIMM_Delta!$F$9*$C$18*$C$21 -> 0 | I18: =SIMM_Delta!$G$9*$C$18*$C$22 -> 0 | J18: =SIMM_Delta!$H$9*$C$18*$C$23 -> 0 | K18: =SIMM_Delta!$I$9*$C$18*$C$24 -> 0 | L18: =SIMM_Delta!$J$9*$C$18*$C$25 -> 0 | M18: =SIMM_Delta!$K$9*$C$18*$C$26 -> 0 | N18: =SIMM_Delta!$L$9*$C$18*$C$27 -> 0 | O18: =SIMM_Delta!$M$9*$C$18*$C$28 -> 0
A19: =Inputs!$D$14 -> 3m | B19: =SUMIFS(Sensitivities!$I$5:$I$100,Sensitivities!$B$5:$B$100,"Risk_IRVol",Sensitivities!$C$5:$C$100,$B$8,Sensitivities!$E$5:$E$100,$A19) -> 0 | C19: =$B$3*B19*$B$12 -> 0 | D19: =SIMM_Delta!$B$10*$C$19*$C$17 -> 0 | E19: =SIMM_Delta!$C$10*$C$19*$C$18 -> 0 | F19: =SIMM_Delta!$D$10*$C$19*$C$19 -> 0 | G19: =SIMM_Delta!$E$10*$C$19*$C$20 -> 0 | H19: =SIMM_Delta!$F$10*$C$19*$C$21 -> 0 | I19: =SIMM_Delta!$G$10*$C$19*$C$22 -> 0 | J19: =SIMM_Delta!$H$10*$C$19*$C$23 -> 0 | K19: =SIMM_Delta!$I$10*$C$19*$C$24 -> 0 | L19: =SIMM_Delta!$J$10*$C$19*$C$25 -> 0 | M19: =SIMM_Delta!$K$10*$C$19*$C$26 -> 0 | N19: =SIMM_Delta!$L$10*$C$19*$C$27 -> 0 | O19: =SIMM_Delta!$M$10*$C$19*$C$28 -> 0
A20: =Inputs!$E$14 -> 6m | B20: =SUMIFS(Sensitivities!$I$5:$I$100,Sensitivities!$B$5:$B$100,"Risk_IRVol",Sensitivities!$C$5:$C$100,$B$8,Sensitivities!$E$5:$E$100,$A20) -> 0 | C20: =$B$3*B20*$B$12 -> 0 | D20: =SIMM_Delta!$B$11*$C$20*$C$17 -> 0 | E20: =SIMM_Delta!$C$11*$C$20*$C$18 -> 0 | F20: =SIMM_Delta!$D$11*$C$20*$C$19 -> 0 | G20: =SIMM_Delta!$E$11*$C$20*$C$20 -> 0 | H20: =SIMM_Delta!$F$11*$C$20*$C$21 -> 0 | I20: =SIMM_Delta!$G$11*$C$20*$C$22 -> 0 | J20: =SIMM_Delta!$H$11*$C$20*$C$23 -> 0 | K20: =SIMM_Delta!$I$11*$C$20*$C$24 -> 0 | L20: =SIMM_Delta!$J$11*$C$20*$C$25 -> 0 | M20: =SIMM_Delta!$K$11*$C$20*$C$26 -> 0 | N20: =SIMM_Delta!$L$11*$C$20*$C$27 -> 0 | O20: =SIMM_Delta!$M$11*$C$20*$C$28 -> 0
A21: =Inputs!$F$14 -> 1y | B21: =SUMIFS(Sensitivities!$I$5:$I$100,Sensitivities!$B$5:$B$100,"Risk_IRVol",Sensitivities!$C$5:$C$100,$B$8,Sensitivities!$E$5:$E$100,$A21) -> 638647.77 | C21: =$B$3*B21*$B$12 -> 127729.55 | D21: =SIMM_Delta!$B$12*$C$21*$C$17 -> 0 | E21: =SIMM_Delta!$C$12*$C$21*$C$18 -> 0 | F21: =SIMM_Delta!$D$12*$C$21*$C$19 -> 0 | G21: =SIMM_Delta!$E$12*$C$21*$C$20 -> 0 | H21: =SIMM_Delta!$F$12*$C$21*$C$21 -> 1.6314839e+10 | I21: =SIMM_Delta!$G$12*$C$21*$C$22 -> 0 | J21: =SIMM_Delta!$H$12*$C$21*$C$23 -> 0 | K21: =SIMM_Delta!$I$12*$C$21*$C$24 -> 0 | L21: =SIMM_Delta!$J$12*$C$21*$C$25 -> 0 | M21: =SIMM_Delta!$K$12*$C$21*$C$26 -> 0 | N21: =SIMM_Delta!$L$12*$C$21*$C$27 -> 0 | O21: =SIMM_Delta!$M$12*$C$21*$C$28 -> 0
A22: =Inputs!$G$14 -> 2y | B22: =SUMIFS(Sensitivities!$I$5:$I$100,Sensitivities!$B$5:$B$100,"Risk_IRVol",Sensitivities!$C$5:$C$100,$B$8,Sensitivities!$E$5:$E$100,$A22) -> 0 | C22: =$B$3*B22*$B$12 -> 0 | D22: =SIMM_Delta!$B$13*$C$22*$C$17 -> 0 | E22: =SIMM_Delta!$C$13*$C$22*$C$18 -> 0 | F22: =SIMM_Delta!$D$13*$C$22*$C$19 -> 0 | G22: =SIMM_Delta!$E$13*$C$22*$C$20 -> 0 | H22: =SIMM_Delta!$F$13*$C$22*$C$21 -> 0 | I22: =SIMM_Delta!$G$13*$C$22*$C$22 -> 0 | J22: =SIMM_Delta!$H$13*$C$22*$C$23 -> 0 | K22: =SIMM_Delta!$I$13*$C$22*$C$24 -> 0 | L22: =SIMM_Delta!$J$13*$C$22*$C$25 -> 0 | M22: =SIMM_Delta!$K$13*$C$22*$C$26 -> 0 | N22: =SIMM_Delta!$L$13*$C$22*$C$27 -> 0 | O22: =SIMM_Delta!$M$13*$C$22*$C$28 -> 0
A23: =Inputs!$H$14 -> 3y | B23: =SUMIFS(Sensitivities!$I$5:$I$100,Sensitivities!$B$5:$B$100,"Risk_IRVol",Sensitivities!$C$5:$C$100,$B$8,Sensitivities!$E$5:$E$100,$A23) -> 0 | C23: =$B$3*B23*$B$12 -> 0 | D23: =SIMM_Delta!$B$14*$C$23*$C$17 -> 0 | E23: =SIMM_Delta!$C$14*$C$23*$C$18 -> 0 | F23: =SIMM_Delta!$D$14*$C$23*$C$19 -> 0 | G23: =SIMM_Delta!$E$14*$C$23*$C$20 -> 0 | H23: =SIMM_Delta!$F$14*$C$23*$C$21 -> 0 | I23: =SIMM_Delta!$G$14*$C$23*$C$22 -> 0 | J23: =SIMM_Delta!$H$14*$C$23*$C$23 -> 0 | K23: =SIMM_Delta!$I$14*$C$23*$C$24 -> 0 | L23: =SIMM_Delta!$J$14*$C$23*$C$25 -> 0 | M23: =SIMM_Delta!$K$14*$C$23*$C$26 -> 0 | N23: =SIMM_Delta!$L$14*$C$23*$C$27 -> 0 | O23: =SIMM_Delta!$M$14*$C$23*$C$28 -> 0
A24: =Inputs!$I$14 -> 5y | B24: =SUMIFS(Sensitivities!$I$5:$I$100,Sensitivities!$B$5:$B$100,"Risk_IRVol",Sensitivities!$C$5:$C$100,$B$8,Sensitivities!$E$5:$E$100,$A24) -> 0 | C24: =$B$3*B24*$B$12 -> 0 | D24: =SIMM_Delta!$B$15*$C$24*$C$17 -> 0 | E24: =SIMM_Delta!$C$15*$C$24*$C$18 -> 0 | F24: =SIMM_Delta!$D$15*$C$24*$C$19 -> 0 | G24: =SIMM_Delta!$E$15*$C$24*$C$20 -> 0 | H24: =SIMM_Delta!$F$15*$C$24*$C$21 -> 0 | I24: =SIMM_Delta!$G$15*$C$24*$C$22 -> 0 | J24: =SIMM_Delta!$H$15*$C$24*$C$23 -> 0 | K24: =SIMM_Delta!$I$15*$C$24*$C$24 -> 0 | L24: =SIMM_Delta!$J$15*$C$24*$C$25 -> 0 | M24: =SIMM_Delta!$K$15*$C$24*$C$26 -> 0 | N24: =SIMM_Delta!$L$15*$C$24*$C$27 -> 0 | O24: =SIMM_Delta!$M$15*$C$24*$C$28 -> 0
A25: =Inputs!$J$14 -> 10y | B25: =SUMIFS(Sensitivities!$I$5:$I$100,Sensitivities!$B$5:$B$100,"Risk_IRVol",Sensitivities!$C$5:$C$100,$B$8,Sensitivities!$E$5:$E$100,$A25) -> 0 | C25: =$B$3*B25*$B$12 -> 0 | D25: =SIMM_Delta!$B$16*$C$25*$C$17 -> 0 | E25: =SIMM_Delta!$C$16*$C$25*$C$18 -> 0 | F25: =SIMM_Delta!$D$16*$C$25*$C$19 -> 0 | G25: =SIMM_Delta!$E$16*$C$25*$C$20 -> 0 | H25: =SIMM_Delta!$F$16*$C$25*$C$21 -> 0 | I25: =SIMM_Delta!$G$16*$C$25*$C$22 -> 0 | J25: =SIMM_Delta!$H$16*$C$25*$C$23 -> 0 | K25: =SIMM_Delta!$I$16*$C$25*$C$24 -> 0 | L25: =SIMM_Delta!$J$16*$C$25*$C$25 -> 0 | M25: =SIMM_Delta!$K$16*$C$25*$C$26 -> 0 | N25: =SIMM_Delta!$L$16*$C$25*$C$27 -> 0 | O25: =SIMM_Delta!$M$16*$C$25*$C$28 -> 0
A26: =Inputs!$K$14 -> 15y | B26: =SUMIFS(Sensitivities!$I$5:$I$100,Sensitivities!$B$5:$B$100,"Risk_IRVol",Sensitivities!$C$5:$C$100,$B$8,Sensitivities!$E$5:$E$100,$A26) -> 0 | C26: =$B$3*B26*$B$12 -> 0 | D26: =SIMM_Delta!$B$17*$C$26*$C$17 -> 0 | E26: =SIMM_Delta!$C$17*$C$26*$C$18 -> 0 | F26: =SIMM_Delta!$D$17*$C$26*$C$19 -> 0 | G26: =SIMM_Delta!$E$17*$C$26*$C$20 -> 0 | H26: =SIMM_Delta!$F$17*$C$26*$C$21 -> 0 | I26: =SIMM_Delta!$G$17*$C$26*$C$22 -> 0 | J26: =SIMM_Delta!$H$17*$C$26*$C$23 -> 0 | K26: =SIMM_Delta!$I$17*$C$26*$C$24 -> 0 | L26: =SIMM_Delta!$J$17*$C$26*$C$25 -> 0 | M26: =SIMM_Delta!$K$17*$C$26*$C$26 -> 0 | N26: =SIMM_Delta!$L$17*$C$26*$C$27 -> 0 | O26: =SIMM_Delta!$M$17*$C$26*$C$28 -> 0
A27: =Inputs!$L$14 -> 20y | B27: =SUMIFS(Sensitivities!$I$5:$I$100,Sensitivities!$B$5:$B$100,"Risk_IRVol",Sensitivities!$C$5:$C$100,$B$8,Sensitivities!$E$5:$E$100,$A27) -> 0 | C27: =$B$3*B27*$B$12 -> 0 | D27: =SIMM_Delta!$B$18*$C$27*$C$17 -> 0 | E27: =SIMM_Delta!$C$18*$C$27*$C$18 -> 0 | F27: =SIMM_Delta!$D$18*$C$27*$C$19 -> 0 | G27: =SIMM_Delta!$E$18*$C$27*$C$20 -> 0 | H27: =SIMM_Delta!$F$18*$C$27*$C$21 -> 0 | I27: =SIMM_Delta!$G$18*$C$27*$C$22 -> 0 | J27: =SIMM_Delta!$H$18*$C$27*$C$23 -> 0 | K27: =SIMM_Delta!$I$18*$C$27*$C$24 -> 0 | L27: =SIMM_Delta!$J$18*$C$27*$C$25 -> 0 | M27: =SIMM_Delta!$K$18*$C$27*$C$26 -> 0 | N27: =SIMM_Delta!$L$18*$C$27*$C$27 -> 0 | O27: =SIMM_Delta!$M$18*$C$27*$C$28 -> 0
A28: =Inputs!$M$14 -> 30y | B28: =SUMIFS(Sensitivities!$I$5:$I$100,Sensitivities!$B$5:$B$100,"Risk_IRVol",Sensitivities!$C$5:$C$100,$B$8,Sensitivities!$E$5:$E$100,$A28) -> 0 | C28: =$B$3*B28*$B$12 -> 0 | D28: =SIMM_Delta!$B$19*$C$28*$C$17 -> 0 | E28: =SIMM_Delta!$C$19*$C$28*$C$18 -> 0 | F28: =SIMM_Delta!$D$19*$C$28*$C$19 -> 0 | G28: =SIMM_Delta!$E$19*$C$28*$C$20 -> 0 | H28: =SIMM_Delta!$F$19*$C$28*$C$21 -> 0 | I28: =SIMM_Delta!$G$19*$C$28*$C$22 -> 0 | J28: =SIMM_Delta!$H$19*$C$28*$C$23 -> 0 | K28: =SIMM_Delta!$I$19*$C$28*$C$24 -> 0 | L28: =SIMM_Delta!$J$19*$C$28*$C$25 -> 0 | M28: =SIMM_Delta!$K$19*$C$28*$C$26 -> 0 | N28: =SIMM_Delta!$L$19*$C$28*$C$27 -> 0 | O28: =SIMM_Delta!$M$19*$C$28*$C$28 -> 0
A32: Currency | B32: =Inputs!$C$13 -> EUR
A33: Concentration group | B33: =IF(ISNUMBER(MATCH(Inputs!$B$4&"|IR|ct_group_member|regular_well_traded|"&$B$32,Parameters!$A$5:$A$689,0)),"regular_well_traded",IF(ISNUMBER(MATCH(Inputs!$B$4&"|IR|ct_group_member|regular_less_well_traded|"&$B$32,Parameters!$A$5:$A$689,0)),"regular_less_well_traded",IF(ISNUMBER(MATCH(Inputs!$B$4&"|IR|ct_group_member|low|"&$B$32,Parameters!$A$5:$A$689,0)),"low","high"))) -> regular_well_traded
A34: Vega threshold (USD mm) | B34: =INDEX(Parameters!$G$5:$G$689,MATCH(Inputs!$B$4&"|IR|"&"vega_ct"&"|"&$B$33&"|"&"",Parameters!$A$5:$A$689,0)) -> 3800
A35: Sum of net vega*vol | B35: =SUM(B41:B52) -> 2115912
A36: VCR | B36: =MAX(1,SQRT(ABS($B$35)/Inputs!$B$9/$B$34)) -> 1
A37: K | B37: =SQRT(MAX(0,SUM(D41:O52))) -> 419996.54
A38: Sum of VR | B38: =SUM(C41:C52) -> 423182.4
A39: S | B39: =MAX(-$B$37,MIN($B$37,$B$38)) -> 419996.54
A40: Tenor | B40: Net vega*vol (USD) | C40: VR | D40: =Inputs!$B$14 -> 2w | E40: =Inputs!$C$14 -> 1m | F40: =Inputs!$D$14 -> 3m | G40: =Inputs!$E$14 -> 6m | H40: =Inputs!$F$14 -> 1y | I40: =Inputs!$G$14 -> 2y | J40: =Inputs!$H$14 -> 3y | K40: =Inputs!$I$14 -> 5y | L40: =Inputs!$J$14 -> 10y | M40: =Inputs!$K$14 -> 15y | N40: =Inputs!$L$14 -> 20y | O40: =Inputs!$M$14 -> 30y
A41: =Inputs!$B$14 -> 2w | B41: =SUMIFS(Sensitivities!$I$5:$I$100,Sensitivities!$B$5:$B$100,"Risk_IRVol",Sensitivities!$C$5:$C$100,$B$32,Sensitivities!$E$5:$E$100,$A41) -> 0 | C41: =$B$3*B41*$B$36 -> 0 | D41: =SIMM_Delta!$B$8*$C$41*$C$41 -> 0 | E41: =SIMM_Delta!$C$8*$C$41*$C$42 -> 0 | F41: =SIMM_Delta!$D$8*$C$41*$C$43 -> 0 | G41: =SIMM_Delta!$E$8*$C$41*$C$44 -> 0 | H41: =SIMM_Delta!$F$8*$C$41*$C$45 -> 0 | I41: =SIMM_Delta!$G$8*$C$41*$C$46 -> 0 | J41: =SIMM_Delta!$H$8*$C$41*$C$47 -> 0 | K41: =SIMM_Delta!$I$8*$C$41*$C$48 -> 0 | L41: =SIMM_Delta!$J$8*$C$41*$C$49 -> 0 | M41: =SIMM_Delta!$K$8*$C$41*$C$50 -> 0 | N41: =SIMM_Delta!$L$8*$C$41*$C$51 -> 0 | O41: =SIMM_Delta!$M$8*$C$41*$C$52 -> 0
A42: =Inputs!$C$14 -> 1m | B42: =SUMIFS(Sensitivities!$I$5:$I$100,Sensitivities!$B$5:$B$100,"Risk_IRVol",Sensitivities!$C$5:$C$100,$B$32,Sensitivities!$E$5:$E$100,$A42) -> 0 | C42: =$B$3*B42*$B$36 -> 0 | D42: =SIMM_Delta!$B$9*$C$42*$C$41 -> 0 | E42: =SIMM_Delta!$C$9*$C$42*$C$42 -> 0 | F42: =SIMM_Delta!$D$9*$C$42*$C$43 -> 0 | G42: =SIMM_Delta!$E$9*$C$42*$C$44 -> 0 | H42: =SIMM_Delta!$F$9*$C$42*$C$45 -> 0 | I42: =SIMM_Delta!$G$9*$C$42*$C$46 -> 0 | J42: =SIMM_Delta!$H$9*$C$42*$C$47 -> 0 | K42: =SIMM_Delta!$I$9*$C$42*$C$48 -> 0 | L42: =SIMM_Delta!$J$9*$C$42*$C$49 -> 0 | M42: =SIMM_Delta!$K$9*$C$42*$C$50 -> 0 | N42: =SIMM_Delta!$L$9*$C$42*$C$51 -> 0 | O42: =SIMM_Delta!$M$9*$C$42*$C$52 -> 0
A43: =Inputs!$D$14 -> 3m | B43: =SUMIFS(Sensitivities!$I$5:$I$100,Sensitivities!$B$5:$B$100,"Risk_IRVol",Sensitivities!$C$5:$C$100,$B$32,Sensitivities!$E$5:$E$100,$A43) -> 0 | C43: =$B$3*B43*$B$36 -> 0 | D43: =SIMM_Delta!$B$10*$C$43*$C$41 -> 0 | E43: =SIMM_Delta!$C$10*$C$43*$C$42 -> 0 | F43: =SIMM_Delta!$D$10*$C$43*$C$43 -> 0 | G43: =SIMM_Delta!$E$10*$C$43*$C$44 -> 0 | H43: =SIMM_Delta!$F$10*$C$43*$C$45 -> 0 | I43: =SIMM_Delta!$G$10*$C$43*$C$46 -> 0 | J43: =SIMM_Delta!$H$10*$C$43*$C$47 -> 0 | K43: =SIMM_Delta!$I$10*$C$43*$C$48 -> 0 | L43: =SIMM_Delta!$J$10*$C$43*$C$49 -> 0 | M43: =SIMM_Delta!$K$10*$C$43*$C$50 -> 0 | N43: =SIMM_Delta!$L$10*$C$43*$C$51 -> 0 | O43: =SIMM_Delta!$M$10*$C$43*$C$52 -> 0
A44: =Inputs!$E$14 -> 6m | B44: =SUMIFS(Sensitivities!$I$5:$I$100,Sensitivities!$B$5:$B$100,"Risk_IRVol",Sensitivities!$C$5:$C$100,$B$32,Sensitivities!$E$5:$E$100,$A44) -> 0 | C44: =$B$3*B44*$B$36 -> 0 | D44: =SIMM_Delta!$B$11*$C$44*$C$41 -> 0 | E44: =SIMM_Delta!$C$11*$C$44*$C$42 -> 0 | F44: =SIMM_Delta!$D$11*$C$44*$C$43 -> 0 | G44: =SIMM_Delta!$E$11*$C$44*$C$44 -> 0 | H44: =SIMM_Delta!$F$11*$C$44*$C$45 -> 0 | I44: =SIMM_Delta!$G$11*$C$44*$C$46 -> 0 | J44: =SIMM_Delta!$H$11*$C$44*$C$47 -> 0 | K44: =SIMM_Delta!$I$11*$C$44*$C$48 -> 0 | L44: =SIMM_Delta!$J$11*$C$44*$C$49 -> 0 | M44: =SIMM_Delta!$K$11*$C$44*$C$50 -> 0 | N44: =SIMM_Delta!$L$11*$C$44*$C$51 -> 0 | O44: =SIMM_Delta!$M$11*$C$44*$C$52 -> 0
A45: =Inputs!$F$14 -> 1y | B45: =SUMIFS(Sensitivities!$I$5:$I$100,Sensitivities!$B$5:$B$100,"Risk_IRVol",Sensitivities!$C$5:$C$100,$B$32,Sensitivities!$E$5:$E$100,$A45) -> 0 | C45: =$B$3*B45*$B$36 -> 0 | D45: =SIMM_Delta!$B$12*$C$45*$C$41 -> 0 | E45: =SIMM_Delta!$C$12*$C$45*$C$42 -> 0 | F45: =SIMM_Delta!$D$12*$C$45*$C$43 -> 0 | G45: =SIMM_Delta!$E$12*$C$45*$C$44 -> 0 | H45: =SIMM_Delta!$F$12*$C$45*$C$45 -> 0 | I45: =SIMM_Delta!$G$12*$C$45*$C$46 -> 0 | J45: =SIMM_Delta!$H$12*$C$45*$C$47 -> 0 | K45: =SIMM_Delta!$I$12*$C$45*$C$48 -> 0 | L45: =SIMM_Delta!$J$12*$C$45*$C$49 -> 0 | M45: =SIMM_Delta!$K$12*$C$45*$C$50 -> 0 | N45: =SIMM_Delta!$L$12*$C$45*$C$51 -> 0 | O45: =SIMM_Delta!$M$12*$C$45*$C$52 -> 0
A46: =Inputs!$G$14 -> 2y | B46: =SUMIFS(Sensitivities!$I$5:$I$100,Sensitivities!$B$5:$B$100,"Risk_IRVol",Sensitivities!$C$5:$C$100,$B$32,Sensitivities!$E$5:$E$100,$A46) -> 0 | C46: =$B$3*B46*$B$36 -> 0 | D46: =SIMM_Delta!$B$13*$C$46*$C$41 -> 0 | E46: =SIMM_Delta!$C$13*$C$46*$C$42 -> 0 | F46: =SIMM_Delta!$D$13*$C$46*$C$43 -> 0 | G46: =SIMM_Delta!$E$13*$C$46*$C$44 -> 0 | H46: =SIMM_Delta!$F$13*$C$46*$C$45 -> 0 | I46: =SIMM_Delta!$G$13*$C$46*$C$46 -> 0 | J46: =SIMM_Delta!$H$13*$C$46*$C$47 -> 0 | K46: =SIMM_Delta!$I$13*$C$46*$C$48 -> 0 | L46: =SIMM_Delta!$J$13*$C$46*$C$49 -> 0 | M46: =SIMM_Delta!$K$13*$C$46*$C$50 -> 0 | N46: =SIMM_Delta!$L$13*$C$46*$C$51 -> 0 | O46: =SIMM_Delta!$M$13*$C$46*$C$52 -> 0
A47: =Inputs!$H$14 -> 3y | B47: =SUMIFS(Sensitivities!$I$5:$I$100,Sensitivities!$B$5:$B$100,"Risk_IRVol",Sensitivities!$C$5:$C$100,$B$32,Sensitivities!$E$5:$E$100,$A47) -> 1057956 | C47: =$B$3*B47*$B$36 -> 211591.2 | D47: =SIMM_Delta!$B$14*$C$47*$C$41 -> 0 | E47: =SIMM_Delta!$C$14*$C$47*$C$42 -> 0 | F47: =SIMM_Delta!$D$14*$C$47*$C$43 -> 0 | G47: =SIMM_Delta!$E$14*$C$47*$C$44 -> 0 | H47: =SIMM_Delta!$F$14*$C$47*$C$45 -> 0 | I47: =SIMM_Delta!$G$14*$C$47*$C$46 -> 0 | J47: =SIMM_Delta!$H$14*$C$47*$C$47 -> 4.4770837e+10 | K47: =SIMM_Delta!$I$14*$C$47*$C$48 -> 4.3427712e+10 | L47: =SIMM_Delta!$J$14*$C$47*$C$49 -> 0 | M47: =SIMM_Delta!$K$14*$C$47*$C$50 -> 0 | N47: =SIMM_Delta!$L$14*$C$47*$C$51 -> 0 | O47: =SIMM_Delta!$M$14*$C$47*$C$52 -> 0
A48: =Inputs!$I$14 -> 5y | B48: =SUMIFS(Sensitivities!$I$5:$I$100,Sensitivities!$B$5:$B$100,"Risk_IRVol",Sensitivities!$C$5:$C$100,$B$32,Sensitivities!$E$5:$E$100,$A48) -> 1057956 | C48: =$B$3*B48*$B$36 -> 211591.2 | D48: =SIMM_Delta!$B$15*$C$48*$C$41 -> 0 | E48: =SIMM_Delta!$C$15*$C$48*$C$42 -> 0 | F48: =SIMM_Delta!$D$15*$C$48*$C$43 -> 0 | G48: =SIMM_Delta!$E$15*$C$48*$C$44 -> 0 | H48: =SIMM_Delta!$F$15*$C$48*$C$45 -> 0 | I48: =SIMM_Delta!$G$15*$C$48*$C$46 -> 0 | J48: =SIMM_Delta!$H$15*$C$48*$C$47 -> 4.3427712e+10 | K48: =SIMM_Delta!$I$15*$C$48*$C$48 -> 4.4770837e+10 | L48: =SIMM_Delta!$J$15*$C$48*$C$49 -> 0 | M48: =SIMM_Delta!$K$15*$C$48*$C$50 -> 0 | N48: =SIMM_Delta!$L$15*$C$48*$C$51 -> 0 | O48: =SIMM_Delta!$M$15*$C$48*$C$52 -> 0
A49: =Inputs!$J$14 -> 10y | B49: =SUMIFS(Sensitivities!$I$5:$I$100,Sensitivities!$B$5:$B$100,"Risk_IRVol",Sensitivities!$C$5:$C$100,$B$32,Sensitivities!$E$5:$E$100,$A49) -> 0 | C49: =$B$3*B49*$B$36 -> 0 | D49: =SIMM_Delta!$B$16*$C$49*$C$41 -> 0 | E49: =SIMM_Delta!$C$16*$C$49*$C$42 -> 0 | F49: =SIMM_Delta!$D$16*$C$49*$C$43 -> 0 | G49: =SIMM_Delta!$E$16*$C$49*$C$44 -> 0 | H49: =SIMM_Delta!$F$16*$C$49*$C$45 -> 0 | I49: =SIMM_Delta!$G$16*$C$49*$C$46 -> 0 | J49: =SIMM_Delta!$H$16*$C$49*$C$47 -> 0 | K49: =SIMM_Delta!$I$16*$C$49*$C$48 -> 0 | L49: =SIMM_Delta!$J$16*$C$49*$C$49 -> 0 | M49: =SIMM_Delta!$K$16*$C$49*$C$50 -> 0 | N49: =SIMM_Delta!$L$16*$C$49*$C$51 -> 0 | O49: =SIMM_Delta!$M$16*$C$49*$C$52 -> 0
A50: =Inputs!$K$14 -> 15y | B50: =SUMIFS(Sensitivities!$I$5:$I$100,Sensitivities!$B$5:$B$100,"Risk_IRVol",Sensitivities!$C$5:$C$100,$B$32,Sensitivities!$E$5:$E$100,$A50) -> 0 | C50: =$B$3*B50*$B$36 -> 0 | D50: =SIMM_Delta!$B$17*$C$50*$C$41 -> 0 | E50: =SIMM_Delta!$C$17*$C$50*$C$42 -> 0 | F50: =SIMM_Delta!$D$17*$C$50*$C$43 -> 0 | G50: =SIMM_Delta!$E$17*$C$50*$C$44 -> 0 | H50: =SIMM_Delta!$F$17*$C$50*$C$45 -> 0 | I50: =SIMM_Delta!$G$17*$C$50*$C$46 -> 0 | J50: =SIMM_Delta!$H$17*$C$50*$C$47 -> 0 | K50: =SIMM_Delta!$I$17*$C$50*$C$48 -> 0 | L50: =SIMM_Delta!$J$17*$C$50*$C$49 -> 0 | M50: =SIMM_Delta!$K$17*$C$50*$C$50 -> 0 | N50: =SIMM_Delta!$L$17*$C$50*$C$51 -> 0 | O50: =SIMM_Delta!$M$17*$C$50*$C$52 -> 0
A51: =Inputs!$L$14 -> 20y | B51: =SUMIFS(Sensitivities!$I$5:$I$100,Sensitivities!$B$5:$B$100,"Risk_IRVol",Sensitivities!$C$5:$C$100,$B$32,Sensitivities!$E$5:$E$100,$A51) -> 0 | C51: =$B$3*B51*$B$36 -> 0 | D51: =SIMM_Delta!$B$18*$C$51*$C$41 -> 0 | E51: =SIMM_Delta!$C$18*$C$51*$C$42 -> 0 | F51: =SIMM_Delta!$D$18*$C$51*$C$43 -> 0 | G51: =SIMM_Delta!$E$18*$C$51*$C$44 -> 0 | H51: =SIMM_Delta!$F$18*$C$51*$C$45 -> 0 | I51: =SIMM_Delta!$G$18*$C$51*$C$46 -> 0 | J51: =SIMM_Delta!$H$18*$C$51*$C$47 -> 0 | K51: =SIMM_Delta!$I$18*$C$51*$C$48 -> 0 | L51: =SIMM_Delta!$J$18*$C$51*$C$49 -> 0 | M51: =SIMM_Delta!$K$18*$C$51*$C$50 -> 0 | N51: =SIMM_Delta!$L$18*$C$51*$C$51 -> 0 | O51: =SIMM_Delta!$M$18*$C$51*$C$52 -> 0
A52: =Inputs!$M$14 -> 30y | B52: =SUMIFS(Sensitivities!$I$5:$I$100,Sensitivities!$B$5:$B$100,"Risk_IRVol",Sensitivities!$C$5:$C$100,$B$32,Sensitivities!$E$5:$E$100,$A52) -> 0 | C52: =$B$3*B52*$B$36 -> 0 | D52: =SIMM_Delta!$B$19*$C$52*$C$41 -> 0 | E52: =SIMM_Delta!$C$19*$C$52*$C$42 -> 0 | F52: =SIMM_Delta!$D$19*$C$52*$C$43 -> 0 | G52: =SIMM_Delta!$E$19*$C$52*$C$44 -> 0 | H52: =SIMM_Delta!$F$19*$C$52*$C$45 -> 0 | I52: =SIMM_Delta!$G$19*$C$52*$C$46 -> 0 | J52: =SIMM_Delta!$H$19*$C$52*$C$47 -> 0 | K52: =SIMM_Delta!$I$19*$C$52*$C$48 -> 0 | L52: =SIMM_Delta!$J$19*$C$52*$C$49 -> 0 | M52: =SIMM_Delta!$K$19*$C$52*$C$50 -> 0 | N52: =SIMM_Delta!$L$19*$C$52*$C$51 -> 0 | O52: =SIMM_Delta!$M$19*$C$52*$C$52 -> 0
A56: Currency | B56: =Inputs!$D$13 -> GBP
A57: Concentration group | B57: =IF(ISNUMBER(MATCH(Inputs!$B$4&"|IR|ct_group_member|regular_well_traded|"&$B$56,Parameters!$A$5:$A$689,0)),"regular_well_traded",IF(ISNUMBER(MATCH(Inputs!$B$4&"|IR|ct_group_member|regular_less_well_traded|"&$B$56,Parameters!$A$5:$A$689,0)),"regular_less_well_traded",IF(ISNUMBER(MATCH(Inputs!$B$4&"|IR|ct_group_member|low|"&$B$56,Parameters!$A$5:$A$689,0)),"low","high"))) -> regular_well_traded
A58: Vega threshold (USD mm) | B58: =INDEX(Parameters!$G$5:$G$689,MATCH(Inputs!$B$4&"|IR|"&"vega_ct"&"|"&$B$57&"|"&"",Parameters!$A$5:$A$689,0)) -> 3800
A59: Sum of net vega*vol | B59: =SUM(B65:B76) -> -1031428.1
A60: VCR | B60: =MAX(1,SQRT(ABS($B$59)/Inputs!$B$9/$B$58)) -> 1
A61: K | B61: =SQRT(MAX(0,SUM(D65:O76))) -> 206285.63
A62: Sum of VR | B62: =SUM(C65:C76) -> -206285.63
A63: S | B63: =MAX(-$B$61,MIN($B$61,$B$62)) -> -206285.63
A64: Tenor | B64: Net vega*vol (USD) | C64: VR | D64: =Inputs!$B$14 -> 2w | E64: =Inputs!$C$14 -> 1m | F64: =Inputs!$D$14 -> 3m | G64: =Inputs!$E$14 -> 6m | H64: =Inputs!$F$14 -> 1y | I64: =Inputs!$G$14 -> 2y | J64: =Inputs!$H$14 -> 3y | K64: =Inputs!$I$14 -> 5y | L64: =Inputs!$J$14 -> 10y | M64: =Inputs!$K$14 -> 15y | N64: =Inputs!$L$14 -> 20y | O64: =Inputs!$M$14 -> 30y
A65: =Inputs!$B$14 -> 2w | B65: =SUMIFS(Sensitivities!$I$5:$I$100,Sensitivities!$B$5:$B$100,"Risk_IRVol",Sensitivities!$C$5:$C$100,$B$56,Sensitivities!$E$5:$E$100,$A65) -> 0 | C65: =$B$3*B65*$B$60 -> 0 | D65: =SIMM_Delta!$B$8*$C$65*$C$65 -> 0 | E65: =SIMM_Delta!$C$8*$C$65*$C$66 -> 0 | F65: =SIMM_Delta!$D$8*$C$65*$C$67 -> 0 | G65: =SIMM_Delta!$E$8*$C$65*$C$68 -> 0 | H65: =SIMM_Delta!$F$8*$C$65*$C$69 -> 0 | I65: =SIMM_Delta!$G$8*$C$65*$C$70 -> 0 | J65: =SIMM_Delta!$H$8*$C$65*$C$71 -> 0 | K65: =SIMM_Delta!$I$8*$C$65*$C$72 -> 0 | L65: =SIMM_Delta!$J$8*$C$65*$C$73 -> 0 | M65: =SIMM_Delta!$K$8*$C$65*$C$74 -> 0 | N65: =SIMM_Delta!$L$8*$C$65*$C$75 -> 0 | O65: =SIMM_Delta!$M$8*$C$65*$C$76 -> 0
A66: =Inputs!$C$14 -> 1m | B66: =SUMIFS(Sensitivities!$I$5:$I$100,Sensitivities!$B$5:$B$100,"Risk_IRVol",Sensitivities!$C$5:$C$100,$B$56,Sensitivities!$E$5:$E$100,$A66) -> 0 | C66: =$B$3*B66*$B$60 -> 0 | D66: =SIMM_Delta!$B$9*$C$66*$C$65 -> 0 | E66: =SIMM_Delta!$C$9*$C$66*$C$66 -> 0 | F66: =SIMM_Delta!$D$9*$C$66*$C$67 -> 0 | G66: =SIMM_Delta!$E$9*$C$66*$C$68 -> 0 | H66: =SIMM_Delta!$F$9*$C$66*$C$69 -> 0 | I66: =SIMM_Delta!$G$9*$C$66*$C$70 -> 0 | J66: =SIMM_Delta!$H$9*$C$66*$C$71 -> 0 | K66: =SIMM_Delta!$I$9*$C$66*$C$72 -> 0 | L66: =SIMM_Delta!$J$9*$C$66*$C$73 -> 0 | M66: =SIMM_Delta!$K$9*$C$66*$C$74 -> 0 | N66: =SIMM_Delta!$L$9*$C$66*$C$75 -> 0 | O66: =SIMM_Delta!$M$9*$C$66*$C$76 -> 0
A67: =Inputs!$D$14 -> 3m | B67: =SUMIFS(Sensitivities!$I$5:$I$100,Sensitivities!$B$5:$B$100,"Risk_IRVol",Sensitivities!$C$5:$C$100,$B$56,Sensitivities!$E$5:$E$100,$A67) -> 0 | C67: =$B$3*B67*$B$60 -> 0 | D67: =SIMM_Delta!$B$10*$C$67*$C$65 -> 0 | E67: =SIMM_Delta!$C$10*$C$67*$C$66 -> 0 | F67: =SIMM_Delta!$D$10*$C$67*$C$67 -> 0 | G67: =SIMM_Delta!$E$10*$C$67*$C$68 -> 0 | H67: =SIMM_Delta!$F$10*$C$67*$C$69 -> 0 | I67: =SIMM_Delta!$G$10*$C$67*$C$70 -> 0 | J67: =SIMM_Delta!$H$10*$C$67*$C$71 -> 0 | K67: =SIMM_Delta!$I$10*$C$67*$C$72 -> 0 | L67: =SIMM_Delta!$J$10*$C$67*$C$73 -> 0 | M67: =SIMM_Delta!$K$10*$C$67*$C$74 -> 0 | N67: =SIMM_Delta!$L$10*$C$67*$C$75 -> 0 | O67: =SIMM_Delta!$M$10*$C$67*$C$76 -> 0
A68: =Inputs!$E$14 -> 6m | B68: =SUMIFS(Sensitivities!$I$5:$I$100,Sensitivities!$B$5:$B$100,"Risk_IRVol",Sensitivities!$C$5:$C$100,$B$56,Sensitivities!$E$5:$E$100,$A68) -> 0 | C68: =$B$3*B68*$B$60 -> 0 | D68: =SIMM_Delta!$B$11*$C$68*$C$65 -> 0 | E68: =SIMM_Delta!$C$11*$C$68*$C$66 -> 0 | F68: =SIMM_Delta!$D$11*$C$68*$C$67 -> 0 | G68: =SIMM_Delta!$E$11*$C$68*$C$68 -> 0 | H68: =SIMM_Delta!$F$11*$C$68*$C$69 -> 0 | I68: =SIMM_Delta!$G$11*$C$68*$C$70 -> 0 | J68: =SIMM_Delta!$H$11*$C$68*$C$71 -> 0 | K68: =SIMM_Delta!$I$11*$C$68*$C$72 -> 0 | L68: =SIMM_Delta!$J$11*$C$68*$C$73 -> 0 | M68: =SIMM_Delta!$K$11*$C$68*$C$74 -> 0 | N68: =SIMM_Delta!$L$11*$C$68*$C$75 -> 0 | O68: =SIMM_Delta!$M$11*$C$68*$C$76 -> 0
A69: =Inputs!$F$14 -> 1y | B69: =SUMIFS(Sensitivities!$I$5:$I$100,Sensitivities!$B$5:$B$100,"Risk_IRVol",Sensitivities!$C$5:$C$100,$B$56,Sensitivities!$E$5:$E$100,$A69) -> 0 | C69: =$B$3*B69*$B$60 -> 0 | D69: =SIMM_Delta!$B$12*$C$69*$C$65 -> 0 | E69: =SIMM_Delta!$C$12*$C$69*$C$66 -> 0 | F69: =SIMM_Delta!$D$12*$C$69*$C$67 -> 0 | G69: =SIMM_Delta!$E$12*$C$69*$C$68 -> 0 | H69: =SIMM_Delta!$F$12*$C$69*$C$69 -> 0 | I69: =SIMM_Delta!$G$12*$C$69*$C$70 -> 0 | J69: =SIMM_Delta!$H$12*$C$69*$C$71 -> 0 | K69: =SIMM_Delta!$I$12*$C$69*$C$72 -> 0 | L69: =SIMM_Delta!$J$12*$C$69*$C$73 -> 0 | M69: =SIMM_Delta!$K$12*$C$69*$C$74 -> 0 | N69: =SIMM_Delta!$L$12*$C$69*$C$75 -> 0 | O69: =SIMM_Delta!$M$12*$C$69*$C$76 -> 0
A70: =Inputs!$G$14 -> 2y | B70: =SUMIFS(Sensitivities!$I$5:$I$100,Sensitivities!$B$5:$B$100,"Risk_IRVol",Sensitivities!$C$5:$C$100,$B$56,Sensitivities!$E$5:$E$100,$A70) -> 0 | C70: =$B$3*B70*$B$60 -> 0 | D70: =SIMM_Delta!$B$13*$C$70*$C$65 -> 0 | E70: =SIMM_Delta!$C$13*$C$70*$C$66 -> 0 | F70: =SIMM_Delta!$D$13*$C$70*$C$67 -> 0 | G70: =SIMM_Delta!$E$13*$C$70*$C$68 -> 0 | H70: =SIMM_Delta!$F$13*$C$70*$C$69 -> 0 | I70: =SIMM_Delta!$G$13*$C$70*$C$70 -> 0 | J70: =SIMM_Delta!$H$13*$C$70*$C$71 -> 0 | K70: =SIMM_Delta!$I$13*$C$70*$C$72 -> 0 | L70: =SIMM_Delta!$J$13*$C$70*$C$73 -> 0 | M70: =SIMM_Delta!$K$13*$C$70*$C$74 -> 0 | N70: =SIMM_Delta!$L$13*$C$70*$C$75 -> 0 | O70: =SIMM_Delta!$M$13*$C$70*$C$76 -> 0
